Workbook

Sheet Dashboard
B2: Global Top Companies Intelligence Database
B3: Phase 1: Top 50 Economies | Executive Dashboard
B4: Last Updated: 2026-07-18
B6: Coverage Summary | E6: Companies per Country
B7: Total Countries Covered | C7: 50 | E7: United States | F7: =COUNTIF('Global Master Database'!$C$2:$C$266,E7) -> 0
B8: Total Companies Profiled | C8: 264 | E8: China | F8: =COUNTIF('Global Master Database'!$C$2:$C$266,E8) -> 0
B9: Total Industries Represented | C9: 56 | E9: Japan | F9: =COUNTIF('Global Master Database'!$C$2:$C$266,E9) -> 0
B10: Fields per Company | C10: 22 | E10: Germany | F10: =COUNTIF('Global Master Database'!$C$2:$C$266,E10) -> 0
B11: Fully Verified Fields | C11: 17 of 22 (stable facts) | E11: India | F11: =COUNTIF('Global Master Database'!$C$2:$C$266,E11) -> 0
B12: Fields Pending Live Verification | C12: 5 of 22 (CEO, financials, rank) | E12: United Kingdom | F12: =COUNTIF('Global Master Database'!$C$2:$C$266,E12) -> 0
E13: France | F13: =COUNTIF('Global Master Database'!$C$2:$C$266,E13) -> 0
B14: Industry Distribution (# Companies) | E14: Italy | F14: =COUNTIF('Global Master Database'!$C$2:$C$266,E14) -> 0
B15: Aerospace | C15: =COUNTIF('Global Master Database'!$E$2:$E$266,B15) -> 1 | E15: Brazil | F15: =COUNTIF('Global Master Database'!$C$2:$C$266,E15) -> 0
B16: Agriculture | C16: =COUNTIF('Global Master Database'!$E$2:$E$266,B16) -> 1 | E16: Canada | F16: =COUNTIF('Global Master Database'!$C$2:$C$266,E16) -> 0
B17: Automotive | C17: =COUNTIF('Global Master Database'!$E$2:$E$266,B17) -> 9 | E17: Russia | F17: =COUNTIF('Global Master Database'!$C$2:$C$266,E17) -> 0
B18: Aviation | C18: =COUNTIF('Global Master Database'!$E$2:$E$266,B18) -> 6 | E18: South Korea | F18: =COUNTIF('Global Master Database'!$C$2:$C$266,E18) -> 0
B19: Aviation/Infrastructure | C19: =COUNTIF('Global Master Database'!$E$2:$E$266,B19) -> 1 | E19: Australia | F19: =COUNTIF('Global Master Database'!$C$2:$C$266,E19) -> 0
B20: Banking | C20: =COUNTIF('Global Master Database'!$E$2:$E$266,B20) -> 63 | E20: Spain | F20: =COUNTIF('Global Master Database'!$C$2:$C$266,E20) -> 0
B21: Beverages | C21: =COUNTIF('Global Master Database'!$E$2:$E$266,B21) -> 4 | E21: Mexico | F21: =COUNTIF('Global Master Database'!$C$2:$C$266,E21) -> 0
B22: Beverages/Retail | C22: =COUNTIF('Global Master Database'!$E$2:$E$266,B22) -> 1 | E22: Indonesia | F22: =COUNTIF('Global Master Database'!$C$2:$C$266,E22) -> 0
B23: Cement | C23: =COUNTIF('Global Master Database'!$E$2:$E$266,B23) -> 1 | E23: Netherlands | F23: =COUNTIF('Global Master Database'!$C$2:$C$266,E23) -> 0
B24: Chemicals | C24: =COUNTIF('Global Master Database'!$E$2:$E$266,B24) -> 4 | E24: Saudi Arabia | F24: =COUNTIF('Global Master Database'!$C$2:$C$266,E24) -> 0
B25: Chemicals/Energy | C25: =COUNTIF('Global Master Database'!$E$2:$E$266,B25) -> 1 | E25: Turkey | F25: =COUNTIF('Global Master Database'!$C$2:$C$266,E25) -> 0
B26: Chemicals/Manufacturing | C26: =COUNTIF('Global Master Database'!$E$2:$E$266,B26) -> 1 | E26: Switzerland | F26: =COUNTIF('Global Master Database'!$C$2:$C$266,E26) -> 0
... B56: Pharmaceuticals | C56: =COUNTIF('Global Master Database'!$E$2:$E$266,B56) -> 7 | E56: Qatar | F56: =COUNTIF('Global Master Database'!$C$2:$C$266,E56) -> 0
B57: Pharmaceuticals/Conglomerate | C57: =COUNTIF('Global Master Database'!$E$2:$E$266,B57) -> 1
B58: Renewable Energy | C58: =COUNTIF('Global Master Database'!$E$2:$E$266,B58) -> 1
B59: Retail | C59: =COUNTIF('Global Master Database'!$E$2:$E$266,B59) -> 5
B60: Semiconductors | C60: =COUNTIF('Global Master Database'!$E$2:$E$266,B60) -> 4
B61: Shipping | C61: =COUNTIF('Global Master Database'!$E$2:$E$266,B61) -> 1
B62: Software | C62: =COUNTIF('Global Master Database'!$E$2:$E$266,B62) -> 1
B63: Steel | C63: =COUNTIF('Global Master Database'!$E$2:$E$266,B63) -> 4
B64: Technology | C64: =COUNTIF('Global Master Database'!$E$2:$E$266,B64) -> 5
B65: Technology/Media | C65: =COUNTIF('Global Master Database'!$E$2:$E$266,B65) -> 1
B66: Telecommunications | C66: =COUNTIF('Global Master Database'!$E$2:$E$266,B66) -> 20
B67: Telecommunications/Investment | C67: =COUNTIF('Global Master Database'!$E$2:$E$266,B67) -> 1
B68: Telecommunications/Technology | C68: =COUNTIF('Global Master Database'!$E$2:$E$266,B68) -> 1
... B70: Utilities/Energy | C70: =COUNTIF('Global Master Database'!$E$2:$E$266,B70) -> 1
B72: Executive Summary
B73: This workbook profiles 264 leading companies across the world's Top 50 economies (by GDP), selected for revenue scale, market capitalization, employment, and strategic national importance. Company identity, HQ, industry classification, and founding data are drawn from stable, well-documented public facts. CEO names and financial figures (revenue, net income, market cap, Fortune Global 500 rank) are marked 'Verification Pending' rather than estimated, since these change quarterly/annually and were not confirmed against a live source at build time. Recommended next step: run a targeted verification pass (financial filings, investor relations pages) before using pending fields in investment or academic analysis. This is Phase 1 of a workbook designed to scale to all ~195 countries and 10,000+ companies.

Sheet Country Index
A1: Country Index
A2: Click a country to jump to its worksheet. Phase 1 covers the Top 50 economies by GDP.
A4: # | B4: Country | C4: # Companies
A5: 1 | B5: United States | C5: 8
A6: 2 | B6: China | C6: 8
A7: 3 | B7: Japan | C7: 7
A8: 4 | B8: Germany | C8: 7
A9: 5 | B9: India | C9: 7
A10: 6 | B10: United Kingdom | C10: 6
A11: 7 | B11: France | C11: 6
A12: 8 | B12: Italy | C12: 5
A13: 9 | B13: Brazil | C13: 5
A14: 10 | B14: Canada | C14: 5
A15: 11 | B15: Russia | C15: 5
A16: 12 | B16: South Korea | C16: 5
... A54: 50 | B54: Qatar | C54: 5

Sheet Global Master Database
A1: Rank | B1: Company Name | C1: Country | D1: HQ City | E1: Industry | F1: Sector | G1: Company Type | H1: Founded Year | I1: CEO | J1: Official Website | K1: Business Description | L1: Main Products/Services | M1: Stock Exchange | N1: Ticker Symbol | O1: Annual Revenue (USD) | P1: Net Income (USD) | Q1: Market Cap (USD) | R1: Fortune Global 500 Rank | S1: Parent Company | T1: Data Source | U1: Verification Status | V1: Last Updated
A2: United States | B2: Apple Inc. | C2: 1 | D2: Cupertino, CA | E2: Technology | F2: Consumer Electronics | G2: Public | H2: 1976 | I2: Verification Pending | J2: https://www.apple.com | K2: Designs and sells consumer electronics, software, and services including iPhone, Mac, and iCloud. | L2: Designs and sells consumer electronics, software, and services including iPhone, Mac, and iCloud | M2: NASDAQ | N2: AAPL | O2: Verification Pending | P2: Verification Pending | Q2: Verification Pending | R2: Verification Pending | S2: N/A | T2: Company knowledge base (stable facts) | U2: Needs financial/leadership verification | V2: 2026-07-18
A3: United States | B3: Microsoft Corporation | C3: 2 | D3: Redmond, WA | E3: Technology | F3: Software & Cloud Computing | G3: Public | H3: 1975 | I3: Verification Pending | J3: https://www.microsoft.com | K3: Develops software, cloud services (Azure), and hardware including Windows and Office. | L3: Develops software, cloud services (Azure), and hardware including Windows and Office | M3: NASDAQ | N3: MSFT | O3: Verification Pending | P3: Verification Pending | Q3: Verification Pending | R3: Verification Pending | S3: N/A | T3: Company knowledge base (stable facts) | U3: Needs financial/leadership verification | V3: 2026-07-18
A4: United States | B4: Amazon.com, Inc. | C4: 3 | D4: Seattle, WA | E4: E-commerce/Cloud Computing | F4: Retail & Cloud Infrastructure | G4: Public | H4: 1994 | I4: Verification Pending | J4: https://www.amazon.com | K4: Global e-commerce and cloud computing (AWS) company. | L4: Global e-commerce and cloud computing (AWS) company | M4: NASDAQ | N4: AMZN | O4: Verification Pending | P4: Verification Pending | Q4: Verification Pending | R4: Verification Pending | S4: N/A | T4: Company knowledge base (stable facts) | U4: Needs financial/leadership verification | V4: 2026-07-18
A5: United States | B5: Alphabet Inc. (Google) | C5: 4 | D5: Mountain View, CA | E5: Technology | F5: Internet Services & AI | G5: Public | H5: 1998 | I5: Verification Pending | J5: https://abc.xyz | K5: Parent of Google; search, advertising, cloud, and AI research. | L5: Parent of Google; search, advertising, cloud, and AI research | M5: NASDAQ | N5: GOOGL | O5: Verification Pending | P5: Verification Pending | Q5: Verification Pending | R5: Verification Pending | S5: N/A | T5: Company knowledge base (stable facts) | U5: Needs financial/leadership verification | V5: 2026-07-18
A6: United States | B6: ExxonMobil | C6: 5 | D6: Spring, TX | E6: Oil & Gas | F6: Energy | G6: Public | H6: 1999 | I6: Verification Pending | J6: https://corporate.exxonmobil.com | K6: Integrated oil and gas exploration, production, and refining company. | L6: Integrated oil and gas exploration, production, and refining company | M6: NYSE | N6: XOM | O6: Verification Pending | P6: Verification Pending | Q6: Verification Pending | R6: Verification Pending | S6: N/A | T6: Company knowledge base (stable facts) | U6: Needs financial/leadership verification | V6: 2026-07-18
A7: United States | B7: JPMorgan Chase & Co. | C7: 6 | D7: New York, NY | E7: Banking | F7: Financial Services | G7: Public | H7: 1799 | I7: Verification Pending | J7: https://www.jpmorganchase.com | K7: Largest U.S. bank by assets, offering investment banking and consumer banking. | L7: Largest U | M7: NYSE | N7: JPM | O7: Verification Pending | P7: Verification Pending | Q7: Verification Pending | R7: Verification Pending | S7: N/A | T7: Company knowledge base (stable facts) | U7: Needs financial/leadership verification | V7: 2026-07-18
A8: United States | B8: Berkshire Hathaway | C8: 7 | D8: Omaha, NE | E8: Conglomerate/Insurance | F8: Financial Services | G8: Public | H8: 1839 | I8: Verification Pending | J8: https://www.berkshirehathaway.com | K8: Diversified holding company with insurance, rail, energy, and equity investments. | L8: Diversified holding company with insurance, rail, energy, and equity investments | M8: NYSE | N8: BRK.A | O8: Verification Pending | P8: Verification Pending | Q8: Verification Pending | R8: Verification Pending | S8: N/A | T8: Company knowledge base (stable facts) | U8: Needs financial/leadership verification | V8: 2026-07-18
A9: United States | B9: UnitedHealth Group | C9: 8 | D9: Minnetonka, MN | E9: Healthcare | F9: Health Insurance & Services | G9: Public | H9: 1977 | I9: Verification Pending | J9: https://www.unitedhealthgroup.com | K9: Largest U.S. health insurer and healthcare services provider. | L9: Largest U | M9: NYSE | N9: UNH | O9: Verification Pending | P9: Verification Pending | Q9: Verification Pending | R9: Verification Pending | S9: N/A | T9: Company knowledge base (stable facts) | U9: Needs financial/leadership verification | V9: 2026-07-18
A10: China | B10: State Grid Corporation of China | C10: 1 | D10: Beijing | E10: Utilities | F10: Electric Power Transmission | G10: State-Owned | H10: 2002 | I10: Verification Pending | J10: https://www.sgcc.com.cn | K10: World's largest electric utility, operating national grid infrastructure. | L10: World's largest electric utility, operating national grid infrastructure | M10: State-owned (not listed) | N10: N/A | O10: Verification Pending | P10: Verification Pending | Q10: Verification Pending | R10: Verification Pending | S10: N/A | T10: Company knowledge base (stable facts) | U10: Needs financial/leadership verification | V10: 2026-07-18
A11: China | B11: Sinopec Group | C11: 2 | D11: Beijing | E11: Oil & Gas | F11: Energy | G11: State-Owned | H11: 1998 | I11: Verification Pending | J11: https://www.sinopecgroup.com | K11: Integrated energy and chemical company; refining and petrochemicals. | L11: Integrated energy and chemical company; refining and petrochemicals | M11: SSE/HKEX | N11: 600028 | O11: Verification Pending | P11: Verification Pending | Q11: Verification Pending | R11: Verification Pending | S11: N/A | T11: Company knowledge base (stable facts) | U11: Needs financial/leadership verification | V11: 2026-07-18
A12: China | B12: PetroChina / CNPC | C12: 3 | D12: Beijing | E12: Oil & Gas | F12: Energy | G12: State-Owned | H12: 1999 | I12: Verification Pending | J12: https://www.petrochina.com.cn | K12: Major oil and gas exploration and production company. | L12: Major oil and gas exploration and production company | M12: SSE/HKEX | N12: 601857 | O12: Verification Pending | P12: Verification Pending | Q12: Verification Pending | R12: Verification Pending | S12: N/A | T12: Company knowledge base (stable facts) | U12: Needs financial/leadership verification | V12: 2026-07-18
A13: China | B13: Industrial and Commercial Bank of China (ICBC) | C13: 4 | D13: Beijing | E13: Banking | F13: Financial Services | G13: State-Owned | H13: 1984 | I13: Verification Pending | J13: https://www.icbc.com.cn | K13: World's largest bank by total assets. | L13: World's largest bank by total assets | M13: SSE/HKEX | N13: 601398 | O13: Verification Pending | P13: Verification Pending | Q13: Verification Pending | R13: Verification Pending | S13: N/A | T13: Company knowledge base (stable facts) | U13: Needs financial/leadership verification | V13: 2026-07-18
... A265: Qatar | B265: Qatar Airways | C265: 5 | D265: Doha | E265: Aviation | F265: Airlines | G265: State-Owned | H265: 1993 | I265: Verification Pending | J265: https://www.qatarairways.com | K265: Qatar's state-owned flag carrier, major global airline. | L265: Qatar's state-owned flag carrier, major global airline | M265: State-owned | N265: N/A | O265: Verification Pending | P265: Verification Pending | Q265: Verification Pending | R265: Verification Pending | S265: N/A | T265: Company knowledge base (stable facts) | U265: Needs financial/leadership verification | V265: 2026-07-18

Sheet United States
A1: Rank | B1: Company Name | C1: Country | D1: HQ City | E1: Industry | F1: Sector | G1: Company Type | H1: Founded Year | I1: CEO | J1: Official Website | K1: Business Description | L1: Main Products/Services | M1: Stock Exchange | N1: Ticker Symbol | O1: Annual Revenue (USD) | P1: Net Income (USD) | Q1: Market Cap (USD) | R1: Fortune Global 500 Rank | S1: Parent Company | T1: Data Source | U1: Verification Status | V1: Last Updated
A2: United States | B2: Apple Inc. | C2: 1 | D2: Cupertino, CA | E2: Technology | F2: Consumer Electronics | G2: Public | H2: 1976 | I2: Verification Pending | J2: https://www.apple.com | K2: Designs and sells consumer electronics, software, and services including iPhone, Mac, and iCloud. | L2: Designs and sells consumer electronics, software, and services including iPhone, Mac, and iCloud | M2: NASDAQ | N2: AAPL | O2: Verification Pending | P2: Verification Pending | Q2: Verification Pending | R2: Verification Pending | S2: N/A | T2: Company knowledge base (stable facts) | U2: Needs financial/leadership verification | V2: 2026-07-18
A3: United States | B3: Microsoft Corporation | C3: 2 | D3: Redmond, WA | E3: Technology | F3: Software & Cloud Computing | G3: Public | H3: 1975 | I3: Verification Pending | J3: https://www.microsoft.com | K3: Develops software, cloud services (Azure), and hardware including Windows and Office. | L3: Develops software, cloud services (Azure), and hardware including Windows and Office | M3: NASDAQ | N3: MSFT | O3: Verification Pending | P3: Verification Pending | Q3: Verification Pending | R3: Verification Pending | S3: N/A | T3: Company knowledge base (stable facts) | U3: Needs financial/leadership verification | V3: 2026-07-18
A4: United States | B4: Amazon.com, Inc. | C4: 3 | D4: Seattle, WA | E4: E-commerce/Cloud Computing | F4: Retail & Cloud Infrastructure | G4: Public | H4: 1994 | I4: Verification Pending | J4: https://www.amazon.com | K4: Global e-commerce and cloud computing (AWS) company. | L4: Global e-commerce and cloud computing (AWS) company | M4: NASDAQ | N4: AMZN | O4: Verification Pending | P4: Verification Pending | Q4: Verification Pending | R4: Verification Pending | S4: N/A | T4: Company knowledge base (stable facts) | U4: Needs financial/leadership verification | V4: 2026-07-18
A5: United States | B5: Alphabet Inc. (Google) | C5: 4 | D5: Mountain View, CA | E5: Technology | F5: Internet Services & AI | G5: Public | H5: 1998 | I5: Verification Pending | J5: https://abc.xyz | K5: Parent of Google; search, advertising, cloud, and AI research. | L5: Parent of Google; search, advertising, cloud, and AI research | M5: NASDAQ | N5: GOOGL | O5: Verification Pending | P5: Verification Pending | Q5: Verification Pending | R5: Verification Pending | S5: N/A | T5: Company knowledge base (stable facts) | U5: Needs financial/leadership verification | V5: 2026-07-18
A6: United States | B6: ExxonMobil | C6: 5 | D6: Spring, TX | E6: Oil & Gas | F6: Energy | G6: Public | H6: 1999 | I6: Verification Pending | J6: https://corporate.exxonmobil.com | K6: Integrated oil and gas exploration, production, and refining company. | L6: Integrated oil and gas exploration, production, and refining company | M6: NYSE | N6: XOM | O6: Verification Pending | P6: Verification Pending | Q6: Verification Pending | R6: Verification Pending | S6: N/A | T6: Company knowledge base (stable facts) | U6: Needs financial/leadership verification | V6: 2026-07-18
A7: United States | B7: JPMorgan Chase & Co. | C7: 6 | D7: New York, NY | E7: Banking | F7: Financial Services | G7: Public | H7: 1799 | I7: Verification Pending | J7: https://www.jpmorganchase.com | K7: Largest U.S. bank by assets, offering investment banking and consumer banking. | L7: Largest U | M7: NYSE | N7: JPM | O7: Verification Pending | P7: Verification Pending | Q7: Verification Pending | R7: Verification Pending | S7: N/A | T7: Company knowledge base (stable facts) | U7: Needs financial/leadership verification | V7: 2026-07-18
A8: United States | B8: Berkshire Hathaway | C8: 7 | D8: Omaha, NE | E8: Conglomerate/Insurance | F8: Financial Services | G8: Public | H8: 1839 | I8: Verification Pending | J8: https://www.berkshirehathaway.com | K8: Diversified holding company with insurance, rail, energy, and equity investments. | L8: Diversified holding company with insurance, rail, energy, and equity investments | M8: NYSE | N8: BRK.A | O8: Verification Pending | P8: Verification Pending | Q8: Verification Pending | R8: Verification Pending | S8: N/A | T8: Company knowledge base (stable facts) | U8: Needs financial/leadership verification | V8: 2026-07-18
A9: United States | B9: UnitedHealth Group | C9: 8 | D9: Minnetonka, MN | E9: Healthcare | F9: Health Insurance & Services | G9: Public | H9: 1977 | I9: Verification Pending | J9: https://www.unitedhealthgroup.com | K9: Largest U.S. health insurer and healthcare services provider. | L9: Largest U | M9: NYSE | N9: UNH | O9: Verification Pending | P9: Verification Pending | Q9: Verification Pending | R9: Verification Pending | S9: N/A | T9: Company knowledge base (stable facts) | U9: Needs financial/leadership verification | V9: 2026-07-18
A11: Note: | B11: Company identity, industry, HQ, founding year, and website are stable facts. 'Verification Pending' fields (CEO, revenue, net income, market cap, Fortune 500 rank) change frequently and require a live data-verification pass before use in analysis.

Sheet China
A1: Rank | B1: Company Name | C1: Country | D1: HQ City | E1: Industry | F1: Sector | G1: Company Type | H1: Founded Year | I1: CEO | J1: Official Website | K1: Business Description | L1: Main Products/Services | M1: Stock Exchange | N1: Ticker Symbol | O1: Annual Revenue (USD) | P1: Net Income (USD) | Q1: Market Cap (USD) | R1: Fortune Global 500 Rank | S1: Parent Company | T1: Data Source | U1: Verification Status | V1: Last Updated
A2: China | B2: State Grid Corporation of China | C2: 1 | D2: Beijing | E2: Utilities | F2: Electric Power Transmission | G2: State-Owned | H2: 2002 | I2: Verification Pending | J2: https://www.sgcc.com.cn | K2: World's largest electric utility, operating national grid infrastructure. | L2: World's largest electric utility, operating national grid infrastructure | M2: State-owned (not listed) | N2: N/A | O2: Verification Pending | P2: Verification Pending | Q2: Verification Pending | R2: Verification Pending | S2: N/A | T2: Company knowledge base (stable facts) | U2: Needs financial/leadership verification | V2: 2026-07-18
A3: China | B3: Sinopec Group | C3: 2 | D3: Beijing | E3: Oil & Gas | F3: Energy | G3: State-Owned | H3: 1998 | I3: Verification Pending | J3: https://www.sinopecgroup.com | K3: Integrated energy and chemical company; refining and petrochemicals. | L3: Integrated energy and chemical company; refining and petrochemicals | M3: SSE/HKEX | N3: 600028 | O3: Verification Pending | P3: Verification Pending | Q3: Verification Pending | R3: Verification Pending | S3: N/A | T3: Company knowledge base (stable facts) | U3: Needs financial/leadership verification | V3: 2026-07-18
A4: China | B4: PetroChina / CNPC | C4: 3 | D4: Beijing | E4: Oil & Gas | F4: Energy | G4: State-Owned | H4: 1999 | I4: Verification Pending | J4: https://www.petrochina.com.cn | K4: Major oil and gas exploration and production company. | L4: Major oil and gas exploration and production company | M4: SSE/HKEX | N4: 601857 | O4: Verification Pending | P4: Verification Pending | Q4: Verification Pending | R4: Verification Pending | S4: N/A | T4: Company knowledge base (stable facts) | U4: Needs financial/leadership verification | V4: 2026-07-18
A5: China | B5: Industrial and Commercial Bank of China (ICBC) | C5: 4 | D5: Beijing | E5: Banking | F5: Financial Services | G5: State-Owned | H5: 1984 | I5: Verification Pending | J5: https://www.icbc.com.cn | K5: World's largest bank by total assets. | L5: World's largest bank by total assets | M5: SSE/HKEX | N5: 601398 | O5: Verification Pending | P5: Verification Pending | Q5: Verification Pending | R5: Verification Pending | S5: N/A | T5: Company knowledge base (stable facts) | U5: Needs financial/leadership verification | V5: 2026-07-18
A6: China | B6: Huawei Technologies | C6: 5 | D6: Shenzhen | E6: Telecommunications/Technology | F6: Networking Equipment & Devices | G6: Private | H6: 1987 | I6: Verification Pending | J6: https://www.huawei.com | K6: Telecom equipment, smartphones, and 5G infrastructure provider. | L6: Telecom equipment, smartphones, and 5G infrastructure provider | M6: Private | N6: N/A | O6: Verification Pending | P6: Verification Pending | Q6: Verification Pending | R6: Verification Pending | S6: N/A | T6: Company knowledge base (stable facts) | U6: Needs financial/leadership verification | V6: 2026-07-18
A7: China | B7: Alibaba Group | C7: 6 | D7: Hangzhou | E7: E-commerce | F7: Internet Services | G7: Public | H7: 1999 | I7: Verification Pending | J7: https://www.alibabagroup.com | K7: E-commerce, cloud computing, and digital payments conglomerate. | L7: E-commerce, cloud computing, and digital payments conglomerate | M7: NYSE/HKEX | N7: BABA | O7: Verification Pending | P7: Verification Pending | Q7: Verification Pending | R7: Verification Pending | S7: N/A | T7: Company knowledge base (stable facts) | U7: Needs financial/leadership verification | V7: 2026-07-18
A8: China | B8: Tencent Holdings | C8: 7 | D8: Shenzhen | E8: Technology | F8: Internet & Gaming | G8: Public | H8: 1998 | I8: Verification Pending | J8: https://www.tencent.com | K8: Social media, gaming, and fintech (WeChat, gaming publishing). | L8: Social media, gaming, and fintech (WeChat, gaming publishing) | M8: HKEX | N8: 0700 | O8: Verification Pending | P8: Verification Pending | Q8: Verification Pending | R8: Verification Pending | S8: N/A | T8: Company knowledge base (stable facts) | U8: Needs financial/leadership verification | V8: 2026-07-18
A9: China | B9: China Construction Bank | C9: 8 | D9: Beijing | E9: Banking | F9: Financial Services | G9: State-Owned | H9: 1954 | I9: Verification Pending | J9: https://www.ccb.com | K9: One of China's 'Big Four' state-owned commercial banks. | L9: One of China's 'Big Four' state-owned commercial banks | M9: SSE/HKEX | N9: 601939 | O9: Verification Pending | P9: Verification Pending | Q9: Verification Pending | R9: Verification Pending | S9: N/A | T9: Company knowledge base (stable facts) | U9: Needs financial/leadership verification | V9: 2026-07-18
A11: Note: | B11: Company identity, industry, HQ, founding year, and website are stable facts. 'Verification Pending' fields (CEO, revenue, net income, market cap, Fortune 500 rank) change frequently and require a live data-verification pass before use in analysis.

Sheet Japan
A1: Rank | B1: Company Name | C1: Country | D1: HQ City | E1: Industry | F1: Sector | G1: Company Type | H1: Founded Year | I1: CEO | J1: Official Website | K1: Business Description | L1: Main Products/Services | M1: Stock Exchange | N1: Ticker Symbol | O1: Annual Revenue (USD) | P1: Net Income (USD) | Q1: Market Cap (USD) | R1: Fortune Global 500 Rank | S1: Parent Company | T1: Data Source | U1: Verification Status | V1: Last Updated
A2: Japan | B2: Toyota Motor Corporation | C2: 1 | D2: Toyota City, Aichi | E2: Automotive | F2: Auto Manufacturing | G2: Public | H2: 1937 | I2: Verification Pending | J2: https://global.toyota | K2: World's largest automaker by sales; also a leader in hybrid vehicle technology. | L2: World's largest automaker by sales; also a leader in hybrid vehicle technology | M2: TSE | N2: 7203 | O2: Verification Pending | P2: Verification Pending | Q2: Verification Pending | R2: Verification Pending | S2: N/A | T2: Company knowledge base (stable facts) | U2: Needs financial/leadership verification | V2: 2026-07-18
A3: Japan | B3: Sony Group Corporation | C3: 2 | D3: Tokyo | E3: Electronics/Entertainment | F3: Consumer Electronics & Media | G3: Public | H3: 1946 | I3: Verification Pending | J3: https://www.sony.com | K3: Consumer electronics, gaming (PlayStation), music, and film. | L3: Consumer electronics, gaming (PlayStation), music, and film | M3: TSE | N3: 6758 | O3: Verification Pending | P3: Verification Pending | Q3: Verification Pending | R3: Verification Pending | S3: N/A | T3: Company knowledge base (stable facts) | U3: Needs financial/leadership verification | V3: 2026-07-18
A4: Japan | B4: Mitsubishi UFJ Financial Group | C4: 3 | D4: Tokyo | E4: Banking | F4: Financial Services | G4: Public | H4: 2005 | I4: Verification Pending | J4: https://www.mufg.jp | K4: Japan's largest bank holding company. | L4: Japan's largest bank holding company | M4: TSE | N4: 8306 | O4: Verification Pending | P4: Verification Pending | Q4: Verification Pending | R4: Verification Pending | S4: N/A | T4: Company knowledge base (stable facts) | U4: Needs financial/leadership verification | V4: 2026-07-18
A5: Japan | B5: Honda Motor Co. | C5: 4 | D5: Tokyo | E5: Automotive | F5: Auto & Motorcycle Manufacturing | G5: Public | H5: 1948 | I5: Verification Pending | J5: https://global.honda | K5: Automobiles, motorcycles, and power equipment manufacturer. | L5: Automobiles, motorcycles, and power equipment manufacturer | M5: TSE | N5: 7267 | O5: Verification Pending | P5: Verification Pending | Q5: Verification Pending | R5: Verification Pending | S5: N/A | T5: Company knowledge base (stable facts) | U5: Needs financial/leadership verification | V5: 2026-07-18
A6: Japan | B6: SoftBank Group | C6: 5 | D6: Tokyo | E6: Telecommunications/Investment | F6: Technology Holding | G6: Public | H6: 1981 | I6: Verification Pending | J6: https://group.softbank | K6: Telecom carrier and technology investment conglomerate (Vision Fund). | L6: Telecom carrier and technology investment conglomerate (Vision Fund) | M6: TSE | N6: 9984 | O6: Verification Pending | P6: Verification Pending | Q6: Verification Pending | R6: Verification Pending | S6: N/A | T6: Company knowledge base (stable facts) | U6: Needs financial/leadership verification | V6: 2026-07-18
A7: Japan | B7: Keyence Corporation | C7: 6 | D7: Osaka | E7: Electronics | F7: Industrial Automation Sensors | G7: Public | H7: 1974 | I7: Verification Pending | J7: https://www.keyence.com | K7: Factory automation sensors and measurement systems. | L7: Factory automation sensors and measurement systems | M7: TSE | N7: 6861 | O7: Verification Pending | P7: Verification Pending | Q7: Verification Pending | R7: Verification Pending | S7: N/A | T7: Company knowledge base (stable facts) | U7: Needs financial/leadership verification | V7: 2026-07-18
A8: Japan | B8: Nippon Telegraph and Telephone (NTT) | C8: 7 | D8: Tokyo | E8: Telecommunications | F8: Telecom Services | G8: Public | H8: 1985 | I8: Verification Pending | J8: https://group.ntt | K8: Japan's largest telecommunications company. | L8: Japan's largest telecommunications company | M8: TSE | N8: 9432 | O8: Verification Pending | P8: Verification Pending | Q8: Verification Pending | R8: Verification Pending | S8: N/A | T8: Company knowledge base (stable facts) | U8: Needs financial/leadership verification | V8: 2026-07-18
A10: Note: | B10: Company identity, industry, HQ, founding year, and website are stable facts. 'Verification Pending' fields (CEO, revenue, net income, market cap, Fortune 500 rank) change frequently and require a live data-verification pass before use in analysis.

Sheet Germany
A1: Rank | B1: Company Name | C1: Country | D1: HQ City | E1: Industry | F1: Sector | G1: Company Type | H1: Founded Year | I1: CEO | J1: Official Website | K1: Business Description | L1: Main Products/Services | M1: Stock Exchange | N1: Ticker Symbol | O1: Annual Revenue (USD) | P1: Net Income (USD) | Q1: Market Cap (USD) | R1: Fortune Global 500 Rank | S1: Parent Company | T1: Data Source | U1: Verification Status | V1: Last Updated
A2: Germany | B2: Volkswagen Group | C2: 1 | D2: Wolfsburg | E2: Automotive | F2: Auto Manufacturing | G2: Public | H2: 1937 | I2: Verification Pending | J2: https://www.volkswagenag.com | K2: World's largest automaker by volume; owns Audi, Porsche, Skoda. | L2: World's largest automaker by volume; owns Audi, Porsche, Skoda | M2: FWB | N2: VOW3 | O2: Verification Pending | P2: Verification Pending | Q2: Verification Pending | R2: Verification Pending | S2: N/A | T2: Company knowledge base (stable facts) | U2: Needs financial/leadership verification | V2: 2026-07-18
A3: Germany | B3: Mercedes-Benz Group | C3: 2 | D3: Stuttgart | E3: Automotive | F3: Luxury Auto Manufacturing | G3: Public | H3: 1926 | I3: Verification Pending | J3: https://group.mercedes-benz.com | K3: Luxury automobiles and commercial vehicles manufacturer. | L3: Luxury automobiles and commercial vehicles manufacturer | M3: FWB | N3: MBG | O3: Verification Pending | P3: Verification Pending | Q3: Verification Pending | R3: Verification Pending | S3: N/A | T3: Company knowledge base (stable facts) | U3: Needs financial/leadership verification | V3: 2026-07-18
A4: Germany | B4: SAP SE | C4: 3 | D4: Walldorf | E4: Software | F4: Enterprise Software | G4: Public | H4: 1972 | I4: Verification Pending | J4: https://www.sap.com | K4: Enterprise resource planning (ERP) software leader. | L4: Enterprise resource planning (ERP) software leader | M4: FWB/NYSE | N4: SAP | O4: Verification Pending | P4: Verification Pending | Q4: Verification Pending | R4: Verification Pending | S4: N/A | T4: Company knowledge base (stable facts) | U4: Needs financial/leadership verification | V4: 2026-07-18
A5: Germany | B5: Siemens AG | C5: 4 | D5: Munich | E5: Industrial Manufacturing | F5: Industrial Automation & Infrastructure | G5: Public | H5: 1847 | I5: Verification Pending | J5: https://www.siemens.com | K5: Industrial automation, healthcare technology, and infrastructure conglomerate. | L5: Industrial automation, healthcare technology, and infrastructure conglomerate | M5: FWB | N5: SIE | O5: Verification Pending | P5: Verification Pending | Q5: Verification Pending | R5: Verification Pending | S5: N/A | T5: Company knowledge base (stable facts) | U5: Needs financial/leadership verification | V5: 2026-07-18
A6: Germany | B6: Allianz SE | C6: 5 | D6: Munich | E6: Insurance | F6: Financial Services | G6: Public | H6: 1890 | I6: Verification Pending | J6: https://www.allianz.com | K6: One of the world's largest insurance and asset management companies. | L6: One of the world's largest insurance and asset management companies | M6: FWB | N6: ALV | O6: Verification Pending | P6: Verification Pending | Q6: Verification Pending | R6: Verification Pending | S6: N/A | T6: Company knowledge base (stable facts) | U6: Needs financial/leadership verification | V6: 2026-07-18
A7: Germany | B7: BMW Group | C7: 6 | D7: Munich | E7: Automotive | F7: Luxury Auto Manufacturing | G7: Public | H7: 1916 | I7: Verification Pending | J7: https://www.bmwgroup.com | K7: Luxury automobiles and motorcycles manufacturer. | L7: Luxury automobiles and motorcycles manufacturer | M7: FWB | N7: BMW | O7: Verification Pending | P7: Verification Pending | Q7: Verification Pending | R7: Verification Pending | S7: N/A | T7: Company knowledge base (stable facts) | U7: Needs financial/leadership verification | V7: 2026-07-18
A8: Germany | B8: Deutsche Telekom | C8: 7 | D8: Bonn | E8: Telecommunications | F8: Telecom Services | G8: Public | H8: 1995 | I8: Verification Pending | J8: https://www.telekom.com | K8: Telecom carrier; majority owner of T-Mobile US. | L8: Telecom carrier; majority owner of T-Mobile US | M8: FWB | N8: DTE | O8: Verification Pending | P8: Verification Pending | Q8: Verification Pending | R8: Verification Pending | S8: N/A | T8: Company knowledge base (stable facts) | U8: Needs financial/leadership verification | V8: 2026-07-18
A10: Note: | B10: Company identity, industry, HQ, founding year, and website are stable facts. 'Verification Pending' fields (CEO, revenue, net income, market cap, Fortune 500 rank) change frequently and require a live data-verification pass before use in analysis.

Sheet India
A1: Rank | B1: Company Name | C1: Country | D1: HQ City | E1: Industry | F1: Sector | G1: Company Type | H1: Founded Year | I1: CEO | J1: Official Website | K1: Business Description | L1: Main Products/Services | M1: Stock Exchange | N1: Ticker Symbol | O1: Annual Revenue (USD) | P1: Net Income (USD) | Q1: Market Cap (USD) | R1: Fortune Global 500 Rank | S1: Parent Company | T1: Data Source | U1: Verification Status | V1: Last Updated
A2: India | B2: Reliance Industries | C2: 1 | D2: Mumbai | E2: Conglomerate | F2: Energy, Retail & Telecom | G2: Public | H2: 1966 | I2: Verification Pending | J2: https://www.ril.com | K2: Diversified conglomerate spanning petrochemicals, retail, and telecom (Jio). | L2: Diversified conglomerate spanning petrochemicals, retail, and telecom (Jio) | M2: NSE/BSE | N2: RELIANCE | O2: Verification Pending | P2: Verification Pending | Q2: Verification Pending | R2: Verification Pending | S2: N/A | T2: Company knowledge base (stable facts) | U2: Needs financial/leadership verification | V2: 2026-07-18
A3: India | B3: Tata Consultancy Services (TCS) | C3: 2 | D3: Mumbai | E3: Information Technology | F3: IT Services | G3: Public | H3: 1968 | I3: Verification Pending | J3: https://www.tcs.com | K3: Global IT services, consulting, and business solutions company. | L3: Global IT services, consulting, and business solutions company | M3: NSE/BSE | N3: TCS | O3: Verification Pending | P3: Verification Pending | Q3: Verification Pending | R3: Verification Pending | S3: N/A | T3: Company knowledge base (stable facts) | U3: Needs financial/leadership verification | V3: 2026-07-18
A4: India | B4: HDFC Bank | C4: 3 | D4: Mumbai | E4: Banking | F4: Financial Services | G4: Public | H4: 1994 | I4: Verification Pending | J4: https://www.hdfcbank.com | K4: India's largest private sector bank by assets. | L4: India's largest private sector bank by assets | M4: NSE/BSE | N4: HDFCBANK | O4: Verification Pending | P4: Verification Pending | Q4: Verification Pending | R4: Verification Pending | S4: N/A | T4: Company knowledge base (stable facts) | U4: Needs financial/leadership verification | V4: 2026-07-18
A5: India | B5: Infosys | C5: 4 | D5: Bengaluru | E5: Information Technology | F5: IT Services | G5: Public | H5: 1981 | I5: Verification Pending | J5: https://www.infosys.com | K5: Global IT consulting and outsourcing services company. | L5: Global IT consulting and outsourcing services company | M5: NSE/BSE | N5: INFY | O5: Verification Pending | P5: Verification Pending | Q5: Verification Pending | R5: Verification Pending | S5: N/A | T5: Company knowledge base (stable facts) | U5: Needs financial/leadership verification | V5: 2026-07-18
A6: India | B6: ICICI Bank | C6: 5 | D6: Mumbai | E6: Banking | F6: Financial Services | G6: Public | H6: 1994 | I6: Verification Pending | J6: https://www.icicibank.com | K6: Major private sector bank offering retail and corporate banking. | L6: Major private sector bank offering retail and corporate banking | M6: NSE/BSE | N6: ICICIBANK | O6: Verification Pending | P6: Verification Pending | Q6: Verification Pending | R6: Verification Pending | S6: N/A | T6: Company knowledge base (stable facts) | U6: Needs financial/leadership verification | V6: 2026-07-18
A7: India | B7: State Bank of India | C7: 6 | D7: Mumbai | E7: Banking | F7: Financial Services | G7: State-Owned | H7: 1955 | I7: Verification Pending | J7: https://www.sbi.co.in | K7: India's largest public sector bank. | L7: India's largest public sector bank | M7: NSE/BSE | N7: SBIN | O7: Verification Pending | P7: Verification Pending | Q7: Verification Pending | R7: Verification Pending | S7: N/A | T7: Company knowledge base (stable facts) | U7: Needs financial/leadership verification | V7: 2026-07-18
A8: India | B8: Adani Group | C8: 7 | D8: Ahmedabad | E8: Conglomerate | F8: Ports, Energy & Infrastructure | G8: Public | H8: 1988 | I8: Verification Pending | J8: https://www.adani.com | K8: Infrastructure conglomerate spanning ports, power, and renewables. | L8: Infrastructure conglomerate spanning ports, power, and renewables | M8: NSE/BSE | N8: ADANIENT | O8: Verification Pending | P8: Verification Pending | Q8: Verification Pending | R8: Verification Pending | S8: N/A | T8: Company knowledge base (stable facts) | U8: Needs financial/leadership verification | V8: 2026-07-18
A10: Note: | B10: Company identity, industry, HQ, founding year, and website are stable facts. 'Verification Pending' fields (CEO, revenue, net income, market cap, Fortune 500 rank) change frequently and require a live data-verification pass before use in analysis.

Sheet United Kingdom
A1: Rank | B1: Company Name | C1: Country | D1: HQ City | E1: Industry | F1: Sector | G1: Company Type | H1: Founded Year | I1: CEO | J1: Official Website | K1: Business Description | L1: Main Products/Services | M1: Stock Exchange | N1: Ticker Symbol | O1: Annual Revenue (USD) | P1: Net Income (USD) | Q1: Market Cap (USD) | R1: Fortune Global 500 Rank | S1: Parent Company | T1: Data Source | U1: Verification Status | V1: Last Updated
A2: United Kingdom | B2: Shell plc | C2: 1 | D2: London | E2: Oil & Gas | F2: Energy | G2: Public | H2: 1907 | I2: Verification Pending | J2: https://www.shell.com | K2: Global integrated oil, gas, and renewable energy company. | L2: Global integrated oil, gas, and renewable energy company | M2: LSE | N2: SHEL | O2: Verification Pending | P2: Verification Pending | Q2: Verification Pending | R2: Verification Pending | S2: N/A | T2: Company knowledge base (stable facts) | U2: Needs financial/leadership verification | V2: 2026-07-18
A3: United Kingdom | B3: HSBC Holdings | C3: 2 | D3: London | E3: Banking | F3: Financial Services | G3: Public | H3: 1865 | I3: Verification Pending | J3: https://www.hsbc.com | K3: One of the world's largest banking and financial services organizations. | L3: One of the world's largest banking and financial services organizations | M3: LSE | N3: HSBA | O3: Verification Pending | P3: Verification Pending | Q3: Verification Pending | R3: Verification Pending | S3: N/A | T3: Company knowledge base (stable facts) | U3: Needs financial/leadership verification | V3: 2026-07-18
A4: United Kingdom | B4: AstraZeneca | C4: 3 | D4: Cambridge | E4: Pharmaceuticals | F4: Biopharmaceuticals | G4: Public | H4: 1999 | I4: Verification Pending | J4: https://www.astrazeneca.com | K4: Global biopharmaceutical company focused on oncology and rare diseases. | L4: Global biopharmaceutical company focused on oncology and rare diseases | M4: LSE | N4: AZN | O4: Verification Pending | P4: Verification Pending | Q4: Verification Pending | R4: Verification Pending | S4: N/A | T4: Company knowledge base (stable facts) | U4: Needs financial/leadership verification | V4: 2026-07-18
A5: United Kingdom | B5: BP plc | C5: 4 | D5: London | E5: Oil & Gas | F5: Energy | G5: Public | H5: 1909 | I5: Verification Pending | J5: https://www.bp.com | K5: Integrated oil and gas company with growing low-carbon business. | L5: Integrated oil and gas company with growing low-carbon business | M5: LSE | N5: BP | O5: Verification Pending | P5: Verification Pending | Q5: Verification Pending | R5: Verification Pending | S5: N/A | T5: Company knowledge base (stable facts) | U5: Needs financial/leadership verification | V5: 2026-07-18
A6: United Kingdom | B6: Unilever | C6: 5 | D6: London | E6: Consumer Goods | F6: FMCG | G6: Public | H6: 1929 | I6: Verification Pending | J6: https://www.unilever.com | K6: Global consumer goods company - food, home and personal care brands. | L6: Global consumer goods company - food, home and personal care brands | M6: LSE | N6: ULVR | O6: Verification Pending | P6: Verification Pending | Q6: Verification Pending | R6: Verification Pending | S6: N/A | T6: Company knowledge base (stable facts) | U6: Needs financial/leadership verification | V6: 2026-07-18
A7: United Kingdom | B7: Diageo | C7: 6 | D7: London | E7: Beverages | F7: Alcoholic Beverages | G7: Public | H7: 1997 | I7: Verification Pending | J7: https://www.diageo.com | K7: World's largest producer of spirits, including Johnnie Walker and Guinness. | L7: World's largest producer of spirits, including Johnnie Walker and Guinness | M7: LSE | N7: DGE | O7: Verification Pending | P7: Verification Pending | Q7: Verification Pending | R7: Verification Pending | S7: N/A | T7: Company knowledge base (stable facts) | U7: Needs financial/leadership verification | V7: 2026-07-18
A9: Note: | B9: Company identity, industry, HQ, founding year, and website are stable facts. 'Verification Pending' fields (CEO, revenue, net income, market cap, Fortune 500 rank) change frequently and require a live data-verification pass before use in analysis.

Sheet France
A1: Rank | B1: Company Name | C1: Country | D1: HQ City | E1: Industry | F1: Sector | G1: Company Type | H1: Founded Year | I1: CEO | J1: Official Website | K1: Business Description | L1: Main Products/Services | M1: Stock Exchange | N1: Ticker Symbol | O1: Annual Revenue (USD) | P1: Net Income (USD) | Q1: Market Cap (USD) | R1: Fortune Global 500 Rank | S1: Parent Company | T1: Data Source | U1: Verification Status | V1: Last Updated
A2: France | B2: TotalEnergies | C2: 1 | D2: Paris | E2: Oil & Gas | F2: Energy | G2: Public | H2: 1924 | I2: Verification Pending | J2: https://totalenergies.com | K2: Multi-energy company spanning oil, gas, and renewables. | L2: Multi-energy company spanning oil, gas, and renewables | M2: Euronext Paris | N2: TTE | O2: Verification Pending | P2: Verification Pending | Q2: Verification Pending | R2: Verification Pending | S2: N/A | T2: Company knowledge base (stable facts) | U2: Needs financial/leadership verification | V2: 2026-07-18
A3: France | B3: LVMH | C3: 2 | D3: Paris | E3: Luxury Goods | F3: Fashion & Retail | G3: Public | H3: 1987 | I3: Verification Pending | J3: https://www.lvmh.com | K3: World's largest luxury goods conglomerate (Louis Vuitton, Dior, Moet Hennessy). | L3: World's largest luxury goods conglomerate (Louis Vuitton, Dior, Moet Hennessy) | M3: Euronext Paris | N3: MC | O3: Verification Pending | P3: Verification Pending | Q3: Verification Pending | R3: Verification Pending | S3: N/A | T3: Company knowledge base (stable facts) | U3: Needs financial/leadership verification | V3: 2026-07-18
A4: France | B4: L'Oreal | C4: 3 | D4: Clichy | E4: Consumer Goods | F4: Cosmetics | G4: Public | H4: 1909 | I4: Verification Pending | J4: https://www.loreal.com | K4: World's largest cosmetics and beauty company. | L4: World's largest cosmetics and beauty company | M4: Euronext Paris | N4: OR | O4: Verification Pending | P4: Verification Pending | Q4: Verification Pending | R4: Verification Pending | S4: N/A | T4: Company knowledge base (stable facts) | U4: Needs financial/leadership verification | V4: 2026-07-18
A5: France | B5: BNP Paribas | C5: 4 | D5: Paris | E5: Banking | F5: Financial Services | G5: Public | H5: 1848 | I5: Verification Pending | J5: https://www.bnpparibas.com | K5: One of the largest banks in the world by assets. | L5: One of the largest banks in the world by assets | M5: Euronext Paris | N5: BNP | O5: Verification Pending | P5: Verification Pending | Q5: Verification Pending | R5: Verification Pending | S5: N/A | T5: Company knowledge base (stable facts) | U5: Needs financial/leadership verification | V5: 2026-07-18
A6: France | B6: Airbus SE | C6: 5 | D6: Toulouse/Leiden | E6: Aerospace | F6: Aircraft Manufacturing | G6: Public | H6: 1970 | I6: Verification Pending | J6: https://www.airbus.com | K6: World's largest commercial aircraft manufacturer alongside Boeing. | L6: World's largest commercial aircraft manufacturer alongside Boeing | M6: Euronext Paris | N6: AIR | O6: Verification Pending | P6: Verification Pending | Q6: Verification Pending | R6: Verification Pending | S6: N/A | T6: Company knowledge base (stable facts) | U6: Needs financial/leadership verification | V6: 2026-07-18
A7: France | B7: Sanofi | C7: 6 | D7: Paris | E7: Pharmaceuticals | F7: Biopharmaceuticals | G7: Public | H7: 1973 | I7: Verification Pending | J7: https://www.sanofi.com | K7: Global pharmaceutical and healthcare company. | L7: Global pharmaceutical and healthcare company | M7: Euronext Paris | N7: SAN | O7: Verification Pending | P7: Verification Pending | Q7: Verification Pending | R7: Verification Pending | S7: N/A | T7: Company knowledge base (stable facts) | U7: Needs financial/leadership verification | V7: 2026-07-18
A9: Note: | B9: Company identity, industry, HQ, founding year, and website are stable facts. 'Verification Pending' fields (CEO, revenue, net income, market cap, Fortune 500 rank) change frequently and require a live data-verification pass before use in analysis.

Sheet Italy
A1: Rank | B1: Company Name | C1: Country | D1: HQ City | E1: Industry | F1: Sector | G1: Company Type | H1: Founded Year | I1: CEO | J1: Official Website | K1: Business Description | L1: Main Products/Services | M1: Stock Exchange | N1: Ticker Symbol | O1: Annual Revenue (USD) | P1: Net Income (USD) | Q1: Market Cap (USD) | R1: Fortune Global 500 Rank | S1: Parent Company | T1: Data Source | U1: Verification Status | V1: Last Updated
A2: Italy | B2: Eni S.p.A. | C2: 1 | D2: Rome | E2: Oil & Gas | F2: Energy | G2: Public | H2: 1953 | I2: Verification Pending | J2: https://www.eni.com | K2: Integrated energy company in oil, gas, and renewables. | L2: Integrated energy company in oil, gas, and renewables | M2: Borsa Italiana | N2: ENI | O2: Verification Pending | P2: Verification Pending | Q2: Verification Pending | R2: Verification Pending | S2: N/A | T2: Company knowledge base (stable facts) | U2: Needs financial/leadership verification | V2: 2026-07-18
A3: Italy | B3: Enel S.p.A. | C3: 2 | D3: Rome | E3: Utilities | F3: Electric Power | G3: Public | H3: 1962 | I3: Verification Pending | J3: https://www.enel.com | K3: Multinational electricity and gas utility, major renewables operator. | L3: Multinational electricity and gas utility, major renewables operator | M3: Borsa Italiana | N3: ENEL | O3: Verification Pending | P3: Verification Pending | Q3: Verification Pending | R3: Verification Pending | S3: N/A | T3: Company knowledge base (stable facts) | U3: Needs financial/leadership verification | V3: 2026-07-18
A4: Italy | B4: Intesa Sanpaolo | C4: 3 | D4: Turin | E4: Banking | F4: Financial Services | G4: Public | H4: 2007 | I4: Verification Pending | J4: https://group.intesasanpaolo.com | K4: Italy's largest banking group. | L4: Italy's largest banking group | M4: Borsa Italiana | N4: ISP | O4: Verification Pending | P4: Verification Pending | Q4: Verification Pending | R4: Verification Pending | S4: N/A | T4: Company knowledge base (stable facts) | U4: Needs financial/leadership verification | V4: 2026-07-18
A5: Italy | B5: UniCredit | C5: 4 | D5: Milan | E5: Banking | F5: Financial Services | G5: Public | H5: 1998 | I5: Verification Pending | J5: https://www.unicredit.eu | K5: Major pan-European commercial bank. | L5: Major pan-European commercial bank | M5: Borsa Italiana | N5: UCG | O5: Verification Pending | P5: Verification Pending | Q5: Verification Pending | R5: Verification Pending | S5: N/A | T5: Company knowledge base (stable facts) | U5: Needs financial/leadership verification | V5: 2026-07-18
A6: Italy | B6: Ferrari N.V. | C6: 5 | D6: Maranello | E6: Automotive | F6: Luxury Sports Cars | G6: Public | H6: 1939 | I6: Verification Pending | J6: https://corporate.ferrari.com | K6: Manufacturer of luxury sports cars and Formula 1 racing team. | L6: Manufacturer of luxury sports cars and Formula 1 racing team | M6: Borsa Italiana/NYSE | N6: RACE | O6: Verification Pending | P6: Verification Pending | Q6: Verification Pending | R6: Verification Pending | S6: N/A | T6: Company knowledge base (stable facts) | U6: Needs financial/leadership verification | V6: 2026-07-18
A8: Note: | B8: Company identity, industry, HQ, founding year, and website are stable facts. 'Verification Pending' fields (CEO, revenue, net income, market cap, Fortune 500 rank) change frequently and require a live data-verification pass before use in analysis.

Sheet Brazil
A1: Rank | B1: Company Name | C1: Country | D1: HQ City | E1: Industry | F1: Sector | G1: Company Type | H1: Founded Year | I1: CEO | J1: Official Website | K1: Business Description | L1: Main Products/Services | M1: Stock Exchange | N1: Ticker Symbol | O1: Annual Revenue (USD) | P1: Net Income (USD) | Q1: Market Cap (USD) | R1: Fortune Global 500 Rank | S1: Parent Company | T1: Data Source | U1: Verification Status | V1: Last Updated
A2: Brazil | B2: Petrobras | C2: 1 | D2: Rio de Janeiro | E2: Oil & Gas | F2: Energy | G2: State-Owned | H2: 1953 | I2: Verification Pending | J2: https://petrobras.com.br | K2: Brazil's state-controlled oil and gas company. | L2: Brazil's state-controlled oil and gas company | M2: B3/NYSE | N2: PETR4 | O2: Verification Pending | P2: Verification Pending | Q2: Verification Pending | R2: Verification Pending | S2: N/A | T2: Company knowledge base (stable facts) | U2: Needs financial/leadership verification | V2: 2026-07-18
A3: Brazil | B3: Vale S.A. | C3: 2 | D3: Rio de Janeiro | E3: Mining | F3: Metals & Mining | G3: Public | H3: 1942 | I3: Verification Pending | J3: https://www.vale.com | K3: World's largest producer of iron ore and nickel. | L3: World's largest producer of iron ore and nickel | M3: B3/NYSE | N3: VALE | O3: Verification Pending | P3: Verification Pending | Q3: Verification Pending | R3: Verification Pending | S3: N/A | T3: Company knowledge base (stable facts) | U3: Needs financial/leadership verification | V3: 2026-07-18
A4: Brazil | B4: Itau Unibanco | C4: 3 | D4: Sao Paulo | E4: Banking | F4: Financial Services | G4: Public | H4: 2008 | I4: Verification Pending | J4: https://www.itau.com.br | K4: Largest private bank in Latin America. | L4: Largest private bank in Latin America | M4: B3 | N4: ITUB4 | O4: Verification Pending | P4: Verification Pending | Q4: Verification Pending | R4: Verification Pending | S4: N/A | T4: Company knowledge base (stable facts) | U4: Needs financial/leadership verification | V4: 2026-07-18
A5: Brazil | B5: Banco Bradesco | C5: 4 | D5: Osasco | E5: Banking | F5: Financial Services | G5: Public | H5: 1943 | I5: Verification Pending | J5: https://www.bradesco.com.br | K5: One of Brazil's largest private banks. | L5: One of Brazil's largest private banks | M5: B3 | N5: BBDC4 | O5: Verification Pending | P5: Verification Pending | Q5: Verification Pending | R5: Verification Pending | S5: N/A | T5: Company knowledge base (stable facts) | U5: Needs financial/leadership verification | V5: 2026-07-18
A6: Brazil | B6: JBS S.A. | C6: 5 | D6: Sao Paulo | E6: Food & Beverage | F6: Meat Processing | G6: Public | H6: 1953 | I6: Verification Pending | J6: https://jbs.com.br | K6: World's largest meat processing company. | L6: World's largest meat processing company | M6: B3 | N6: JBSS3 | O6: Verification Pending | P6: Verification Pending | Q6: Verification Pending | R6: Verification Pending | S6: N/A | T6: Company knowledge base (stable facts) | U6: Needs financial/leadership verification | V6: 2026-07-18
A8: Note: | B8: Company identity, industry, HQ, founding year, and website are stable facts. 'Verification Pending' fields (CEO, revenue, net income, market cap, Fortune 500 rank) change frequently and require a live data-verification pass before use in analysis.

Sheet Canada
A1: Rank | B1: Company Name | C1: Country | D1: HQ City | E1: Industry | F1: Sector | G1: Company Type | H1: Founded Year | I1: CEO | J1: Official Website | K1: Business Description | L1: Main Products/Services | M1: Stock Exchange | N1: Ticker Symbol | O1: Annual Revenue (USD) | P1: Net Income (USD) | Q1: Market Cap (USD) | R1: Fortune Global 500 Rank | S1: Parent Company | T1: Data Source | U1: Verification Status | V1: Last Updated
A2: Canada | B2: Royal Bank of Canada | C2: 1 | D2: Toronto | E2: Banking | F2: Financial Services | G2: Public | H2: 1864 | I2: Verification Pending | J2: https://www.rbc.com | K2: Canada's largest bank by market capitalization. | L2: Canada's largest bank by market capitalization | M2: TSX/NYSE | N2: RY | O2: Verification Pending | P2: Verification Pending | Q2: Verification Pending | R2: Verification Pending | S2: N/A | T2: Company knowledge base (stable facts) | U2: Needs financial/leadership verification | V2: 2026-07-18
A3: Canada | B3: Toronto-Dominion Bank | C3: 2 | D3: Toronto | E3: Banking | F3: Financial Services | G3: Public | H3: 1955 | I3: Verification Pending | J3: https://www.td.com | K3: Major Canadian bank with large U.S. retail presence. | L3: Major Canadian bank with large U | M3: TSX/NYSE | N3: TD | O3: Verification Pending | P3: Verification Pending | Q3: Verification Pending | R3: Verification Pending | S3: N/A | T3: Company knowledge base (stable facts) | U3: Needs financial/leadership verification | V3: 2026-07-18
A4: Canada | B4: Enbridge | C4: 3 | D4: Calgary | E4: Oil & Gas | F4: Energy Infrastructure | G4: Public | H4: 1949 | I4: Verification Pending | J4: https://www.enbridge.com | K4: North America's largest energy pipeline infrastructure company. | L4: North America's largest energy pipeline infrastructure company | M4: TSX/NYSE | N4: ENB | O4: Verification Pending | P4: Verification Pending | Q4: Verification Pending | R4: Verification Pending | S4: N/A | T4: Company knowledge base (stable facts) | U4: Needs financial/leadership verification | V4: 2026-07-18
A5: Canada | B5: Canadian National Railway | C5: 4 | D5: Montreal | E5: Logistics | F5: Rail Transport | G5: Public | H5: 1919 | I5: Verification Pending | J5: https://www.cn.ca | K5: Major transcontinental freight railway. | L5: Major transcontinental freight railway | M5: TSX/NYSE | N5: CNR | O5: Verification Pending | P5: Verification Pending | Q5: Verification Pending | R5: Verification Pending | S5: N/A | T5: Company knowledge base (stable facts) | U5: Needs financial/leadership verification | V5: 2026-07-18
A6: Canada | B6: Suncor Energy | C6: 5 | D6: Calgary | E6: Oil & Gas | F6: Energy | G6: Public | H6: 1917 | I6: Verification Pending | J6: https://www.suncor.com | K6: Integrated oil sands energy company. | L6: Integrated oil sands energy company | M6: TSX/NYSE | N6: SU | O6: Verification Pending | P6: Verification Pending | Q6: Verification Pending | R6: Verification Pending | S6: N/A | T6: Company knowledge base (stable facts) | U6: Needs financial/leadership verification | V6: 2026-07-18
A8: Note: | B8: Company identity, industry, HQ, founding year, and website are stable facts. 'Verification Pending' fields (CEO, revenue, net income, market cap, Fortune 500 rank) change frequently and require a live data-verification pass before use in analysis.

Sheet Russia
A1: Rank | B1: Company Name | C1: Country | D1: HQ City | E1: Industry | F1: Sector | G1: Company Type | H1: Founded Year | I1: CEO | J1: Official Website | K1: Business Description | L1: Main Products/Services | M1: Stock Exchange | N1: Ticker Symbol | O1: Annual Revenue (USD) | P1: Net Income (USD) | Q1: Market Cap (USD) | R1: Fortune Global 500 Rank | S1: Parent Company | T1: Data Source | U1: Verification Status | V1: Last Updated
A2: Russia | B2: Gazprom | C2: 1 | D2: Moscow | E2: Oil & Gas | F2: Energy | G2: State-Owned | H2: 1989 | I2: Verification Pending | J2: https://www.gazprom.com | K2: World's largest natural gas extraction and pipeline company. | L2: World's largest natural gas extraction and pipeline company | M2: MOEX | N2: GAZP | O2: Verification Pending | P2: Verification Pending | Q2: Verification Pending | R2: Verification Pending | S2: N/A | T2: Company knowledge base (stable facts) | U2: Needs financial/leadership verification | V2: 2026-07-18
A3: Russia | B3: Rosneft | C3: 2 | D3: Moscow | E3: Oil & Gas | F3: Energy | G3: State-Owned | H3: 1993 | I3: Verification Pending | J3: https://www.rosneft.com | K3: Russia's largest oil producer. | L3: Russia's largest oil producer | M3: MOEX | N3: ROSN | O3: Verification Pending | P3: Verification Pending | Q3: Verification Pending | R3: Verification Pending | S3: N/A | T3: Company knowledge base (stable facts) | U3: Needs financial/leadership verification | V3: 2026-07-18
A4: Russia | B4: Sberbank | C4: 3 | D4: Moscow | E4: Banking | F4: Financial Services | G4: State-Owned | H4: 1841 | I4: Verification Pending | J4: https://www.sberbank.com | K4: Russia's largest bank. | L4: Russia's largest bank | M4: MOEX | N4: SBER | O4: Verification Pending | P4: Verification Pending | Q4: Verification Pending | R4: Verification Pending | S4: N/A | T4: Company knowledge base (stable facts) | U4: Needs financial/leadership verification | V4: 2026-07-18
A5: Russia | B5: Lukoil | C5: 4 | D5: Moscow | E5: Oil & Gas | F5: Energy | G5: Public | H5: 1991 | I5: Verification Pending | J5: https://www.lukoil.com | K5: Major privately-owned Russian oil and gas company. | L5: Major privately-owned Russian oil and gas company | M5: MOEX | N5: LKOH | O5: Verification Pending | P5: Verification Pending | Q5: Verification Pending | R5: Verification Pending | S5: N/A | T5: Company knowledge base (stable facts) | U5: Needs financial/leadership verification | V5: 2026-07-18
A6: Russia | B6: Norilsk Nickel | C6: 5 | D6: Moscow | E6: Mining | F6: Metals & Mining | G6: Public | H6: 1935 | I6: Verification Pending | J6: https://www.nornickel.com | K6: World's largest producer of refined nickel and palladium. | L6: World's largest producer of refined nickel and palladium | M6: MOEX | N6: GMKN | O6: Verification Pending | P6: Verification Pending | Q6: Verification Pending | R6: Verification Pending | S6: N/A | T6: Company knowledge base (stable facts) | U6: Needs financial/leadership verification | V6: 2026-07-18
A8: Note: | B8: Company identity, industry, HQ, founding year, and website are stable facts. 'Verification Pending' fields (CEO, revenue, net income, market cap, Fortune 500 rank) change frequently and require a live data-verification pass before use in analysis.

Sheet South Korea
A1: Rank | B1: Company Name | C1: Country | D1: HQ City | E1: Industry | F1: Sector | G1: Company Type | H1: Founded Year | I1: CEO | J1: Official Website | K1: Business Description | L1: Main Products/Services | M1: Stock Exchange | N1: Ticker Symbol | O1: Annual Revenue (USD) | P1: Net Income (USD) | Q1: Market Cap (USD) | R1: Fortune Global 500 Rank | S1: Parent Company | T1: Data Source | U1: Verification Status | V1: Last Updated
A2: South Korea | B2: Samsung Electronics | C2: 1 | D2: Suwon | E2: Electronics | F2: Consumer Electronics & Semiconductors | G2: Public | H2: 1969 | I2: Verification Pending | J2: https://www.samsung.com | K2: World's largest maker of smartphones, memory chips, and displays. | L2: World's largest maker of smartphones, memory chips, and displays | M2: KRX | N2: 005930 | O2: Verification Pending | P2: Verification Pending | Q2: Verification Pending | R2: Verification Pending | S2: N/A | T2: Company knowledge base (stable facts) | U2: Needs financial/leadership verification | V2: 2026-07-18
A3: South Korea | B3: SK Hynix | C3: 2 | D3: Icheon | E3: Semiconductors | F3: Memory Chips | G3: Public | H3: 1983 | I3: Verification Pending | J3: https://www.skhynix.com | K3: Second-largest global memory chip maker. | L3: Second-largest global memory chip maker | M3: KRX | N3: 000660 | O3: Verification Pending | P3: Verification Pending | Q3: Verification Pending | R3: Verification Pending | S3: N/A | T3: Company knowledge base (stable facts) | U3: Needs financial/leadership verification | V3: 2026-07-18
A4: South Korea | B4: Hyundai Motor Company | C4: 3 | D4: Seoul | E4: Automotive | F4: Auto Manufacturing | G4: Public | H4: 1967 | I4: Verification Pending | J4: https://www.hyundai.com | K4: South Korea's largest automaker. | L4: South Korea's largest automaker | M4: KRX | N4: 005380 | O4: Verification Pending | P4: Verification Pending | Q4: Verification Pending | R4: Verification Pending | S4: N/A | T4: Company knowledge base (stable facts) | U4: Needs financial/leadership verification | V4: 2026-07-18
A5: South Korea | B5: LG Electronics | C5: 4 | D5: Seoul | E5: Electronics | F5: Consumer Electronics & Appliances | G5: Public | H5: 1958 | I5: Verification Pending | J5: https://www.lg.com | K5: Consumer electronics, home appliances, and displays manufacturer. | L5: Consumer electronics, home appliances, and displays manufacturer | M5: KRX | N5: 066570 | O5: Verification Pending | P5: Verification Pending | Q5: Verification Pending | R5: Verification Pending | S5: N/A | T5: Company knowledge base (stable facts) | U5: Needs financial/leadership verification | V5: 2026-07-18
A6: South Korea | B6: POSCO Holdings | C6: 5 | D6: Pohang | E6: Steel | F6: Metals & Mining | G6: Public | H6: 1968 | I6: Verification Pending | J6: https://www.posco-holdings.com | K6: One of the world's largest steel producers. | L6: One of the world's largest steel producers | M6: KRX | N6: 005490 | O6: Verification Pending | P6: Verification Pending | Q6: Verification Pending | R6: Verification Pending | S6: N/A | T6: Company knowledge base (stable facts) | U6: Needs financial/leadership verification | V6: 2026-07-18
A8: Note: | B8: Company identity, industry, HQ, founding year, and website are stable facts. 'Verification Pending' fields (CEO, revenue, net income, market cap, Fortune 500 rank) change frequently and require a live data-verification pass before use in analysis.

Sheet Australia
A1: Rank | B1: Company Name | C1: Country | D1: HQ City | E1: Industry | F1: Sector | G1: Company Type | H1: Founded Year | I1: CEO | J1: Official Website | K1: Business Description | L1: Main Products/Services | M1: Stock Exchange | N1: Ticker Symbol | O1: Annual Revenue (USD) | P1: Net Income (USD) | Q1: Market Cap (USD) | R1: Fortune Global 500 Rank | S1: Parent Company | T1: Data Source | U1: Verification Status | V1: Last Updated
A2: Australia | B2: BHP Group | C2: 1 | D2: Melbourne | E2: Mining | F2: Metals & Mining | G2: Public | H2: 1885 | I2: Verification Pending | J2: https://www.bhp.com | K2: World's largest mining company by market cap. | L2: World's largest mining company by market cap | M2: ASX | N2: BHP | O2: Verification Pending | P2: Verification Pending | Q2: Verification Pending | R2: Verification Pending | S2: N/A | T2: Company knowledge base (stable facts) | U2: Needs financial/leadership verification | V2: 2026-07-18
A3: Australia | B3: Commonwealth Bank of Australia | C3: 2 | D3: Sydney | E3: Banking | F3: Financial Services | G3: Public | H3: 1911 | I3: Verification Pending | J3: https://www.commbank.com.au | K3: Australia's largest bank by market capitalization. | L3: Australia's largest bank by market capitalization | M3: ASX | N3: CBA | O3: Verification Pending | P3: Verification Pending | Q3: Verification Pending | R3: Verification Pending | S3: N/A | T3: Company knowledge base (stable facts) | U3: Needs financial/leadership verification | V3: 2026-07-18
A4: Australia | B4: Rio Tinto | C4: 3 | D4: Melbourne/London | E4: Mining | F4: Metals & Mining | G4: Public | H4: 1873 | I4: Verification Pending | J4: https://www.riotinto.com | K4: Major global mining and metals company. | L4: Major global mining and metals company | M4: ASX/LSE | N4: RIO | O4: Verification Pending | P4: Verification Pending | Q4: Verification Pending | R4: Verification Pending | S4: N/A | T4: Company knowledge base (stable facts) | U4: Needs financial/leadership verification | V4: 2026-07-18
A5: Australia | B5: Westpac Banking Corporation | C5: 4 | D5: Sydney | E5: Banking | F5: Financial Services | G5: Public | H5: 1817 | I5: Verification Pending | J5: https://www.westpac.com.au | K5: One of Australia's 'Big Four' banks. | L5: One of Australia's 'Big Four' banks | M5: ASX | N5: WBC | O5: Verification Pending | P5: Verification Pending | Q5: Verification Pending | R5: Verification Pending | S5: N/A | T5: Company knowledge base (stable facts) | U5: Needs financial/leadership verification | V5: 2026-07-18
A6: Australia | B6: Woolworths Group | C6: 5 | D6: Sydney | E6: Retail | F6: Grocery Retail | G6: Public | H6: 1924 | I6: Verification Pending | J6: https://www.woolworthsgroup.com.au | K6: Australia's largest supermarket and retail group. | L6: Australia's largest supermarket and retail group | M6: ASX | N6: WOW | O6: Verification Pending | P6: Verification Pending | Q6: Verification Pending | R6: Verification Pending | S6: N/A | T6: Company knowledge base (stable facts) | U6: Needs financial/leadership verification | V6: 2026-07-18
A8: Note: | B8: Company identity, industry, HQ, founding year, and website are stable facts. 'Verification Pending' fields (CEO, revenue, net income, market cap, Fortune 500 rank) change frequently and require a live data-verification pass before use in analysis.

Sheet Spain
A1: Rank | B1: Company Name | C1: Country | D1: HQ City | E1: Industry | F1: Sector | G1: Company Type | H1: Founded Year | I1: CEO | J1: Official Website | K1: Business Description | L1: Main Products/Services | M1: Stock Exchange | N1: Ticker Symbol | O1: Annual Revenue (USD) | P1: Net Income (USD) | Q1: Market Cap (USD) | R1: Fortune Global 500 Rank | S1: Parent Company | T1: Data Source | U1: Verification Status | V1: Last Updated
A2: Spain | B2: Banco Santander | C2: 1 | D2: Madrid | E2: Banking | F2: Financial Services | G2: Public | H2: 1857 | I2: Verification Pending | J2: https://www.santander.com | K2: One of the largest banks in the Eurozone with large Latin America presence. | L2: One of the largest banks in the Eurozone with large Latin America presence | M2: BME | N2: SAN | O2: Verification Pending | P2: Verification Pending | Q2: Verification Pending | R2: Verification Pending | S2: N/A | T2: Company knowledge base (stable facts) | U2: Needs financial/leadership verification | V2: 2026-07-18
A3: Spain | B3: Iberdrola | C3: 2 | D3: Bilbao | E3: Utilities | F3: Electric Power & Renewables | G3: Public | H3: 1992 | I3: Verification Pending | J3: https://www.iberdrola.com | K3: Global leader in renewable energy generation. | L3: Global leader in renewable energy generation | M3: BME | N3: IBE | O3: Verification Pending | P3: Verification Pending | Q3: Verification Pending | R3: Verification Pending | S3: N/A | T3: Company knowledge base (stable facts) | U3: Needs financial/leadership verification | V3: 2026-07-18
A4: Spain | B4: Inditex (Zara) | C4: 3 | D4: Arteixo | E4: Retail | F4: Apparel Retail | G4: Public | H4: 1985 | I4: Verification Pending | J4: https://www.inditex.com | K4: World's largest fashion retailer, owner of Zara. | L4: World's largest fashion retailer, owner of Zara | M4: BME | N4: ITX | O4: Verification Pending | P4: Verification Pending | Q4: Verification Pending | R4: Verification Pending | S4: N/A | T4: Company knowledge base (stable facts) | U4: Needs financial/leadership verification | V4: 2026-07-18
A5: Spain | B5: Repsol | C5: 4 | D5: Madrid | E5: Oil & Gas | F5: Energy | G5: Public | H5: 1987 | I5: Verification Pending | J5: https://www.repsol.com | K5: Integrated energy company in oil, gas, and renewables. | L5: Integrated energy company in oil, gas, and renewables | M5: BME | N5: REP | O5: Verification Pending | P5: Verification Pending | Q5: Verification Pending | R5: Verification Pending | S5: N/A | T5: Company knowledge base (stable facts) | U5: Needs financial/leadership verification | V5: 2026-07-18
A6: Spain | B6: BBVA | C6: 5 | D6: Bilbao/Madrid | E6: Banking | F6: Financial Services | G6: Public | H6: 1857 | I6: Verification Pending | J6: https://www.bbva.com | K6: Major multinational Spanish bank. | L6: Major multinational Spanish bank | M6: BME | N6: BBVA | O6: Verification Pending | P6: Verification Pending | Q6: Verification Pending | R6: Verification Pending | S6: N/A | T6: Company knowledge base (stable facts) | U6: Needs financial/leadership verification | V6: 2026-07-18
A8: Note: | B8: Company identity, industry, HQ, founding year, and website are stable facts. 'Verification Pending' fields (CEO, revenue, net income, market cap, Fortune 500 rank) change frequently and require a live data-verification pass before use in analysis.

Sheet Mexico
A1: Rank | B1: Company Name | C1: Country | D1: HQ City | E1: Industry | F1: Sector | G1: Company Type | H1: Founded Year | I1: CEO | J1: Official Website | K1: Business Description | L1: Main Products/Services | M1: Stock Exchange | N1: Ticker Symbol | O1: Annual Revenue (USD) | P1: Net Income (USD) | Q1: Market Cap (USD) | R1: Fortune Global 500 Rank | S1: Parent Company | T1: Data Source | U1: Verification Status | V1: Last Updated
A2: Mexico | B2: America Movil | C2: 1 | D2: Mexico City | E2: Telecommunications | F2: Telecom Services | G2: Public | H2: 2000 | I2: Verification Pending | J2: https://www.americamovil.com | K2: Latin America's largest telecom carrier. | L2: Latin America's largest telecom carrier | M2: BMV/NYSE | N2: AMX | O2: Verification Pending | P2: Verification Pending | Q2: Verification Pending | R2: Verification Pending | S2: N/A | T2: Company knowledge base (stable facts) | U2: Needs financial/leadership verification | V2: 2026-07-18
A3: Mexico | B3: Femsa | C3: 2 | D3: Monterrey | E3: Beverages/Retail | F3: Beverages & Convenience Retail | G3: Public | H3: 1890 | I3: Verification Pending | J3: https://www.femsa.com | K3: Beverage bottler (Coca-Cola FEMSA) and OXXO convenience store operator. | L3: Beverage bottler (Coca-Cola FEMSA) and OXXO convenience store operator | M3: BMV/NYSE | N3: FEMSAUBD | O3: Verification Pending | P3: Verification Pending | Q3: Verification Pending | R3: Verification Pending | S3: N/A | T3: Company knowledge base (stable facts) | U3: Needs financial/leadership verification | V3: 2026-07-18
A4: Mexico | B4: Grupo Mexico | C4: 3 | D4: Mexico City | E4: Mining | F4: Metals & Mining | G4: Public | H4: 1942 | I4: Verification Pending | J4: https://www.gmexico.com | K4: One of the world's largest copper mining companies. | L4: One of the world's largest copper mining companies | M4: BMV | N4: GMEXICOB | O4: Verification Pending | P4: Verification Pending | Q4: Verification Pending | R4: Verification Pending | S4: N/A | T4: Company knowledge base (stable facts) | U4: Needs financial/leadership verification | V4: 2026-07-18
A5: Mexico | B5: Cemex | C5: 4 | D5: Monterrey | E5: Cement | F5: Building Materials | G5: Public | H5: 1906 | I5: Verification Pending | J5: https://www.cemex.com | K5: Global building materials and cement producer. | L5: Global building materials and cement producer | M5: BMV/NYSE | N5: CEMEXCPO | O5: Verification Pending | P5: Verification Pending | Q5: Verification Pending | R5: Verification Pending | S5: N/A | T5: Company knowledge base (stable facts) | U5: Needs financial/leadership verification | V5: 2026-07-18
A6: Mexico | B6: Pemex | C6: 5 | D6: Mexico City | E6: Oil & Gas | F6: Energy | G6: State-Owned | H6: 1938 | I6: Verification Pending | J6: https://www.pemex.com | K6: Mexico's state-owned petroleum company. | L6: Mexico's state-owned petroleum company | M6: State-owned | N6: N/A | O6: Verification Pending | P6: Verification Pending | Q6: Verification Pending | R6: Verification Pending | S6: N/A | T6: Company knowledge base (stable facts) | U6: Needs financial/leadership verification | V6: 2026-07-18
A8: Note: | B8: Company identity, industry, HQ, founding year, and website are stable facts. 'Verification Pending' fields (CEO, revenue, net income, market cap, Fortune 500 rank) change frequently and require a live data-verification pass before use in analysis.

Sheet Indonesia
A1: Rank | B1: Company Name | C1: Country | D1: HQ City | E1: Industry | F1: Sector | G1: Company Type | H1: Founded Year | I1: CEO | J1: Official Website | K1: Business Description | L1: Main Products/Services | M1: Stock Exchange | N1: Ticker Symbol | O1: Annual Revenue (USD) | P1: Net Income (USD) | Q1: Market Cap (USD) | R1: Fortune Global 500 Rank | S1: Parent Company | T1: Data Source | U1: Verification Status | V1: Last Updated
A2: Indonesia | B2: Bank Central Asia | C2: 1 | D2: Jakarta | E2: Banking | F2: Financial Services | G2: Public | H2: 1957 | I2: Verification Pending | J2: https://www.bca.co.id | K2: Indonesia's largest private bank. | L2: Indonesia's largest private bank | M2: IDX | N2: BBCA | O2: Verification Pending | P2: Verification Pending | Q2: Verification Pending | R2: Verification Pending | S2: N/A | T2: Company knowledge base (stable facts) | U2: Needs financial/leadership verification | V2: 2026-07-18
A3: Indonesia | B3: Bank Rakyat Indonesia | C3: 2 | D3: Jakarta | E3: Banking | F3: Financial Services | G3: State-Owned | H3: 1895 | I3: Verification Pending | J3: https://bri.co.id | K3: Largest bank by assets, focused on micro and SME lending. | L3: Largest bank by assets, focused on micro and SME lending | M3: IDX | N3: BBRI | O3: Verification Pending | P3: Verification Pending | Q3: Verification Pending | R3: Verification Pending | S3: N/A | T3: Company knowledge base (stable facts) | U3: Needs financial/leadership verification | V3: 2026-07-18
A4: Indonesia | B4: Telkom Indonesia | C4: 3 | D4: Bandung | E4: Telecommunications | F4: Telecom Services | G4: State-Owned | H4: 1991 | I4: Verification Pending | J4: https://www.telkom.co.id | K4: Indonesia's largest telecommunications provider. | L4: Indonesia's largest telecommunications provider | M4: IDX/NYSE | N4: TLKM | O4: Verification Pending | P4: Verification Pending | Q4: Verification Pending | R4: Verification Pending | S4: N/A | T4: Company knowledge base (stable facts) | U4: Needs financial/leadership verification | V4: 2026-07-18
A5: Indonesia | B5: Astra International | C5: 4 | D5: Jakarta | E5: Conglomerate | F5: Automotive & Agribusiness | G5: Public | H5: 1957 | I5: Verification Pending | J5: https://www.astra.co.id | K5: Diversified conglomerate in automotive, agribusiness, and financial services. | L5: Diversified conglomerate in automotive, agribusiness, and financial services | M5: IDX | N5: ASII | O5: Verification Pending | P5: Verification Pending | Q5: Verification Pending | R5: Verification Pending | S5: N/A | T5: Company knowledge base (stable facts) | U5: Needs financial/leadership verification | V5: 2026-07-18
A6: Indonesia | B6: Pertamina | C6: 5 | D6: Jakarta | E6: Oil & Gas | F6: Energy | G6: State-Owned | H6: 1957 | I6: Verification Pending | J6: https://www.pertamina.com | K6: Indonesia's state-owned oil and gas company. | L6: Indonesia's state-owned oil and gas company | M6: State-owned | N6: N/A | O6: Verification Pending | P6: Verification Pending | Q6: Verification Pending | R6: Verification Pending | S6: N/A | T6: Company knowledge base (stable facts) | U6: Needs financial/leadership verification | V6: 2026-07-18
A8: Note: | B8: Company identity, industry, HQ, founding year, and website are stable facts. 'Verification Pending' fields (CEO, revenue, net income, market cap, Fortune 500 rank) change frequently and require a live data-verification pass before use in analysis.

Sheet Netherlands
A1: Rank | B1: Company Name | C1: Country | D1: HQ City | E1: Industry | F1: Sector | G1: Company Type | H1: Founded Year | I1: CEO | J1: Official Website | K1: Business Description | L1: Main Products/Services | M1: Stock Exchange | N1: Ticker Symbol | O1: Annual Revenue (USD) | P1: Net Income (USD) | Q1: Market Cap (USD) | R1: Fortune Global 500 Rank | S1: Parent Company | T1: Data Source | U1: Verification Status | V1: Last Updated
A2: Netherlands | B2: Shell plc | C2: 1 | D2: The Hague | E2: Oil & Gas | F2: Energy | G2: Public | H2: 1907 | I2: Verification Pending | J2: https://www.shell.com | K2: Global integrated energy company (dual-listed/HQ London since 2022). | L2: Global integrated energy company (dual-listed/HQ London since 2022) | M2: Euronext Amsterdam/LSE | N2: SHEL | O2: Verification Pending | P2: Verification Pending | Q2: Verification Pending | R2: Verification Pending | S2: N/A | T2: Company knowledge base (stable facts) | U2: Needs financial/leadership verification | V2: 2026-07-18
A3: Netherlands | B3: ASML Holding | C3: 2 | D3: Veldhoven | E3: Semiconductors | F3: Semiconductor Equipment | G3: Public | H3: 1984 | I3: Verification Pending | J3: https://www.asml.com | K3: Sole global supplier of extreme ultraviolet (EUV) lithography machines. | L3: Sole global supplier of extreme ultraviolet (EUV) lithography machines | M3: Euronext Amsterdam/NASDAQ | N3: ASML | O3: Verification Pending | P3: Verification Pending | Q3: Verification Pending | R3: Verification Pending | S3: N/A | T3: Company knowledge base (stable facts) | U3: Needs financial/leadership verification | V3: 2026-07-18
A4: Netherlands | B4: ING Group | C4: 3 | D4: Amsterdam | E4: Banking | F4: Financial Services | G4: Public | H4: 1991 | I4: Verification Pending | J4: https://www.ing.com | K4: Major Dutch multinational bank. | L4: Major Dutch multinational bank | M4: Euronext Amsterdam | N4: INGA | O4: Verification Pending | P4: Verification Pending | Q4: Verification Pending | R4: Verification Pending | S4: N/A | T4: Company knowledge base (stable facts) | U4: Needs financial/leadership verification | V4: 2026-07-18
A5: Netherlands | B5: Heineken N.V. | C5: 4 | D5: Amsterdam | E5: Beverages | F5: Brewing | G5: Public | H5: 1864 | I5: Verification Pending | J5: https://www.theheinekencompany.com | K5: World's second-largest brewer. | L5: World's second-largest brewer | M5: Euronext Amsterdam | N5: HEIA | O5: Verification Pending | P5: Verification Pending | Q5: Verification Pending | R5: Verification Pending | S5: N/A | T5: Company knowledge base (stable facts) | U5: Needs financial/leadership verification | V5: 2026-07-18
A6: Netherlands | B6: Unilever | C6: 5 | D6: London/Rotterdam heritage | E6: Consumer Goods | F6: FMCG | G6: Public | H6: 1929 | I6: Verification Pending | J6: https://www.unilever.com | K6: Global consumer goods company (Anglo-Dutch heritage, UK-headquartered). | L6: Global consumer goods company (Anglo-Dutch heritage, UK-headquartered) | M6: Euronext Amsterdam/LSE | N6: ULVR | O6: Verification Pending | P6: Verification Pending | Q6: Verification Pending | R6: Verification Pending | S6: N/A | T6: Company knowledge base (stable facts) | U6: Needs financial/leadership verification | V6: 2026-07-18
A8: Note: | B8: Company identity, industry, HQ, founding year, and website are stable facts. 'Verification Pending' fields (CEO, revenue, net income, market cap, Fortune 500 rank) change frequently and require a live data-verification pass before use in analysis.

Sheet Saudi Arabia
A1: Rank | B1: Company Name | C1: Country | D1: HQ City | E1: Industry | F1: Sector | G1: Company Type | H1: Founded Year | I1: CEO | J1: Official Website | K1: Business Description | L1: Main Products/Services | M1: Stock Exchange | N1: Ticker Symbol | O1: Annual Revenue (USD) | P1: Net Income (USD) | Q1: Market Cap (USD) | R1: Fortune Global 500 Rank | S1: Parent Company | T1: Data Source | U1: Verification Status | V1: Last Updated
A2: Saudi Arabia | B2: Saudi Aramco | C2: 1 | D2: Dhahran | E2: Oil & Gas | F2: Energy | G2: State-Owned/Public | H2: 1933 | I2: Verification Pending | J2: https://www.aramco.com | K2: World's largest oil producer and most valuable energy company. | L2: World's largest oil producer and most valuable energy company | M2: Tadawul | N2: 2222 | O2: Verification Pending | P2: Verification Pending | Q2: Verification Pending | R2: Verification Pending | S2: N/A | T2: Company knowledge base (stable facts) | U2: Needs financial/leadership verification | V2: 2026-07-18
A3: Saudi Arabia | B3: SABIC | C3: 2 | D3: Riyadh | E3: Chemicals | F3: Petrochemicals | G3: Public | H3: 1976 | I3: Verification Pending | J3: https://www.sabic.com | K3: One of the world's largest petrochemical manufacturers. | L3: One of the world's largest petrochemical manufacturers | M3: Tadawul | N3: 2010 | O3: Verification Pending | P3: Verification Pending | Q3: Verification Pending | R3: Verification Pending | S3: N/A | T3: Company knowledge base (stable facts) | U3: Needs financial/leadership verification | V3: 2026-07-18
A4: Saudi Arabia | B4: Al Rajhi Bank | C4: 3 | D4: Riyadh | E4: Banking | F4: Financial Services | G4: Public | H4: 1957 | I4: Verification Pending | J4: https://www.alrajhibank.com.sa | K4: World's largest Islamic bank. | L4: World's largest Islamic bank | M4: Tadawul | N4: 1120 | O4: Verification Pending | P4: Verification Pending | Q4: Verification Pending | R4: Verification Pending | S4: N/A | T4: Company knowledge base (stable facts) | U4: Needs financial/leadership verification | V4: 2026-07-18
A5: Saudi Arabia | B5: Saudi Telecom Company (STC) | C5: 4 | D5: Riyadh | E5: Telecommunications | F5: Telecom Services | G5: Public | H5: 1998 | I5: Verification Pending | J5: https://www.stc.com.sa | K5: Saudi Arabia's largest telecommunications provider. | L5: Saudi Arabia's largest telecommunications provider | M5: Tadawul | N5: 7010 | O5: Verification Pending | P5: Verification Pending | Q5: Verification Pending | R5: Verification Pending | S5: N/A | T5: Company knowledge base (stable facts) | U5: Needs financial/leadership verification | V5: 2026-07-18
A6: Saudi Arabia | B6: Saudi Electricity Company | C6: 5 | D6: Riyadh | E6: Utilities | F6: Electric Power | G6: Public | H6: 2000 | I6: Verification Pending | J6: https://www.se.com.sa | K6: Primary electricity generation and distribution company in Saudi Arabia. | L6: Primary electricity generation and distribution company in Saudi Arabia | M6: Tadawul | N6: 5110 | O6: Verification Pending | P6: Verification Pending | Q6: Verification Pending | R6: Verification Pending | S6: N/A | T6: Company knowledge base (stable facts) | U6: Needs financial/leadership verification | V6: 2026-07-18
A8: Note: | B8: Company identity, industry, HQ, founding year, and website are stable facts. 'Verification Pending' fields (CEO, revenue, net income, market cap, Fortune 500 rank) change frequently and require a live data-verification pass before use in analysis.

Sheet Turkey
A1: Rank | B1: Company Name | C1: Country | D1: HQ City | E1: Industry | F1: Sector | G1: Company Type | H1: Founded Year | I1: CEO | J1: Official Website | K1: Business Description | L1: Main Products/Services | M1: Stock Exchange | N1: Ticker Symbol | O1: Annual Revenue (USD) | P1: Net Income (USD) | Q1: Market Cap (USD) | R1: Fortune Global 500 Rank | S1: Parent Company | T1: Data Source | U1: Verification Status | V1: Last Updated
A2: Turkey | B2: Turkish Airlines | C2: 1 | D2: Istanbul | E2: Aviation | F2: Airlines | G2: Public | H2: 1933 | I2: Verification Pending | J2: https://www.turkishairlines.com | K2: Turkey's flag carrier airline, flying to more countries than any other airline. | L2: Turkey's flag carrier airline, flying to more countries than any other airline | M2: BIST | N2: THYAO | O2: Verification Pending | P2: Verification Pending | Q2: Verification Pending | R2: Verification Pending | S2: N/A | T2: Company knowledge base (stable facts) | U2: Needs financial/leadership verification | V2: 2026-07-18
A3: Turkey | B3: Koc Holding | C3: 2 | D3: Istanbul | E3: Conglomerate | F3: Diversified Industrial | G3: Public | H3: 1926 | I3: Verification Pending | J3: https://www.koc.com.tr | K3: Turkey's largest industrial and financial conglomerate. | L3: Turkey's largest industrial and financial conglomerate | M3: BIST | N3: KCHOL | O3: Verification Pending | P3: Verification Pending | Q3: Verification Pending | R3: Verification Pending | S3: N/A | T3: Company knowledge base (stable facts) | U3: Needs financial/leadership verification | V3: 2026-07-18
A4: Turkey | B4: Turkiye Is Bankasi (Isbank) | C4: 3 | D4: Istanbul | E4: Banking | F4: Financial Services | G4: Public | H4: 1924 | I4: Verification Pending | J4: https://www.isbank.com.tr | K4: One of Turkey's largest private banks. | L4: One of Turkey's largest private banks | M4: BIST | N4: ISCTR | O4: Verification Pending | P4: Verification Pending | Q4: Verification Pending | R4: Verification Pending | S4: N/A | T4: Company knowledge base (stable facts) | U4: Needs financial/leadership verification | V4: 2026-07-18
A5: Turkey | B5: BOTAS | C5: 4 | D5: Ankara | E5: Oil & Gas | F5: Energy Infrastructure | G5: State-Owned | H5: 1974 | I5: Verification Pending | J5: https://www.botas.gov.tr | K5: State pipeline company for petroleum and natural gas transport. | L5: State pipeline company for petroleum and natural gas transport | M5: State-owned | N5: N/A | O5: Verification Pending | P5: Verification Pending | Q5: Verification Pending | R5: Verification Pending | S5: N/A | T5: Company knowledge base (stable facts) | U5: Needs financial/leadership verification | V5: 2026-07-18
A6: Turkey | B6: Sabanci Holding | C6: 5 | D6: Istanbul | E6: Conglomerate | F6: Diversified Industrial | G6: Public | H6: 1967 | I6: Verification Pending | J6: https://www.sabanci.com | K6: Major diversified conglomerate in banking, energy, and industrials. | L6: Major diversified conglomerate in banking, energy, and industrials | M6: BIST | N6: SAHOL | O6: Verification Pending | P6: Verification Pending | Q6: Verification Pending | R6: Verification Pending | S6: N/A | T6: Company knowledge base (stable facts) | U6: Needs financial/leadership verification | V6: 2026-07-18
A8: Note: | B8: Company identity, industry, HQ, founding year, and website are stable facts. 'Verification Pending' fields (CEO, revenue, net income, market cap, Fortune 500 rank) change frequently and require a live data-verification pass before use in analysis.

Sheet Switzerland
A1: Rank | B1: Company Name | C1: Country | D1: HQ City | E1: Industry | F1: Sector | G1: Company Type | H1: Founded Year | I1: CEO | J1: Official Website | K1: Business Description | L1: Main Products/Services | M1: Stock Exchange | N1: Ticker Symbol | O1: Annual Revenue (USD) | P1: Net Income (USD) | Q1: Market Cap (USD) | R1: Fortune Global 500 Rank | S1: Parent Company | T1: Data Source | U1: Verification Status | V1: Last Updated
A2: Switzerland | B2: Nestle S.A. | C2: 1 | D2: Vevey | E2: Food & Beverage | F2: Packaged Foods | G2: Public | H2: 1866 | I2: Verification Pending | J2: https://www.nestle.com | K2: World's largest food and beverage company. | L2: World's largest food and beverage company | M2: SIX | N2: NESN | O2: Verification Pending | P2: Verification Pending | Q2: Verification Pending | R2: Verification Pending | S2: N/A | T2: Company knowledge base (stable facts) | U2: Needs financial/leadership verification | V2: 2026-07-18
A3: Switzerland | B3: Roche Holding | C3: 2 | D3: Basel | E3: Pharmaceuticals | F3: Biopharmaceuticals & Diagnostics | G3: Public | H3: 1896 | I3: Verification Pending | J3: https://www.roche.com | K3: Global leader in pharmaceuticals and in-vitro diagnostics. | L3: Global leader in pharmaceuticals and in-vitro diagnostics | M3: SIX | N3: ROG | O3: Verification Pending | P3: Verification Pending | Q3: Verification Pending | R3: Verification Pending | S3: N/A | T3: Company knowledge base (stable facts) | U3: Needs financial/leadership verification | V3: 2026-07-18
A4: Switzerland | B4: Novartis AG | C4: 3 | D4: Basel | E4: Pharmaceuticals | F4: Biopharmaceuticals | G4: Public | H4: 1996 | I4: Verification Pending | J4: https://www.novartis.com | K4: Global pharmaceutical company focused on innovative medicines. | L4: Global pharmaceutical company focused on innovative medicines | M4: SIX | N4: NOVN | O4: Verification Pending | P4: Verification Pending | Q4: Verification Pending | R4: Verification Pending | S4: N/A | T4: Company knowledge base (stable facts) | U4: Needs financial/leadership verification | V4: 2026-07-18
A5: Switzerland | B5: UBS Group | C5: 4 | D5: Zurich | E5: Banking | F5: Financial Services | G5: Public | H5: 1862 | I5: Verification Pending | J5: https://www.ubs.com | K5: Switzerland's largest bank, following 2023 acquisition of Credit Suisse. | L5: Switzerland's largest bank, following 2023 acquisition of Credit Suisse | M5: SIX/NYSE | N5: UBSG | O5: Verification Pending | P5: Verification Pending | Q5: Verification Pending | R5: Verification Pending | S5: N/A | T5: Company knowledge base (stable facts) | U5: Needs financial/leadership verification | V5: 2026-07-18
A6: Switzerland | B6: Glencore | C6: 5 | D6: Baar | E6: Mining/Commodities | F6: Metals, Mining & Trading | G6: Public | H6: 1974 | I6: Verification Pending | J6: https://www.glencore.com | K6: Global commodities trading and mining conglomerate. | L6: Global commodities trading and mining conglomerate | M6: LSE | N6: GLEN | O6: Verification Pending | P6: Verification Pending | Q6: Verification Pending | R6: Verification Pending | S6: N/A | T6: Company knowledge base (stable facts) | U6: Needs financial/leadership verification | V6: 2026-07-18
A8: Note: | B8: Company identity, industry, HQ, founding year, and website are stable facts. 'Verification Pending' fields (CEO, revenue, net income, market cap, Fortune 500 rank) change frequently and require a live data-verification pass before use in analysis.

Sheet Poland
A1: Rank | B1: Company Name | C1: Country | D1: HQ City | E1: Industry | F1: Sector | G1: Company Type | H1: Founded Year | I1: CEO | J1: Official Website | K1: Business Description | L1: Main Products/Services | M1: Stock Exchange | N1: Ticker Symbol | O1: Annual Revenue (USD) | P1: Net Income (USD) | Q1: Market Cap (USD) | R1: Fortune Global 500 Rank | S1: Parent Company | T1: Data Source | U1: Verification Status | V1: Last Updated
A2: Poland | B2: PKN Orlen | C2: 1 | D2: Plock | E2: Oil & Gas | F2: Energy | G2: Public | H2: 1999 | I2: Verification Pending | J2: https://www.orlen.pl | K2: Central Europe's largest oil refiner and fuel retailer. | L2: Central Europe's largest oil refiner and fuel retailer | M2: GPW | N2: PKN | O2: Verification Pending | P2: Verification Pending | Q2: Verification Pending | R2: Verification Pending | S2: N/A | T2: Company knowledge base (stable facts) | U2: Needs financial/leadership verification | V2: 2026-07-18
A3: Poland | B3: PKO Bank Polski | C3: 2 | D3: Warsaw | E3: Banking | F3: Financial Services | G3: Public | H3: 1919 | I3: Verification Pending | J3: https://www.pkobp.pl | K3: Poland's largest bank by assets. | L3: Poland's largest bank by assets | M3: GPW | N3: PKO | O3: Verification Pending | P3: Verification Pending | Q3: Verification Pending | R3: Verification Pending | S3: N/A | T3: Company knowledge base (stable facts) | U3: Needs financial/leadership verification | V3: 2026-07-18
A4: Poland | B4: KGHM Polska Miedz | C4: 3 | D4: Lubin | E4: Mining | F4: Metals & Mining | G4: Public | H4: 1961 | I4: Verification Pending | J4: https://kghm.com | K4: Major global copper and silver producer. | L4: Major global copper and silver producer | M4: GPW | N4: KGH | O4: Verification Pending | P4: Verification Pending | Q4: Verification Pending | R4: Verification Pending | S4: N/A | T4: Company knowledge base (stable facts) | U4: Needs financial/leadership verification | V4: 2026-07-18
A5: Poland | B5: PGE Polska Grupa Energetyczna | C5: 4 | D5: Warsaw | E5: Utilities | F5: Electric Power | G5: State-Owned | H5: 1990 | I5: Verification Pending | J5: https://www.gkpge.pl | K5: Poland's largest electricity producer. | L5: Poland's largest electricity producer | M5: GPW | N5: PGE | O5: Verification Pending | P5: Verification Pending | Q5: Verification Pending | R5: Verification Pending | S5: N/A | T5: Company knowledge base (stable facts) | U5: Needs financial/leadership verification | V5: 2026-07-18
A6: Poland | B6: Bank Pekao | C6: 5 | D6: Warsaw | E6: Banking | F6: Financial Services | G6: Public | H6: 1929 | I6: Verification Pending | J6: https://www.pekao.com.pl | K6: One of Poland's largest banks. | L6: One of Poland's largest banks | M6: GPW | N6: PEO | O6: Verification Pending | P6: Verification Pending | Q6: Verification Pending | R6: Verification Pending | S6: N/A | T6: Company knowledge base (stable facts) | U6: Needs financial/leadership verification | V6: 2026-07-18
A8: Note: | B8: Company identity, industry, HQ, founding year, and website are stable facts. 'Verification Pending' fields (CEO, revenue, net income, market cap, Fortune 500 rank) change frequently and require a live data-verification pass before use in analysis.

Sheet Taiwan
A1: Rank | B1: Company Name | C1: Country | D1: HQ City | E1: Industry | F1: Sector | G1: Company Type | H1: Founded Year | I1: CEO | J1: Official Website | K1: Business Description | L1: Main Products/Services | M1: Stock Exchange | N1: Ticker Symbol | O1: Annual Revenue (USD) | P1: Net Income (USD) | Q1: Market Cap (USD) | R1: Fortune Global 500 Rank | S1: Parent Company | T1: Data Source | U1: Verification Status | V1: Last Updated
A2: Taiwan | B2: Taiwan Semiconductor Manufacturing Company (TSMC) | C2: 1 | D2: Hsinchu | E2: Semiconductors | F2: Semiconductor Foundry | G2: Public | H2: 1987 | I2: Verification Pending | J2: https://www.tsmc.com | K2: World's largest and most advanced semiconductor contract manufacturer. | L2: World's largest and most advanced semiconductor contract manufacturer | M2: TWSE/NYSE | N2: 2330 | O2: Verification Pending | P2: Verification Pending | Q2: Verification Pending | R2: Verification Pending | S2: N/A | T2: Company knowledge base (stable facts) | U2: Needs financial/leadership verification | V2: 2026-07-18
A3: Taiwan | B3: Hon Hai Precision (Foxconn) | C3: 2 | D3: New Taipei City | E3: Electronics | F3: Electronics Manufacturing Services | G3: Public | H3: 1974 | I3: Verification Pending | J3: https://www.foxconn.com | K3: World's largest electronics contract manufacturer, key Apple supplier. | L3: World's largest electronics contract manufacturer, key Apple supplier | M3: TWSE | N3: 2317 | O3: Verification Pending | P3: Verification Pending | Q3: Verification Pending | R3: Verification Pending | S3: N/A | T3: Company knowledge base (stable facts) | U3: Needs financial/leadership verification | V3: 2026-07-18
A4: Taiwan | B4: MediaTek | C4: 3 | D4: Hsinchu | E4: Semiconductors | F4: Fabless Chip Design | G4: Public | H4: 1997 | I4: Verification Pending | J4: https://www.mediatek.com | K4: Major fabless semiconductor company for mobile and IoT chips. | L4: Major fabless semiconductor company for mobile and IoT chips | M4: TWSE | N4: 2454 | O4: Verification Pending | P4: Verification Pending | Q4: Verification Pending | R4: Verification Pending | S4: N/A | T4: Company knowledge base (stable facts) | U4: Needs financial/leadership verification | V4: 2026-07-18
A5: Taiwan | B5: Cathay Financial Holding | C5: 4 | D5: Taipei | E5: Financial Services | F5: Insurance & Banking | G5: Public | H5: 2001 | I5: Verification Pending | J5: https://www.cathayholdings.com | K5: Taiwan's largest financial holding company. | L5: Taiwan's largest financial holding company | M5: TWSE | N5: 2882 | O5: Verification Pending | P5: Verification Pending | Q5: Verification Pending | R5: Verification Pending | S5: N/A | T5: Company knowledge base (stable facts) | U5: Needs financial/leadership verification | V5: 2026-07-18
A6: Taiwan | B6: Chunghwa Telecom | C6: 5 | D6: Taipei | E6: Telecommunications | F6: Telecom Services | G6: Public | H6: 1996 | I6: Verification Pending | J6: https://www.cht.com.tw | K6: Taiwan's largest telecommunications provider. | L6: Taiwan's largest telecommunications provider | M6: TWSE/NYSE | N6: 2412 | O6: Verification Pending | P6: Verification Pending | Q6: Verification Pending | R6: Verification Pending | S6: N/A | T6: Company knowledge base (stable facts) | U6: Needs financial/leadership verification | V6: 2026-07-18
A8: Note: | B8: Company identity, industry, HQ, founding year, and website are stable facts. 'Verification Pending' fields (CEO, revenue, net income, market cap, Fortune 500 rank) change frequently and require a live data-verification pass before use in analysis.

Sheet Belgium
A1: Rank | B1: Company Name | C1: Country | D1: HQ City | E1: Industry | F1: Sector | G1: Company Type | H1: Founded Year | I1: CEO | J1: Official Website | K1: Business Description | L1: Main Products/Services | M1: Stock Exchange | N1: Ticker Symbol | O1: Annual Revenue (USD) | P1: Net Income (USD) | Q1: Market Cap (USD) | R1: Fortune Global 500 Rank | S1: Parent Company | T1: Data Source | U1: Verification Status | V1: Last Updated
A2: Belgium | B2: Anheuser-Busch InBev | C2: 1 | D2: Leuven | E2: Beverages | F2: Brewing | G2: Public | H2: 2008 | I2: Verification Pending | J2: https://www.ab-inbev.com | K2: World's largest brewer, maker of Budweiser and Stella Artois. | L2: World's largest brewer, maker of Budweiser and Stella Artois | M2: Euronext Brussels/NYSE | N2: ABI | O2: Verification Pending | P2: Verification Pending | Q2: Verification Pending | R2: Verification Pending | S2: N/A | T2: Company knowledge base (stable facts) | U2: Needs financial/leadership verification | V2: 2026-07-18
A3: Belgium | B3: KBC Group | C3: 2 | D3: Brussels | E3: Banking | F3: Financial Services & Insurance | G3: Public | H3: 1998 | I3: Verification Pending | J3: https://www.kbc.com | K3: Major Belgian bank-insurance group. | L3: Major Belgian bank-insurance group | M3: Euronext Brussels | N3: KBC | O3: Verification Pending | P3: Verification Pending | Q3: Verification Pending | R3: Verification Pending | S3: N/A | T3: Company knowledge base (stable facts) | U3: Needs financial/leadership verification | V3: 2026-07-18
A4: Belgium | B4: Solvay | C4: 3 | D4: Brussels | E4: Chemicals | F4: Specialty Chemicals | G4: Public | H4: 1863 | I4: Verification Pending | J4: https://www.solvay.com | K4: Global specialty chemicals and materials company. | L4: Global specialty chemicals and materials company | M4: Euronext Brussels | N4: SOLB | O4: Verification Pending | P4: Verification Pending | Q4: Verification Pending | R4: Verification Pending | S4: N/A | T4: Company knowledge base (stable facts) | U4: Needs financial/leadership verification | V4: 2026-07-18
A5: Belgium | B5: UCB S.A. | C5: 4 | D5: Brussels | E5: Pharmaceuticals | F5: Biopharmaceuticals | G5: Public | H5: 1928 | I5: Verification Pending | J5: https://www.ucb.com | K5: Biopharmaceutical company focused on neurology and immunology. | L5: Biopharmaceutical company focused on neurology and immunology | M5: Euronext Brussels | N5: UCB | O5: Verification Pending | P5: Verification Pending | Q5: Verification Pending | R5: Verification Pending | S5: N/A | T5: Company knowledge base (stable facts) | U5: Needs financial/leadership verification | V5: 2026-07-18
A6: Belgium | B6: Ageas | C6: 5 | D6: Brussels | E6: Insurance | F6: Financial Services | G6: Public | H6: 1990 | I6: Verification Pending | J6: https://www.ageas.com | K6: International insurance group. | L6: International insurance group | M6: Euronext Brussels | N6: AGS | O6: Verification Pending | P6: Verification Pending | Q6: Verification Pending | R6: Verification Pending | S6: N/A | T6: Company knowledge base (stable facts) | U6: Needs financial/leadership verification | V6: 2026-07-18
A8: Note: | B8: Company identity, industry, HQ, founding year, and website are stable facts. 'Verification Pending' fields (CEO, revenue, net income, market cap, Fortune 500 rank) change frequently and require a live data-verification pass before use in analysis.

Sheet Argentina
A1: Rank | B1: Company Name | C1: Country | D1: HQ City | E1: Industry | F1: Sector | G1: Company Type | H1: Founded Year | I1: CEO | J1: Official Website | K1: Business Description | L1: Main Products/Services | M1: Stock Exchange | N1: Ticker Symbol | O1: Annual Revenue (USD) | P1: Net Income (USD) | Q1: Market Cap (USD) | R1: Fortune Global 500 Rank | S1: Parent Company | T1: Data Source | U1: Verification Status | V1: Last Updated
A2: Argentina | B2: YPF S.A. | C2: 1 | D2: Buenos Aires | E2: Oil & Gas | F2: Energy | G2: State-Controlled | H2: 1922 | I2: Verification Pending | J2: https://www.ypf.com | K2: Argentina's largest energy company. | L2: Argentina's largest energy company | M2: BYMA/NYSE | N2: YPF | O2: Verification Pending | P2: Verification Pending | Q2: Verification Pending | R2: Verification Pending | S2: N/A | T2: Company knowledge base (stable facts) | U2: Needs financial/leadership verification | V2: 2026-07-18
A3: Argentina | B3: Mercado Libre | C3: 2 | D3: Buenos Aires | E3: E-commerce | F3: Internet Services | G3: Public | H3: 1999 | I3: Verification Pending | J3: https://www.mercadolibre.com | K3: Latin America's largest e-commerce and fintech platform. | L3: Latin America's largest e-commerce and fintech platform | M3: NASDAQ | N3: MELI | O3: Verification Pending | P3: Verification Pending | Q3: Verification Pending | R3: Verification Pending | S3: N/A | T3: Company knowledge base (stable facts) | U3: Needs financial/leadership verification | V3: 2026-07-18
A4: Argentina | B4: Grupo Financiero Galicia | C4: 3 | D4: Buenos Aires | E4: Banking | F4: Financial Services | G4: Public | H4: 1905 | I4: Verification Pending | J4: https://www.gfgsa.com | K4: One of Argentina's largest private banking groups. | L4: One of Argentina's largest private banking groups | M4: BYMA/NASDAQ | N4: GGAL | O4: Verification Pending | P4: Verification Pending | Q4: Verification Pending | R4: Verification Pending | S4: N/A | T4: Company knowledge base (stable facts) | U4: Needs financial/leadership verification | V4: 2026-07-18
A5: Argentina | B5: Pampa Energia | C5: 4 | D5: Buenos Aires | E5: Utilities/Energy | F5: Power & Gas | G5: Public | H5: 1945 | I5: Verification Pending | J5: https://www.pampaenergia.com | K5: Argentina's largest integrated energy company. | L5: Argentina's largest integrated energy company | M5: BYMA/NYSE | N5: PAM | O5: Verification Pending | P5: Verification Pending | Q5: Verification Pending | R5: Verification Pending | S5: N/A | T5: Company knowledge base (stable facts) | U5: Needs financial/leadership verification | V5: 2026-07-18
A6: Argentina | B6: Banco Macro | C6: 5 | D6: Buenos Aires | E6: Banking | F6: Financial Services | G6: Public | H6: 1988 | I6: Verification Pending | J6: https://www.macro.com.ar | K6: Major private Argentine bank focused on regional expansion. | L6: Major private Argentine bank focused on regional expansion | M6: BYMA/NYSE | N6: BMA | O6: Verification Pending | P6: Verification Pending | Q6: Verification Pending | R6: Verification Pending | S6: N/A | T6: Company knowledge base (stable facts) | U6: Needs financial/leadership verification | V6: 2026-07-18
A8: Note: | B8: Company identity, industry, HQ, founding year, and website are stable facts. 'Verification Pending' fields (CEO, revenue, net income, market cap, Fortune 500 rank) change frequently and require a live data-verification pass before use in analysis.

Sheet Sweden
A1: Rank | B1: Company Name | C1: Country | D1: HQ City | E1: Industry | F1: Sector | G1: Company Type | H1: Founded Year | I1: CEO | J1: Official Website | K1: Business Description | L1: Main Products/Services | M1: Stock Exchange | N1: Ticker Symbol | O1: Annual Revenue (USD) | P1: Net Income (USD) | Q1: Market Cap (USD) | R1: Fortune Global 500 Rank | S1: Parent Company | T1: Data Source | U1: Verification Status | V1: Last Updated
A2: Sweden | B2: Volvo Group | C2: 1 | D2: Gothenburg | E2: Automotive | F2: Commercial Vehicles | G2: Public | H2: 1927 | I2: Verification Pending | J2: https://www.volvogroup.com | K2: Major manufacturer of trucks, buses, and construction equipment. | L2: Major manufacturer of trucks, buses, and construction equipment | M2: Nasdaq Stockholm | N2: VOLV-B | O2: Verification Pending | P2: Verification Pending | Q2: Verification Pending | R2: Verification Pending | S2: N/A | T2: Company knowledge base (stable facts) | U2: Needs financial/leadership verification | V2: 2026-07-18
A3: Sweden | B3: Ericsson | C3: 2 | D3: Stockholm | E3: Telecommunications | F3: Networking Equipment | G3: Public | H3: 1876 | I3: Verification Pending | J3: https://www.ericsson.com | K3: Major global telecom network equipment provider. | L3: Major global telecom network equipment provider | M3: Nasdaq Stockholm/NASDAQ | N3: ERIC-B | O3: Verification Pending | P3: Verification Pending | Q3: Verification Pending | R3: Verification Pending | S3: N/A | T3: Company knowledge base (stable facts) | U3: Needs financial/leadership verification | V3: 2026-07-18
A4: Sweden | B4: H&M Group | C4: 3 | D4: Stockholm | E4: Retail | F4: Apparel Retail | G4: Public | H4: 1947 | I4: Verification Pending | J4: https://hmgroup.com | K4: One of the world's largest fashion retailers. | L4: One of the world's largest fashion retailers | M4: Nasdaq Stockholm | N4: HM-B | O4: Verification Pending | P4: Verification Pending | Q4: Verification Pending | R4: Verification Pending | S4: N/A | T4: Company knowledge base (stable facts) | U4: Needs financial/leadership verification | V4: 2026-07-18
A5: Sweden | B5: Atlas Copco | C5: 4 | D5: Nacka | E5: Industrial Manufacturing | F5: Industrial Equipment | G5: Public | H5: 1873 | I5: Verification Pending | J5: https://www.atlascopcogroup.com | K5: Global leader in industrial compressors and equipment. | L5: Global leader in industrial compressors and equipment | M5: Nasdaq Stockholm | N5: ATCO-A | O5: Verification Pending | P5: Verification Pending | Q5: Verification Pending | R5: Verification Pending | S5: N/A | T5: Company knowledge base (stable facts) | U5: Needs financial/leadership verification | V5: 2026-07-18
A6: Sweden | B6: Investor AB | C6: 5 | D6: Stockholm | E6: Investment | F6: Holding Company | G6: Public | H6: 1916 | I6: Verification Pending | J6: https://www.investorab.com | K6: Wallenberg family investment holding company. | L6: Wallenberg family investment holding company | M6: Nasdaq Stockholm | N6: INVE-B | O6: Verification Pending | P6: Verification Pending | Q6: Verification Pending | R6: Verification Pending | S6: N/A | T6: Company knowledge base (stable facts) | U6: Needs financial/leadership verification | V6: 2026-07-18
A8: Note: | B8: Company identity, industry, HQ, founding year, and website are stable facts. 'Verification Pending' fields (CEO, revenue, net income, market cap, Fortune 500 rank) change frequently and require a live data-verification pass before use in analysis.

Sheet Ireland
A1: Rank | B1: Company Name | C1: Country | D1: HQ City | E1: Industry | F1: Sector | G1: Company Type | H1: Founded Year | I1: CEO | J1: Official Website | K1: Business Description | L1: Main Products/Services | M1: Stock Exchange | N1: Ticker Symbol | O1: Annual Revenue (USD) | P1: Net Income (USD) | Q1: Market Cap (USD) | R1: Fortune Global 500 Rank | S1: Parent Company | T1: Data Source | U1: Verification Status | V1: Last Updated
A2: Ireland | B2: CRH plc | C2: 1 | D2: Dublin | E2: Construction | F2: Building Materials | G2: Public | H2: 1970 | I2: Verification Pending | J2: https://www.crh.com | K2: World's largest building materials company. | L2: World's largest building materials company | M2: NYSE/LSE | N2: CRH | O2: Verification Pending | P2: Verification Pending | Q2: Verification Pending | R2: Verification Pending | S2: N/A | T2: Company knowledge base (stable facts) | U2: Needs financial/leadership verification | V2: 2026-07-18
A3: Ireland | B3: Ryanair Holdings | C3: 2 | D3: Dublin | E3: Aviation | F3: Airlines | G3: Public | H3: 1984 | I3: Verification Pending | J3: https://www.ryanair.com | K3: Europe's largest low-cost airline by passenger numbers. | L3: Europe's largest low-cost airline by passenger numbers | M3: Euronext Dublin/NASDAQ | N3: RY4C | O3: Verification Pending | P3: Verification Pending | Q3: Verification Pending | R3: Verification Pending | S3: N/A | T3: Company knowledge base (stable facts) | U3: Needs financial/leadership verification | V3: 2026-07-18
A4: Ireland | B4: Kerry Group | C4: 3 | D4: Tralee | E4: Food & Beverage | F4: Food Ingredients | G4: Public | H4: 1972 | I4: Verification Pending | J4: https://www.kerrygroup.com | K4: Global leader in food ingredients and flavor technology. | L4: Global leader in food ingredients and flavor technology | M4: Euronext Dublin | N4: KRZ | O4: Verification Pending | P4: Verification Pending | Q4: Verification Pending | R4: Verification Pending | S4: N/A | T4: Company knowledge base (stable facts) | U4: Needs financial/leadership verification | V4: 2026-07-18
A5: Ireland | B5: AIB Group | C5: 4 | D5: Dublin | E5: Banking | F5: Financial Services | G5: Public | H5: 1966 | I5: Verification Pending | J5: https://aib.ie | K5: One of Ireland's largest retail and commercial banks. | L5: One of Ireland's largest retail and commercial banks | M5: Euronext Dublin | N5: A5G | O5: Verification Pending | P5: Verification Pending | Q5: Verification Pending | R5: Verification Pending | S5: N/A | T5: Company knowledge base (stable facts) | U5: Needs financial/leadership verification | V5: 2026-07-18
A6: Ireland | B6: Smurfit WestRock | C6: 5 | D6: Dublin | E6: Packaging | F6: Paper & Packaging | G6: Public | H6: 1934 | I6: Verification Pending | J6: https://www.smurfitwestrock.com | K6: Global leader in sustainable packaging solutions. | L6: Global leader in sustainable packaging solutions | M6: NYSE/LSE | N6: SW | O6: Verification Pending | P6: Verification Pending | Q6: Verification Pending | R6: Verification Pending | S6: N/A | T6: Company knowledge base (stable facts) | U6: Needs financial/leadership verification | V6: 2026-07-18
A8: Note: | B8: Company identity, industry, HQ, founding year, and website are stable facts. 'Verification Pending' fields (CEO, revenue, net income, market cap, Fortune 500 rank) change frequently and require a live data-verification pass before use in analysis.

Sheet Israel
A1: Rank | B1: Company Name | C1: Country | D1: HQ City | E1: Industry | F1: Sector | G1: Company Type | H1: Founded Year | I1: CEO | J1: Official Website | K1: Business Description | L1: Main Products/Services | M1: Stock Exchange | N1: Ticker Symbol | O1: Annual Revenue (USD) | P1: Net Income (USD) | Q1: Market Cap (USD) | R1: Fortune Global 500 Rank | S1: Parent Company | T1: Data Source | U1: Verification Status | V1: Last Updated
A2: Israel | B2: Teva Pharmaceutical Industries | C2: 1 | D2: Tel Aviv | E2: Pharmaceuticals | F2: Generic Drugs | G2: Public | H2: 1901 | I2: Verification Pending | J2: https://www.tevapharm.com | K2: World's largest generic drug manufacturer. | L2: World's largest generic drug manufacturer | M2: TASE/NYSE | N2: TEVA | O2: Verification Pending | P2: Verification Pending | Q2: Verification Pending | R2: Verification Pending | S2: N/A | T2: Company knowledge base (stable facts) | U2: Needs financial/leadership verification | V2: 2026-07-18
A3: Israel | B3: Check Point Software | C3: 2 | D3: Tel Aviv | E3: Cybersecurity | F3: Network Security | G3: Public | H3: 1993 | I3: Verification Pending | J3: https://www.checkpoint.com | K3: Global leader in cybersecurity and network security solutions. | L3: Global leader in cybersecurity and network security solutions | M3: NASDAQ | N3: CHKP | O3: Verification Pending | P3: Verification Pending | Q3: Verification Pending | R3: Verification Pending | S3: N/A | T3: Company knowledge base (stable facts) | U3: Needs financial/leadership verification | V3: 2026-07-18
A4: Israel | B4: Bank Hapoalim | C4: 3 | D4: Tel Aviv | E4: Banking | F4: Financial Services | G4: Public | H4: 1921 | I4: Verification Pending | J4: https://www.bankhapoalim.com | K4: One of Israel's two largest banks. | L4: One of Israel's two largest banks | M4: TASE | N4: POLI | O4: Verification Pending | P4: Verification Pending | Q4: Verification Pending | R4: Verification Pending | S4: N/A | T4: Company knowledge base (stable facts) | U4: Needs financial/leadership verification | V4: 2026-07-18
A5: Israel | B5: Wix.com | C5: 4 | D5: Tel Aviv | E5: Technology | F5: Web Development Platform | G5: Public | H5: 2006 | I5: Verification Pending | J5: https://www.wix.com | K5: Cloud-based website building and business platform. | L5: Cloud-based website building and business platform | M5: NASDAQ | N5: WIX | O5: Verification Pending | P5: Verification Pending | Q5: Verification Pending | R5: Verification Pending | S5: N/A | T5: Company knowledge base (stable facts) | U5: Needs financial/leadership verification | V5: 2026-07-18
A6: Israel | B6: ICL Group | C6: 5 | D6: Tel Aviv | E6: Chemicals | F6: Specialty Minerals & Fertilizers | G6: Public | H6: 1968 | I6: Verification Pending | J6: https://www.icl-group.com | K6: Global specialty minerals and fertilizer company. | L6: Global specialty minerals and fertilizer company | M6: TASE/NYSE | N6: ICL | O6: Verification Pending | P6: Verification Pending | Q6: Verification Pending | R6: Verification Pending | S6: N/A | T6: Company knowledge base (stable facts) | U6: Needs financial/leadership verification | V6: 2026-07-18
A8: Note: | B8: Company identity, industry, HQ, founding year, and website are stable facts. 'Verification Pending' fields (CEO, revenue, net income, market cap, Fortune 500 rank) change frequently and require a live data-verification pass before use in analysis.

Sheet Thailand
A1: Rank | B1: Company Name | C1: Country | D1: HQ City | E1: Industry | F1: Sector | G1: Company Type | H1: Founded Year | I1: CEO | J1: Official Website | K1: Business Description | L1: Main Products/Services | M1: Stock Exchange | N1: Ticker Symbol | O1: Annual Revenue (USD) | P1: Net Income (USD) | Q1: Market Cap (USD) | R1: Fortune Global 500 Rank | S1: Parent Company | T1: Data Source | U1: Verification Status | V1: Last Updated
A2: Thailand | B2: PTT Public Company | C2: 1 | D2: Bangkok | E2: Oil & Gas | F2: Energy | G2: State-Owned | H2: 1978 | I2: Verification Pending | J2: https://www.pttplc.com | K2: Thailand's largest energy conglomerate. | L2: Thailand's largest energy conglomerate | M2: SET | N2: PTT | O2: Verification Pending | P2: Verification Pending | Q2: Verification Pending | R2: Verification Pending | S2: N/A | T2: Company knowledge base (stable facts) | U2: Needs financial/leadership verification | V2: 2026-07-18
A3: Thailand | B3: Siam Cement Group (SCG) | C3: 2 | D3: Bangkok | E3: Construction/Chemicals | F3: Building Materials & Petrochemicals | G3: Public | H3: 1913 | I3: Verification Pending | J3: https://www.scg.com | K3: Thailand's largest industrial conglomerate. | L3: Thailand's largest industrial conglomerate | M3: SET | N3: SCC | O3: Verification Pending | P3: Verification Pending | Q3: Verification Pending | R3: Verification Pending | S3: N/A | T3: Company knowledge base (stable facts) | U3: Needs financial/leadership verification | V3: 2026-07-18
A4: Thailand | B4: CP Group (Charoen Pokphand) | C4: 3 | D4: Bangkok | E4: Conglomerate | F4: Agribusiness & Retail | G4: Private | H4: 1921 | I4: Verification Pending | J4: https://www.cpgroupglobal.com | K4: Thailand's largest conglomerate spanning agribusiness, retail, and telecom. | L4: Thailand's largest conglomerate spanning agribusiness, retail, and telecom | M4: Private/SET subsidiaries | N4: N/A | O4: Verification Pending | P4: Verification Pending | Q4: Verification Pending | R4: Verification Pending | S4: N/A | T4: Company knowledge base (stable facts) | U4: Needs financial/leadership verification | V4: 2026-07-18
A5: Thailand | B5: Kasikornbank | C5: 4 | D5: Bangkok | E5: Banking | F5: Financial Services | G5: Public | H5: 1945 | I5: Verification Pending | J5: https://www.kasikornbank.com | K5: One of Thailand's largest banks. | L5: One of Thailand's largest banks | M5: SET | N5: KBANK | O5: Verification Pending | P5: Verification Pending | Q5: Verification Pending | R5: Verification Pending | S5: N/A | T5: Company knowledge base (stable facts) | U5: Needs financial/leadership verification | V5: 2026-07-18
A6: Thailand | B6: Advanced Info Service (AIS) | C6: 5 | D6: Bangkok | E6: Telecommunications | F6: Telecom Services | G6: Public | H6: 1986 | I6: Verification Pending | J6: https://www.ais.co.th | K6: Thailand's largest mobile network operator. | L6: Thailand's largest mobile network operator | M6: SET | N6: ADVANC | O6: Verification Pending | P6: Verification Pending | Q6: Verification Pending | R6: Verification Pending | S6: N/A | T6: Company knowledge base (stable facts) | U6: Needs financial/leadership verification | V6: 2026-07-18
A8: Note: | B8: Company identity, industry, HQ, founding year, and website are stable facts. 'Verification Pending' fields (CEO, revenue, net income, market cap, Fortune 500 rank) change frequently and require a live data-verification pass before use in analysis.

Sheet Nigeria
A1: Rank | B1: Company Name | C1: Country | D1: HQ City | E1: Industry | F1: Sector | G1: Company Type | H1: Founded Year | I1: CEO | J1: Official Website | K1: Business Description | L1: Main Products/Services | M1: Stock Exchange | N1: Ticker Symbol | O1: Annual Revenue (USD) | P1: Net Income (USD) | Q1: Market Cap (USD) | R1: Fortune Global 500 Rank | S1: Parent Company | T1: Data Source | U1: Verification Status | V1: Last Updated
A2: Nigeria | B2: Dangote Group | C2: 1 | D2: Lagos | E2: Conglomerate | F2: Cement & Industrial | G2: Private/Public | H2: 1981 | I2: Verification Pending | J2: https://www.dangote.com | K2: West Africa's largest industrial conglomerate, cement and refining. | L2: West Africa's largest industrial conglomerate, cement and refining | M2: NGX (Dangote Cement listed) | N2: DANGCEM | O2: Verification Pending | P2: Verification Pending | Q2: Verification Pending | R2: Verification Pending | S2: N/A | T2: Company knowledge base (stable facts) | U2: Needs financial/leadership verification | V2: 2026-07-18
A3: Nigeria | B3: MTN Nigeria | C3: 2 | D3: Lagos | E3: Telecommunications | F3: Telecom Services | G3: Public | H3: 2001 | I3: Verification Pending | J3: https://www.mtn.ng | K3: Nigeria's largest mobile telecom operator. | L3: Nigeria's largest mobile telecom operator | M3: NGX | N3: MTNN | O3: Verification Pending | P3: Verification Pending | Q3: Verification Pending | R3: Verification Pending | S3: N/A | T3: Company knowledge base (stable facts) | U3: Needs financial/leadership verification | V3: 2026-07-18
A4: Nigeria | B4: Zenith Bank | C4: 3 | D4: Lagos | E4: Banking | F4: Financial Services | G4: Public | H4: 1990 | I4: Verification Pending | J4: https://www.zenithbank.com | K4: One of Nigeria's largest banks by assets. | L4: One of Nigeria's largest banks by assets | M4: NGX | N4: ZENITHBANK | O4: Verification Pending | P4: Verification Pending | Q4: Verification Pending | R4: Verification Pending | S4: N/A | T4: Company knowledge base (stable facts) | U4: Needs financial/leadership verification | V4: 2026-07-18
A5: Nigeria | B5: Guaranty Trust Holding (GTCO) | C5: 4 | D5: Lagos | E5: Banking | F5: Financial Services | G5: Public | H5: 1990 | I5: Verification Pending | J5: https://www.gtcoplc.com | K5: Major Nigerian banking group. | L5: Major Nigerian banking group | M5: NGX | N5: GTCO | O5: Verification Pending | P5: Verification Pending | Q5: Verification Pending | R5: Verification Pending | S5: N/A | T5: Company knowledge base (stable facts) | U5: Needs financial/leadership verification | V5: 2026-07-18
A6: Nigeria | B6: Nigerian National Petroleum Corporation (NNPC) | C6: 5 | D6: Abuja | E6: Oil & Gas | F6: Energy | G6: State-Owned | H6: 1977 | I6: Verification Pending | J6: https://www.nnpcgroup.com | K6: Nigeria's state oil corporation. | L6: Nigeria's state oil corporation | M6: State-owned | N6: N/A | O6: Verification Pending | P6: Verification Pending | Q6: Verification Pending | R6: Verification Pending | S6: N/A | T6: Company knowledge base (stable facts) | U6: Needs financial/leadership verification | V6: 2026-07-18
A8: Note: | B8: Company identity, industry, HQ, founding year, and website are stable facts. 'Verification Pending' fields (CEO, revenue, net income, market cap, Fortune 500 rank) change frequently and require a live data-verification pass before use in analysis.

Sheet United Arab Emirates
A1: Rank | B1: Company Name | C1: Country | D1: HQ City | E1: Industry | F1: Sector | G1: Company Type | H1: Founded Year | I1: CEO | J1: Official Website | K1: Business Description | L1: Main Products/Services | M1: Stock Exchange | N1: Ticker Symbol | O1: Annual Revenue (USD) | P1: Net Income (USD) | Q1: Market Cap (USD) | R1: Fortune Global 500 Rank | S1: Parent Company | T1: Data Source | U1: Verification Status | V1: Last Updated
A2: United Arab Emirates | B2: ADNOC Group | C2: 1 | D2: Abu Dhabi | E2: Oil & Gas | F2: Energy | G2: State-Owned | H2: 1971 | I2: Verification Pending | J2: https://www.adnoc.ae | K2: Abu Dhabi's state-owned oil company, one of world's largest energy producers. | L2: Abu Dhabi's state-owned oil company, one of world's largest energy producers | M2: State-owned (units listed on ADX) | N2: N/A | O2: Verification Pending | P2: Verification Pending | Q2: Verification Pending | R2: Verification Pending | S2: N/A | T2: Company knowledge base (stable facts) | U2: Needs financial/leadership verification | V2: 2026-07-18
A3: United Arab Emirates | B3: Emirates Group | C3: 2 | D3: Dubai | E3: Aviation | F3: Airlines & Logistics | G3: State-Owned | H3: 1985 | I3: Verification Pending | J3: https://www.emirates.com | K3: Dubai's flag carrier and one of the world's largest international airlines. | L3: Dubai's flag carrier and one of the world's largest international airlines | M3: State-owned | N3: N/A | O3: Verification Pending | P3: Verification Pending | Q3: Verification Pending | R3: Verification Pending | S3: N/A | T3: Company knowledge base (stable facts) | U3: Needs financial/leadership verification | V3: 2026-07-18
A4: United Arab Emirates | B4: Emirates NBD | C4: 3 | D4: Dubai | E4: Banking | F4: Financial Services | G4: Public | H4: 2007 | I4: Verification Pending | J4: https://www.emiratesnbd.com | K4: Leading banking group in the UAE and MENA region. | L4: Leading banking group in the UAE and MENA region | M4: DFM | N4: EMIRATESNBD | O4: Verification Pending | P4: Verification Pending | Q4: Verification Pending | R4: Verification Pending | S4: N/A | T4: Company knowledge base (stable facts) | U4: Needs financial/leadership verification | V4: 2026-07-18
A5: United Arab Emirates | B5: First Abu Dhabi Bank | C5: 4 | D5: Abu Dhabi | E5: Banking | F5: Financial Services | G5: Public | H5: 2017 | I5: Verification Pending | J5: https://www.bankfab.com | K5: UAE's largest bank by assets. | L5: UAE's largest bank by assets | M5: ADX | N5: FAB | O5: Verification Pending | P5: Verification Pending | Q5: Verification Pending | R5: Verification Pending | S5: N/A | T5: Company knowledge base (stable facts) | U5: Needs financial/leadership verification | V5: 2026-07-18
A6: United Arab Emirates | B6: DP World | C6: 5 | D6: Dubai | E6: Logistics | F6: Ports & Shipping | G6: State-Owned | H6: 1972 | I6: Verification Pending | J6: https://www.dpworld.com | K6: Global ports, logistics, and maritime services operator. | L6: Global ports, logistics, and maritime services operator | M6: DFM (delisted 2020, state-owned) | N6: N/A | O6: Verification Pending | P6: Verification Pending | Q6: Verification Pending | R6: Verification Pending | S6: N/A | T6: Company knowledge base (stable facts) | U6: Needs financial/leadership verification | V6: 2026-07-18
A8: Note: | B8: Company identity, industry, HQ, founding year, and website are stable facts. 'Verification Pending' fields (CEO, revenue, net income, market cap, Fortune 500 rank) change frequently and require a live data-verification pass before use in analysis.

Sheet Norway
A1: Rank | B1: Company Name | C1: Country | D1: HQ City | E1: Industry | F1: Sector | G1: Company Type | H1: Founded Year | I1: CEO | J1: Official Website | K1: Business Description | L1: Main Products/Services | M1: Stock Exchange | N1: Ticker Symbol | O1: Annual Revenue (USD) | P1: Net Income (USD) | Q1: Market Cap (USD) | R1: Fortune Global 500 Rank | S1: Parent Company | T1: Data Source | U1: Verification Status | V1: Last Updated
A2: Norway | B2: Equinor ASA | C2: 1 | D2: Stavanger | E2: Oil & Gas | F2: Energy | G2: State-Owned | H2: 1972 | I2: Verification Pending | J2: https://www.equinor.com | K2: Norway's state-controlled oil, gas, and renewable energy company. | L2: Norway's state-controlled oil, gas, and renewable energy company | M2: Oslo Bors/NYSE | N2: EQNR | O2: Verification Pending | P2: Verification Pending | Q2: Verification Pending | R2: Verification Pending | S2: N/A | T2: Company knowledge base (stable facts) | U2: Needs financial/leadership verification | V2: 2026-07-18
A3: Norway | B3: Telenor Group | C3: 2 | D3: Oslo/Fornebu | E3: Telecommunications | F3: Telecom Services | G3: Public | H3: 1855 | I3: Verification Pending | J3: https://www.telenor.com | K3: Major Nordic and Asian telecommunications operator. | L3: Major Nordic and Asian telecommunications operator | M3: Oslo Bors | N3: TEL | O3: Verification Pending | P3: Verification Pending | Q3: Verification Pending | R3: Verification Pending | S3: N/A | T3: Company knowledge base (stable facts) | U3: Needs financial/leadership verification | V3: 2026-07-18
A4: Norway | B4: Norsk Hydro | C4: 3 | D4: Oslo | E4: Metals & Mining | F4: Aluminum Production | G4: Public | H4: 1905 | I4: Verification Pending | J4: https://www.hydro.com | K4: Major global aluminum and renewable energy company. | L4: Major global aluminum and renewable energy company | M4: Oslo Bors | N4: NHY | O4: Verification Pending | P4: Verification Pending | Q4: Verification Pending | R4: Verification Pending | S4: N/A | T4: Company knowledge base (stable facts) | U4: Needs financial/leadership verification | V4: 2026-07-18
A5: Norway | B5: DNB Bank | C5: 4 | D5: Oslo | E5: Banking | F5: Financial Services | G5: Public | H5: 1822 | I5: Verification Pending | J5: https://www.dnb.no | K5: Norway's largest financial services group. | L5: Norway's largest financial services group | M5: Oslo Bors | N5: DNB | O5: Verification Pending | P5: Verification Pending | Q5: Verification Pending | R5: Verification Pending | S5: N/A | T5: Company knowledge base (stable facts) | U5: Needs financial/leadership verification | V5: 2026-07-18
A6: Norway | B6: Yara International | C6: 5 | D6: Oslo | E6: Chemicals | F6: Agricultural Fertilizers | G6: Public | H6: 1905 | I6: Verification Pending | J6: https://www.yara.com | K6: World's largest crop nutrition and fertilizer company. | L6: World's largest crop nutrition and fertilizer company | M6: Oslo Bors | N6: YAR | O6: Verification Pending | P6: Verification Pending | Q6: Verification Pending | R6: Verification Pending | S6: N/A | T6: Company knowledge base (stable facts) | U6: Needs financial/leadership verification | V6: 2026-07-18
A8: Note: | B8: Company identity, industry, HQ, founding year, and website are stable facts. 'Verification Pending' fields (CEO, revenue, net income, market cap, Fortune 500 rank) change frequently and require a live data-verification pass before use in analysis.

Sheet Egypt
A1: Rank | B1: Company Name | C1: Country | D1: HQ City | E1: Industry | F1: Sector | G1: Company Type | H1: Founded Year | I1: CEO | J1: Official Website | K1: Business Description | L1: Main Products/Services | M1: Stock Exchange | N1: Ticker Symbol | O1: Annual Revenue (USD) | P1: Net Income (USD) | Q1: Market Cap (USD) | R1: Fortune Global 500 Rank | S1: Parent Company | T1: Data Source | U1: Verification Status | V1: Last Updated
A2: Egypt | B2: Commercial International Bank (CIB) | C2: 1 | D2: Cairo | E2: Banking | F2: Financial Services | G2: Public | H2: 1975 | I2: Verification Pending | J2: https://www.cibeg.com | K2: Egypt's largest private sector bank. | L2: Egypt's largest private sector bank | M2: EGX | N2: COMI | O2: Verification Pending | P2: Verification Pending | Q2: Verification Pending | R2: Verification Pending | S2: N/A | T2: Company knowledge base (stable facts) | U2: Needs financial/leadership verification | V2: 2026-07-18
A3: Egypt | B3: Egyptian General Petroleum Corporation (EGPC) | C3: 2 | D3: Cairo | E3: Oil & Gas | F3: Energy | G3: State-Owned | H3: 1976 | I3: Verification Pending | J3: https://www.egpc.com.eg | K3: Egypt's national oil company. | L3: Egypt's national oil company | M3: State-owned | N3: N/A | O3: Verification Pending | P3: Verification Pending | Q3: Verification Pending | R3: Verification Pending | S3: N/A | T3: Company knowledge base (stable facts) | U3: Needs financial/leadership verification | V3: 2026-07-18
A4: Egypt | B4: Orascom Construction | C4: 3 | D4: Cairo | E4: Construction | F4: Engineering & Construction | G4: Public | H4: 1950 | I4: Verification Pending | J4: https://orascomconstruction.com | K4: Major regional engineering and construction contractor. | L4: Major regional engineering and construction contractor | M4: EGX/Nasdaq Dubai | N4: ORAS | O4: Verification Pending | P4: Verification Pending | Q4: Verification Pending | R4: Verification Pending | S4: N/A | T4: Company knowledge base (stable facts) | U4: Needs financial/leadership verification | V4: 2026-07-18
A5: Egypt | B5: Telecom Egypt | C5: 4 | D5: Cairo | E5: Telecommunications | F5: Telecom Services | G5: Public | H5: 1998 | I5: Verification Pending | J5: https://www.te.eg | K5: Egypt's historic incumbent telecom operator. | L5: Egypt's historic incumbent telecom operator | M5: EGX | N5: ETEL | O5: Verification Pending | P5: Verification Pending | Q5: Verification Pending | R5: Verification Pending | S5: N/A | T5: Company knowledge base (stable facts) | U5: Needs financial/leadership verification | V5: 2026-07-18
A6: Egypt | B6: Orascom Investment Holding | C6: 5 | D6: Cairo | E6: Conglomerate | F6: Diversified Industrial | G6: Public | H6: 1998 | I6: Verification Pending | J6: https://orascomholding.com | K6: Diversified conglomerate spanning telecom, industry, and technology. | L6: Diversified conglomerate spanning telecom, industry, and technology | M6: EGX | N6: OIH | O6: Verification Pending | P6: Verification Pending | Q6: Verification Pending | R6: Verification Pending | S6: N/A | T6: Company knowledge base (stable facts) | U6: Needs financial/leadership verification | V6: 2026-07-18
A8: Note: | B8: Company identity, industry, HQ, founding year, and website are stable facts. 'Verification Pending' fields (CEO, revenue, net income, market cap, Fortune 500 rank) change frequently and require a live data-verification pass before use in analysis.

Sheet Austria
A1: Rank | B1: Company Name | C1: Country | D1: HQ City | E1: Industry | F1: Sector | G1: Company Type | H1: Founded Year | I1: CEO | J1: Official Website | K1: Business Description | L1: Main Products/Services | M1: Stock Exchange | N1: Ticker Symbol | O1: Annual Revenue (USD) | P1: Net Income (USD) | Q1: Market Cap (USD) | R1: Fortune Global 500 Rank | S1: Parent Company | T1: Data Source | U1: Verification Status | V1: Last Updated
A2: Austria | B2: OMV Group | C2: 1 | D2: Vienna | E2: Oil & Gas | F2: Energy & Chemicals | G2: Public | H2: 1956 | I2: Verification Pending | J2: https://www.omv.com | K2: Austria's largest industrial company; oil, gas, and chemicals. | L2: Austria's largest industrial company; oil, gas, and chemicals | M2: Wiener Borse | N2: OMV | O2: Verification Pending | P2: Verification Pending | Q2: Verification Pending | R2: Verification Pending | S2: N/A | T2: Company knowledge base (stable facts) | U2: Needs financial/leadership verification | V2: 2026-07-18
A3: Austria | B3: Erste Group Bank | C3: 2 | D3: Vienna | E3: Banking | F3: Financial Services | G3: Public | H3: 1819 | I3: Verification Pending | J3: https://www.erstegroup.com | K3: Major Central and Eastern European banking group. | L3: Major Central and Eastern European banking group | M3: Wiener Borse | N3: EBS | O3: Verification Pending | P3: Verification Pending | Q3: Verification Pending | R3: Verification Pending | S3: N/A | T3: Company knowledge base (stable facts) | U3: Needs financial/leadership verification | V3: 2026-07-18
A4: Austria | B4: Voestalpine AG | C4: 3 | D4: Linz | E4: Steel | F4: Steel & Technology | G4: Public | H4: 1938 | I4: Verification Pending | J4: https://www.voestalpine.com | K4: Leading steel and technology group. | L4: Leading steel and technology group | M4: Wiener Borse | N4: VOE | O4: Verification Pending | P4: Verification Pending | Q4: Verification Pending | R4: Verification Pending | S4: N/A | T4: Company knowledge base (stable facts) | U4: Needs financial/leadership verification | V4: 2026-07-18
A5: Austria | B5: Raiffeisen Bank International | C5: 4 | D5: Vienna | E5: Banking | F5: Financial Services | G5: Public | H5: 1927 | I5: Verification Pending | J5: https://www.rbinternational.com | K5: Major Austrian bank with extensive CEE operations. | L5: Major Austrian bank with extensive CEE operations | M5: Wiener Borse | N5: RBI | O5: Verification Pending | P5: Verification Pending | Q5: Verification Pending | R5: Verification Pending | S5: N/A | T5: Company knowledge base (stable facts) | U5: Needs financial/leadership verification | V5: 2026-07-18
A6: Austria | B6: Andritz AG | C6: 5 | D6: Graz | E6: Industrial Manufacturing | F6: Plant Engineering | G6: Public | H6: 1852 | I6: Verification Pending | J6: https://www.andritz.com | K6: Global supplier of plants, equipment, and services for industry. | L6: Global supplier of plants, equipment, and services for industry | M6: Wiener Borse | N6: ANDR | O6: Verification Pending | P6: Verification Pending | Q6: Verification Pending | R6: Verification Pending | S6: N/A | T6: Company knowledge base (stable facts) | U6: Needs financial/leadership verification | V6: 2026-07-18
A8: Note: | B8: Company identity, industry, HQ, founding year, and website are stable facts. 'Verification Pending' fields (CEO, revenue, net income, market cap, Fortune 500 rank) change frequently and require a live data-verification pass before use in analysis.

Sheet Singapore
A1: Rank | B1: Company Name | C1: Country | D1: HQ City | E1: Industry | F1: Sector | G1: Company Type | H1: Founded Year | I1: CEO | J1: Official Website | K1: Business Description | L1: Main Products/Services | M1: Stock Exchange | N1: Ticker Symbol | O1: Annual Revenue (USD) | P1: Net Income (USD) | Q1: Market Cap (USD) | R1: Fortune Global 500 Rank | S1: Parent Company | T1: Data Source | U1: Verification Status | V1: Last Updated
A2: Singapore | B2: DBS Group Holdings | C2: 1 | D2: Singapore | E2: Banking | F2: Financial Services | G2: Public | H2: 1968 | I2: Verification Pending | J2: https://www.dbs.com | K2: Southeast Asia's largest bank by assets. | L2: Southeast Asia's largest bank by assets | M2: SGX | N2: D05 | O2: Verification Pending | P2: Verification Pending | Q2: Verification Pending | R2: Verification Pending | S2: N/A | T2: Company knowledge base (stable facts) | U2: Needs financial/leadership verification | V2: 2026-07-18
A3: Singapore | B3: Singapore Airlines | C3: 2 | D3: Singapore | E3: Aviation | F3: Airlines | G3: Public | H3: 1947 | I3: Verification Pending | J3: https://www.singaporeair.com | K3: Singapore's flag carrier, renowned for premium service. | L3: Singapore's flag carrier, renowned for premium service | M3: SGX | N3: C6L | O3: Verification Pending | P3: Verification Pending | Q3: Verification Pending | R3: Verification Pending | S3: N/A | T3: Company knowledge base (stable facts) | U3: Needs financial/leadership verification | V3: 2026-07-18
A4: Singapore | B4: OCBC Bank | C4: 3 | D4: Singapore | E4: Banking | F4: Financial Services | G4: Public | H4: 1932 | I4: Verification Pending | J4: https://www.ocbc.com | K4: One of Southeast Asia's largest financial services groups. | L4: One of Southeast Asia's largest financial services groups | M4: SGX | N4: O39 | O4: Verification Pending | P4: Verification Pending | Q4: Verification Pending | R4: Verification Pending | S4: N/A | T4: Company knowledge base (stable facts) | U4: Needs financial/leadership verification | V4: 2026-07-18
A5: Singapore | B5: Wilmar International | C5: 4 | D5: Singapore | E5: Agriculture | F5: Agribusiness | G5: Public | H5: 1991 | I5: Verification Pending | J5: https://www.wilmar-international.com | K5: Asia's leading agribusiness group, palm oil and food products. | L5: Asia's leading agribusiness group, palm oil and food products | M5: SGX | N5: F34 | O5: Verification Pending | P5: Verification Pending | Q5: Verification Pending | R5: Verification Pending | S5: N/A | T5: Company knowledge base (stable facts) | U5: Needs financial/leadership verification | V5: 2026-07-18
A6: Singapore | B6: Temasek Holdings | C6: 5 | D6: Singapore | E6: Investment | F6: Sovereign Wealth Investment | G6: State-Owned | H6: 1974 | I6: Verification Pending | J6: https://www.temasek.com.sg | K6: Singapore's state investment company managing a global portfolio. | L6: Singapore's state investment company managing a global portfolio | M6: State-owned (unlisted) | N6: N/A | O6: Verification Pending | P6: Verification Pending | Q6: Verification Pending | R6: Verification Pending | S6: N/A | T6: Company knowledge base (stable facts) | U6: Needs financial/leadership verification | V6: 2026-07-18
A8: Note: | B8: Company identity, industry, HQ, founding year, and website are stable facts. 'Verification Pending' fields (CEO, revenue, net income, market cap, Fortune 500 rank) change frequently and require a live data-verification pass before use in analysis.

Sheet Philippines
A1: Rank | B1: Company Name | C1: Country | D1: HQ City | E1: Industry | F1: Sector | G1: Company Type | H1: Founded Year | I1: CEO | J1: Official Website | K1: Business Description | L1: Main Products/Services | M1: Stock Exchange | N1: Ticker Symbol | O1: Annual Revenue (USD) | P1: Net Income (USD) | Q1: Market Cap (USD) | R1: Fortune Global 500 Rank | S1: Parent Company | T1: Data Source | U1: Verification Status | V1: Last Updated
A2: Philippines | B2: SM Investments Corporation | C2: 1 | D2: Pasay | E2: Conglomerate | F2: Retail, Banking & Property | G2: Public | H2: 1958 | I2: Verification Pending | J2: https://www.sminvestments.com | K2: Philippines' largest conglomerate spanning retail, banking, and real estate. | L2: Philippines' largest conglomerate spanning retail, banking, and real estate | M2: PSE | N2: SM | O2: Verification Pending | P2: Verification Pending | Q2: Verification Pending | R2: Verification Pending | S2: N/A | T2: Company knowledge base (stable facts) | U2: Needs financial/leadership verification | V2: 2026-07-18
A3: Philippines | B3: BDO Unibank | C3: 2 | D3: Makati | E3: Banking | F3: Financial Services | G3: Public | H3: 1968 | I3: Verification Pending | J3: https://www.bdo.com.ph | K3: Philippines' largest bank by assets. | L3: Philippines' largest bank by assets | M3: PSE | N3: BDO | O3: Verification Pending | P3: Verification Pending | Q3: Verification Pending | R3: Verification Pending | S3: N/A | T3: Company knowledge base (stable facts) | U3: Needs financial/leadership verification | V3: 2026-07-18
A4: Philippines | B4: Ayala Corporation | C4: 3 | D4: Makati | E4: Conglomerate | F4: Real Estate, Banking & Telecom | G4: Public | H4: 1834 | I4: Verification Pending | J4: https://www.ayala.com.ph | K4: One of the Philippines' oldest and largest conglomerates. | L4: One of the Philippines' oldest and largest conglomerates | M4: PSE | N4: AC | O4: Verification Pending | P4: Verification Pending | Q4: Verification Pending | R4: Verification Pending | S4: N/A | T4: Company knowledge base (stable facts) | U4: Needs financial/leadership verification | V4: 2026-07-18
A5: Philippines | B5: PLDT Inc. | C5: 4 | D5: Makati | E5: Telecommunications | F5: Telecom Services | G5: Public | H5: 1928 | I5: Verification Pending | J5: https://www.pldt.com | K5: Philippines' largest telecommunications company. | L5: Philippines' largest telecommunications company | M5: PSE/NYSE | N5: TEL | O5: Verification Pending | P5: Verification Pending | Q5: Verification Pending | R5: Verification Pending | S5: N/A | T5: Company knowledge base (stable facts) | U5: Needs financial/leadership verification | V5: 2026-07-18
A6: Philippines | B6: San Miguel Corporation | C6: 5 | D6: Mandaluyong | E6: Food & Beverage | F6: Diversified Food, Beverage & Infrastructure | G6: Public | H6: 1890 | I6: Verification Pending | J6: https://www.sanmiguel.com.ph | K6: Major diversified conglomerate, originally a brewery. | L6: Major diversified conglomerate, originally a brewery | M6: PSE | N6: SMC | O6: Verification Pending | P6: Verification Pending | Q6: Verification Pending | R6: Verification Pending | S6: N/A | T6: Company knowledge base (stable facts) | U6: Needs financial/leadership verification | V6: 2026-07-18
A8: Note: | B8: Company identity, industry, HQ, founding year, and website are stable facts. 'Verification Pending' fields (CEO, revenue, net income, market cap, Fortune 500 rank) change frequently and require a live data-verification pass before use in analysis.

Sheet Malaysia
A1: Rank | B1: Company Name | C1: Country | D1: HQ City | E1: Industry | F1: Sector | G1: Company Type | H1: Founded Year | I1: CEO | J1: Official Website | K1: Business Description | L1: Main Products/Services | M1: Stock Exchange | N1: Ticker Symbol | O1: Annual Revenue (USD) | P1: Net Income (USD) | Q1: Market Cap (USD) | R1: Fortune Global 500 Rank | S1: Parent Company | T1: Data Source | U1: Verification Status | V1: Last Updated
A2: Malaysia | B2: Petronas | C2: 1 | D2: Kuala Lumpur | E2: Oil & Gas | F2: Energy | G2: State-Owned | H2: 1974 | I2: Verification Pending | J2: https://www.petronas.com | K2: Malaysia's state-owned oil and gas company, Fortune Global 500 member. | L2: Malaysia's state-owned oil and gas company, Fortune Global 500 member | M2: State-owned | N2: N/A | O2: Verification Pending | P2: Verification Pending | Q2: Verification Pending | R2: Verification Pending | S2: N/A | T2: Company knowledge base (stable facts) | U2: Needs financial/leadership verification | V2: 2026-07-18
A3: Malaysia | B3: Maybank | C3: 2 | D3: Kuala Lumpur | E3: Banking | F3: Financial Services | G3: Public | H3: 1960 | I3: Verification Pending | J3: https://www.maybank.com | K3: Malaysia's largest bank by assets. | L3: Malaysia's largest bank by assets | M3: Bursa Malaysia | N3: 1155 | O3: Verification Pending | P3: Verification Pending | Q3: Verification Pending | R3: Verification Pending | S3: N/A | T3: Company knowledge base (stable facts) | U3: Needs financial/leadership verification | V3: 2026-07-18
A4: Malaysia | B4: Public Bank Berhad | C4: 3 | D4: Kuala Lumpur | E4: Banking | F4: Financial Services | G4: Public | H4: 1966 | I4: Verification Pending | J4: https://www.pbebank.com | K4: One of Malaysia's largest banking groups. | L4: One of Malaysia's largest banking groups | M4: Bursa Malaysia | N4: 1295 | O4: Verification Pending | P4: Verification Pending | Q4: Verification Pending | R4: Verification Pending | S4: N/A | T4: Company knowledge base (stable facts) | U4: Needs financial/leadership verification | V4: 2026-07-18
A5: Malaysia | B5: CIMB Group | C5: 4 | D5: Kuala Lumpur | E5: Banking | F5: Financial Services | G5: Public | H5: 1924 | I5: Verification Pending | J5: https://www.cimb.com | K5: Major Southeast Asian universal bank. | L5: Major Southeast Asian universal bank | M5: Bursa Malaysia | N5: 1023 | O5: Verification Pending | P5: Verification Pending | Q5: Verification Pending | R5: Verification Pending | S5: N/A | T5: Company knowledge base (stable facts) | U5: Needs financial/leadership verification | V5: 2026-07-18
A6: Malaysia | B6: Tenaga Nasional | C6: 5 | D6: Kuala Lumpur | E6: Utilities | F6: Electric Power | G6: Public | H6: 1990 | I6: Verification Pending | J6: https://www.tnb.com.my | K6: Malaysia's largest electricity utility. | L6: Malaysia's largest electricity utility | M6: Bursa Malaysia | N6: 5347 | O6: Verification Pending | P6: Verification Pending | Q6: Verification Pending | R6: Verification Pending | S6: N/A | T6: Company knowledge base (stable facts) | U6: Needs financial/leadership verification | V6: 2026-07-18
A8: Note: | B8: Company identity, industry, HQ, founding year, and website are stable facts. 'Verification Pending' fields (CEO, revenue, net income, market cap, Fortune 500 rank) change frequently and require a live data-verification pass before use in analysis.

Sheet South Africa
A1: Rank | B1: Company Name | C1: Country | D1: HQ City | E1: Industry | F1: Sector | G1: Company Type | H1: Founded Year | I1: CEO | J1: Official Website | K1: Business Description | L1: Main Products/Services | M1: Stock Exchange | N1: Ticker Symbol | O1: Annual Revenue (USD) | P1: Net Income (USD) | Q1: Market Cap (USD) | R1: Fortune Global 500 Rank | S1: Parent Company | T1: Data Source | U1: Verification Status | V1: Last Updated
A2: South Africa | B2: Naspers | C2: 1 | D2: Cape Town | E2: Technology/Media | F2: Internet & Media Investment | G2: Public | H2: 1915 | I2: Verification Pending | J2: https://www.naspers.com | K2: Africa's largest company by market cap, major Tencent shareholder. | L2: Africa's largest company by market cap, major Tencent shareholder | M2: JSE | N2: NPN | O2: Verification Pending | P2: Verification Pending | Q2: Verification Pending | R2: Verification Pending | S2: N/A | T2: Company knowledge base (stable facts) | U2: Needs financial/leadership verification | V2: 2026-07-18
A3: South Africa | B3: Sasol | C3: 2 | D3: Johannesburg | E3: Chemicals/Energy | F3: Chemicals & Synthetic Fuels | G3: Public | H3: 1950 | I3: Verification Pending | J3: https://www.sasol.com | K3: Global chemicals and energy company, pioneer of coal-to-liquid fuel. | L3: Global chemicals and energy company, pioneer of coal-to-liquid fuel | M3: JSE/NYSE | N3: SOL | O3: Verification Pending | P3: Verification Pending | Q3: Verification Pending | R3: Verification Pending | S3: N/A | T3: Company knowledge base (stable facts) | U3: Needs financial/leadership verification | V3: 2026-07-18
A4: South Africa | B4: Standard Bank Group | C4: 3 | D4: Johannesburg | E4: Banking | F4: Financial Services | G4: Public | H4: 1862 | I4: Verification Pending | J4: https://www.standardbank.com | K4: Africa's largest bank by assets. | L4: Africa's largest bank by assets | M4: JSE | N4: SBK | O4: Verification Pending | P4: Verification Pending | Q4: Verification Pending | R4: Verification Pending | S4: N/A | T4: Company knowledge base (stable facts) | U4: Needs financial/leadership verification | V4: 2026-07-18
A5: South Africa | B5: MTN Group | C5: 4 | D5: Johannesburg | E5: Telecommunications | F5: Telecom Services | G5: Public | H5: 1994 | I5: Verification Pending | J5: https://www.mtn.com | K5: Africa's largest mobile telecom operator by subscribers. | L5: Africa's largest mobile telecom operator by subscribers | M5: JSE | N5: MTN | O5: Verification Pending | P5: Verification Pending | Q5: Verification Pending | R5: Verification Pending | S5: N/A | T5: Company knowledge base (stable facts) | U5: Needs financial/leadership verification | V5: 2026-07-18
A6: South Africa | B6: Anglo American plc | C6: 5 | D6: Johannesburg/London | E6: Mining | F6: Metals & Mining | G6: Public | H6: 1917 | I6: Verification Pending | J6: https://www.angloamerican.com | K6: Major global diversified mining company. | L6: Major global diversified mining company | M6: JSE/LSE | N6: AGL | O6: Verification Pending | P6: Verification Pending | Q6: Verification Pending | R6: Verification Pending | S6: N/A | T6: Company knowledge base (stable facts) | U6: Needs financial/leadership verification | V6: 2026-07-18
A8: Note: | B8: Company identity, industry, HQ, founding year, and website are stable facts. 'Verification Pending' fields (CEO, revenue, net income, market cap, Fortune 500 rank) change frequently and require a live data-verification pass before use in analysis.

Sheet Denmark
A1: Rank | B1: Company Name | C1: Country | D1: HQ City | E1: Industry | F1: Sector | G1: Company Type | H1: Founded Year | I1: CEO | J1: Official Website | K1: Business Description | L1: Main Products/Services | M1: Stock Exchange | N1: Ticker Symbol | O1: Annual Revenue (USD) | P1: Net Income (USD) | Q1: Market Cap (USD) | R1: Fortune Global 500 Rank | S1: Parent Company | T1: Data Source | U1: Verification Status | V1: Last Updated
A2: Denmark | B2: Novo Nordisk | C2: 1 | D2: Bagsvaerd | E2: Pharmaceuticals | F2: Biopharmaceuticals | G2: Public | H2: 1923 | I2: Verification Pending | J2: https://www.novonordisk.com | K2: Global leader in diabetes and obesity treatment (Ozempic, Wegovy). | L2: Global leader in diabetes and obesity treatment (Ozempic, Wegovy) | M2: Nasdaq Copenhagen/NYSE | N2: NOVO-B | O2: Verification Pending | P2: Verification Pending | Q2: Verification Pending | R2: Verification Pending | S2: N/A | T2: Company knowledge base (stable facts) | U2: Needs financial/leadership verification | V2: 2026-07-18
A3: Denmark | B3: Maersk | C3: 2 | D3: Copenhagen | E3: Shipping | F3: Container Shipping & Logistics | G3: Public | H3: 1904 | I3: Verification Pending | J3: https://www.maersk.com | K3: World's largest container shipping and logistics company. | L3: World's largest container shipping and logistics company | M3: Nasdaq Copenhagen | N3: MAERSK-B | O3: Verification Pending | P3: Verification Pending | Q3: Verification Pending | R3: Verification Pending | S3: N/A | T3: Company knowledge base (stable facts) | U3: Needs financial/leadership verification | V3: 2026-07-18
A4: Denmark | B4: Orsted | C4: 3 | D4: Fredericia | E4: Renewable Energy | F4: Offshore Wind Power | G4: Public | H4: 2006 | I4: Verification Pending | J4: https://orsted.com | K4: World's largest offshore wind farm developer. | L4: World's largest offshore wind farm developer | M4: Nasdaq Copenhagen | N4: ORSTED | O4: Verification Pending | P4: Verification Pending | Q4: Verification Pending | R4: Verification Pending | S4: N/A | T4: Company knowledge base (stable facts) | U4: Needs financial/leadership verification | V4: 2026-07-18
A5: Denmark | B5: Danske Bank | C5: 4 | D5: Copenhagen | E5: Banking | F5: Financial Services | G5: Public | H5: 1871 | I5: Verification Pending | J5: https://www.danskebank.com | K5: Denmark's largest bank. | L5: Denmark's largest bank | M5: Nasdaq Copenhagen | N5: DANSKE | O5: Verification Pending | P5: Verification Pending | Q5: Verification Pending | R5: Verification Pending | S5: N/A | T5: Company knowledge base (stable facts) | U5: Needs financial/leadership verification | V5: 2026-07-18
A6: Denmark | B6: Carlsberg Group | C6: 5 | D6: Copenhagen | E6: Beverages | F6: Brewing | G6: Public | H6: 1847 | I6: Verification Pending | J6: https://www.carlsberggroup.com | K6: World's third-largest brewery group. | L6: World's third-largest brewery group | M6: Nasdaq Copenhagen | N6: CARL-B | O6: Verification Pending | P6: Verification Pending | Q6: Verification Pending | R6: Verification Pending | S6: N/A | T6: Company knowledge base (stable facts) | U6: Needs financial/leadership verification | V6: 2026-07-18
A8: Note: | B8: Company identity, industry, HQ, founding year, and website are stable facts. 'Verification Pending' fields (CEO, revenue, net income, market cap, Fortune 500 rank) change frequently and require a live data-verification pass before use in analysis.

Sheet Bangladesh
A1: Rank | B1: Company Name | C1: Country | D1: HQ City | E1: Industry | F1: Sector | G1: Company Type | H1: Founded Year | I1: CEO | J1: Official Website | K1: Business Description | L1: Main Products/Services | M1: Stock Exchange | N1: Ticker Symbol | O1: Annual Revenue (USD) | P1: Net Income (USD) | Q1: Market Cap (USD) | R1: Fortune Global 500 Rank | S1: Parent Company | T1: Data Source | U1: Verification Status | V1: Last Updated
A2: Bangladesh | B2: Square Group | C2: 1 | D2: Dhaka | E2: Pharmaceuticals/Conglomerate | F2: Pharma & Consumer Goods | G2: Public | H2: 1958 | I2: Verification Pending | J2: https://www.squaregroup.com | K2: Bangladesh's largest pharmaceutical company and diversified conglomerate. | L2: Bangladesh's largest pharmaceutical company and diversified conglomerate | M2: DSE (Square Pharma listed) | N2: SQURPHARMA | O2: Verification Pending | P2: Verification Pending | Q2: Verification Pending | R2: Verification Pending | S2: N/A | T2: Company knowledge base (stable facts) | U2: Needs financial/leadership verification | V2: 2026-07-18
A3: Bangladesh | B3: Beximco Group | C3: 2 | D3: Dhaka | E3: Conglomerate | F3: Pharma, Textiles & Energy | G3: Public | H3: 1972 | I3: Verification Pending | J3: https://www.beximco.com | K3: One of Bangladesh's largest diversified conglomerates. | L3: One of Bangladesh's largest diversified conglomerates | M3: DSE | N3: BEXIMCO | O3: Verification Pending | P3: Verification Pending | Q3: Verification Pending | R3: Verification Pending | S3: N/A | T3: Company knowledge base (stable facts) | U3: Needs financial/leadership verification | V3: 2026-07-18
A4: Bangladesh | B4: Grameenphone | C4: 3 | D4: Dhaka | E4: Telecommunications | F4: Telecom Services | G4: Public | H4: 1996 | I4: Verification Pending | J4: https://www.grameenphone.com | K4: Bangladesh's largest mobile telecom operator. | L4: Bangladesh's largest mobile telecom operator | M4: DSE | N4: GRAMEENPHONE | O4: Verification Pending | P4: Verification Pending | Q4: Verification Pending | R4: Verification Pending | S4: N/A | T4: Company knowledge base (stable facts) | U4: Needs financial/leadership verification | V4: 2026-07-18
A5: Bangladesh | B5: Islami Bank Bangladesh | C5: 4 | D5: Dhaka | E5: Banking | F5: Financial Services | G5: Public | H5: 1983 | I5: Verification Pending | J5: https://www.islamibankbd.com | K5: Bangladesh's largest Islamic bank. | L5: Bangladesh's largest Islamic bank | M5: DSE | N5: ISLAMIBANK | O5: Verification Pending | P5: Verification Pending | Q5: Verification Pending | R5: Verification Pending | S5: N/A | T5: Company knowledge base (stable facts) | U5: Needs financial/leadership verification | V5: 2026-07-18
A6: Bangladesh | B6: BSRM Group | C6: 5 | D6: Chattogram | E6: Steel | F6: Steel Manufacturing | G6: Public | H6: 1952 | I6: Verification Pending | J6: https://bsrm.com | K6: Bangladesh's leading steel manufacturer. | L6: Bangladesh's leading steel manufacturer | M6: DSE (BSRM Steels listed) | N6: BSRMSTEEL | O6: Verification Pending | P6: Verification Pending | Q6: Verification Pending | R6: Verification Pending | S6: N/A | T6: Company knowledge base (stable facts) | U6: Needs financial/leadership verification | V6: 2026-07-18
A8: Note: | B8: Company identity, industry, HQ, founding year, and website are stable facts. 'Verification Pending' fields (CEO, revenue, net income, market cap, Fortune 500 rank) change frequently and require a live data-verification pass before use in analysis.

Sheet Vietnam
A1: Rank | B1: Company Name | C1: Country | D1: HQ City | E1: Industry | F1: Sector | G1: Company Type | H1: Founded Year | I1: CEO | J1: Official Website | K1: Business Description | L1: Main Products/Services | M1: Stock Exchange | N1: Ticker Symbol | O1: Annual Revenue (USD) | P1: Net Income (USD) | Q1: Market Cap (USD) | R1: Fortune Global 500 Rank | S1: Parent Company | T1: Data Source | U1: Verification Status | V1: Last Updated
A2: Vietnam | B2: Vingroup | C2: 1 | D2: Hanoi | E2: Conglomerate | F2: Real Estate, Retail & Automotive | G2: Public | H2: 1993 | I2: Verification Pending | J2: https://www.vingroup.net | K2: Vietnam's largest private conglomerate, spans property to EV manufacturing (VinFast). | L2: Vietnam's largest private conglomerate, spans property to EV manufacturing (VinFast) | M2: HOSE | N2: VIC | O2: Verification Pending | P2: Verification Pending | Q2: Verification Pending | R2: Verification Pending | S2: N/A | T2: Company knowledge base (stable facts) | U2: Needs financial/leadership verification | V2: 2026-07-18
A3: Vietnam | B3: Vietcombank | C3: 2 | D3: Hanoi | E3: Banking | F3: Financial Services | G3: State-Owned | H3: 1963 | I3: Verification Pending | J3: https://www.vietcombank.com.vn | K3: Vietnam's largest bank by market capitalization. | L3: Vietnam's largest bank by market capitalization | M3: HOSE | N3: VCB | O3: Verification Pending | P3: Verification Pending | Q3: Verification Pending | R3: Verification Pending | S3: N/A | T3: Company knowledge base (stable facts) | U3: Needs financial/leadership verification | V3: 2026-07-18
A4: Vietnam | B4: PetroVietnam | C4: 3 | D4: Hanoi | E4: Oil & Gas | F4: Energy | G4: State-Owned | H4: 1977 | I4: Verification Pending | J4: https://www.pvn.vn | K4: Vietnam's state-owned oil and gas corporation. | L4: Vietnam's state-owned oil and gas corporation | M4: State-owned | N4: N/A | O4: Verification Pending | P4: Verification Pending | Q4: Verification Pending | R4: Verification Pending | S4: N/A | T4: Company knowledge base (stable facts) | U4: Needs financial/leadership verification | V4: 2026-07-18
A5: Vietnam | B5: Viettel Group | C5: 4 | D5: Hanoi | E5: Telecommunications | F5: Telecom Services | G5: State-Owned | H5: 1989 | I5: Verification Pending | J5: https://www.viettel.com.vn | K5: Vietnam's largest telecom operator, military-owned. | L5: Vietnam's largest telecom operator, military-owned | M5: State-owned (military-run) | N5: N/A | O5: Verification Pending | P5: Verification Pending | Q5: Verification Pending | R5: Verification Pending | S5: N/A | T5: Company knowledge base (stable facts) | U5: Needs financial/leadership verification | V5: 2026-07-18
A6: Vietnam | B6: Hoa Phat Group | C6: 5 | D6: Hanoi | E6: Steel | F6: Steel Manufacturing | G6: Public | H6: 1992 | I6: Verification Pending | J6: https://www.hoaphat.com.vn | K6: Vietnam's largest steel producer. | L6: Vietnam's largest steel producer | M6: HOSE | N6: HPG | O6: Verification Pending | P6: Verification Pending | Q6: Verification Pending | R6: Verification Pending | S6: N/A | T6: Company knowledge base (stable facts) | U6: Needs financial/leadership verification | V6: 2026-07-18
A8: Note: | B8: Company identity, industry, HQ, founding year, and website are stable facts. 'Verification Pending' fields (CEO, revenue, net income, market cap, Fortune 500 rank) change frequently and require a live data-verification pass before use in analysis.

Sheet Colombia
A1: Rank | B1: Company Name | C1: Country | D1: HQ City | E1: Industry | F1: Sector | G1: Company Type | H1: Founded Year | I1: CEO | J1: Official Website | K1: Business Description | L1: Main Products/Services | M1: Stock Exchange | N1: Ticker Symbol | O1: Annual Revenue (USD) | P1: Net Income (USD) | Q1: Market Cap (USD) | R1: Fortune Global 500 Rank | S1: Parent Company | T1: Data Source | U1: Verification Status | V1: Last Updated
A2: Colombia | B2: Ecopetrol | C2: 1 | D2: Bogota | E2: Oil & Gas | F2: Energy | G2: State-Controlled | H2: 1951 | I2: Verification Pending | J2: https://www.ecopetrol.com.co | K2: Colombia's largest oil and gas company. | L2: Colombia's largest oil and gas company | M2: BVC/NYSE | N2: ECOPETROL | O2: Verification Pending | P2: Verification Pending | Q2: Verification Pending | R2: Verification Pending | S2: N/A | T2: Company knowledge base (stable facts) | U2: Needs financial/leadership verification | V2: 2026-07-18
A3: Colombia | B3: Grupo Bancolombia | C3: 2 | D3: Medellin | E3: Banking | F3: Financial Services | G3: Public | H3: 1875 | I3: Verification Pending | J3: https://www.grupobancolombia.com | K3: Colombia's largest bank. | L3: Colombia's largest bank | M3: BVC/NYSE | N3: BCOLOMBIA | O3: Verification Pending | P3: Verification Pending | Q3: Verification Pending | R3: Verification Pending | S3: N/A | T3: Company knowledge base (stable facts) | U3: Needs financial/leadership verification | V3: 2026-07-18
A4: Colombia | B4: Grupo Argos | C4: 3 | D4: Medellin | E4: Construction | F4: Cement & Infrastructure | G4: Public | H4: 1934 | I4: Verification Pending | J4: https://www.grupoargos.com | K4: Major Colombian conglomerate in cement, energy, and infrastructure. | L4: Major Colombian conglomerate in cement, energy, and infrastructure | M4: BVC | N4: GRUPOARGOS | O4: Verification Pending | P4: Verification Pending | Q4: Verification Pending | R4: Verification Pending | S4: N/A | T4: Company knowledge base (stable facts) | U4: Needs financial/leadership verification | V4: 2026-07-18
A5: Colombia | B5: Grupo Exito | C5: 4 | D5: Envigado | E5: Retail | F5: Grocery & General Retail | G5: Public | H5: 1949 | I5: Verification Pending | J5: https://www.grupoexito.com.co | K5: Colombia's largest retail chain. | L5: Colombia's largest retail chain | M5: BVC | N5: EXITO | O5: Verification Pending | P5: Verification Pending | Q5: Verification Pending | R5: Verification Pending | S5: N/A | T5: Company knowledge base (stable facts) | U5: Needs financial/leadership verification | V5: 2026-07-18
A6: Colombia | B6: ISA (Interconexion Electrica) | C6: 5 | D6: Medellin | E6: Utilities | F6: Electric Power Transmission | G6: State-Controlled | H6: 1967 | I6: Verification Pending | J6: https://www.isa.co | K6: Major Latin American electricity transmission company. | L6: Major Latin American electricity transmission company | M6: BVC | N6: ISA | O6: Verification Pending | P6: Verification Pending | Q6: Verification Pending | R6: Verification Pending | S6: N/A | T6: Company knowledge base (stable facts) | U6: Needs financial/leadership verification | V6: 2026-07-18
A8: Note: | B8: Company identity, industry, HQ, founding year, and website are stable facts. 'Verification Pending' fields (CEO, revenue, net income, market cap, Fortune 500 rank) change frequently and require a live data-verification pass before use in analysis.

Sheet Chile
A1: Rank | B1: Company Name | C1: Country | D1: HQ City | E1: Industry | F1: Sector | G1: Company Type | H1: Founded Year | I1: CEO | J1: Official Website | K1: Business Description | L1: Main Products/Services | M1: Stock Exchange | N1: Ticker Symbol | O1: Annual Revenue (USD) | P1: Net Income (USD) | Q1: Market Cap (USD) | R1: Fortune Global 500 Rank | S1: Parent Company | T1: Data Source | U1: Verification Status | V1: Last Updated
A2: Chile | B2: Codelco | C2: 1 | D2: Santiago | E2: Mining | F2: Copper Mining | G2: State-Owned | H2: 1976 | I2: Verification Pending | J2: https://www.codelco.com | K2: World's largest copper producer. | L2: World's largest copper producer | M2: State-owned | N2: N/A | O2: Verification Pending | P2: Verification Pending | Q2: Verification Pending | R2: Verification Pending | S2: N/A | T2: Company knowledge base (stable facts) | U2: Needs financial/leadership verification | V2: 2026-07-18
A3: Chile | B3: Banco de Chile | C3: 2 | D3: Santiago | E3: Banking | F3: Financial Services | G3: Public | H3: 1893 | I3: Verification Pending | J3: https://www.bancochile.cl | K3: One of Chile's largest banks. | L3: One of Chile's largest banks | M3: BCS/NYSE | N3: CHILE | O3: Verification Pending | P3: Verification Pending | Q3: Verification Pending | R3: Verification Pending | S3: N/A | T3: Company knowledge base (stable facts) | U3: Needs financial/leadership verification | V3: 2026-07-18
A4: Chile | B4: Empresas CMPC | C4: 3 | D4: Santiago | E4: Forestry/Paper | F4: Pulp & Paper | G4: Public | H4: 1920 | I4: Verification Pending | J4: https://www.cmpc.com | K4: Major Latin American pulp, paper, and tissue producer. | L4: Major Latin American pulp, paper, and tissue producer | M4: BCS | N4: CMPC | O4: Verification Pending | P4: Verification Pending | Q4: Verification Pending | R4: Verification Pending | S4: N/A | T4: Company knowledge base (stable facts) | U4: Needs financial/leadership verification | V4: 2026-07-18
A5: Chile | B5: LATAM Airlines Group | C5: 4 | D5: Santiago | E5: Aviation | F5: Airlines | G5: Public | H5: 1929 | I5: Verification Pending | J5: https://www.latamairlinesgroup.net | K5: Latin America's largest airline group. | L5: Latin America's largest airline group | M5: BCS/NYSE | N5: LTM | O5: Verification Pending | P5: Verification Pending | Q5: Verification Pending | R5: Verification Pending | S5: N/A | T5: Company knowledge base (stable facts) | U5: Needs financial/leadership verification | V5: 2026-07-18
A6: Chile | B6: SQM (Sociedad Quimica y Minera) | C6: 5 | D6: Santiago | E6: Mining/Chemicals | F6: Lithium & Specialty Chemicals | G6: Public | H6: 1968 | I6: Verification Pending | J6: https://www.sqm.com | K6: World's largest lithium producer. | L6: World's largest lithium producer | M6: BCS/NYSE | N6: SQM | O6: Verification Pending | P6: Verification Pending | Q6: Verification Pending | R6: Verification Pending | S6: N/A | T6: Company knowledge base (stable facts) | U6: Needs financial/leadership verification | V6: 2026-07-18
A8: Note: | B8: Company identity, industry, HQ, founding year, and website are stable facts. 'Verification Pending' fields (CEO, revenue, net income, market cap, Fortune 500 rank) change frequently and require a live data-verification pass before use in analysis.

Sheet Finland
A1: Rank | B1: Company Name | C1: Country | D1: HQ City | E1: Industry | F1: Sector | G1: Company Type | H1: Founded Year | I1: CEO | J1: Official Website | K1: Business Description | L1: Main Products/Services | M1: Stock Exchange | N1: Ticker Symbol | O1: Annual Revenue (USD) | P1: Net Income (USD) | Q1: Market Cap (USD) | R1: Fortune Global 500 Rank | S1: Parent Company | T1: Data Source | U1: Verification Status | V1: Last Updated
A2: Finland | B2: Nokia Corporation | C2: 1 | D2: Espoo | E2: Telecommunications | F2: Networking Equipment | G2: Public | H2: 1865 | I2: Verification Pending | J2: https://www.nokia.com | K2: Major global telecom network infrastructure and technology licensing company. | L2: Major global telecom network infrastructure and technology licensing company | M2: Nasdaq Helsinki/NYSE | N2: NOKIA | O2: Verification Pending | P2: Verification Pending | Q2: Verification Pending | R2: Verification Pending | S2: N/A | T2: Company knowledge base (stable facts) | U2: Needs financial/leadership verification | V2: 2026-07-18
A3: Finland | B3: Neste Corporation | C3: 2 | D3: Espoo | E3: Oil & Gas/Renewables | F3: Renewable Fuels | G3: Public | H3: 1948 | I3: Verification Pending | J3: https://www.neste.com | K3: World's leading producer of renewable diesel and sustainable aviation fuel. | L3: World's leading producer of renewable diesel and sustainable aviation fuel | M3: Nasdaq Helsinki | N3: NESTE | O3: Verification Pending | P3: Verification Pending | Q3: Verification Pending | R3: Verification Pending | S3: N/A | T3: Company knowledge base (stable facts) | U3: Needs financial/leadership verification | V3: 2026-07-18
A4: Finland | B4: Kone Corporation | C4: 3 | D4: Espoo | E4: Industrial Manufacturing | F4: Elevators & Escalators | G4: Public | H4: 1910 | I4: Verification Pending | J4: https://www.kone.com | K4: Global leader in elevator and escalator manufacturing. | L4: Global leader in elevator and escalator manufacturing | M4: Nasdaq Helsinki | N4: KNEBV | O4: Verification Pending | P4: Verification Pending | Q4: Verification Pending | R4: Verification Pending | S4: N/A | T4: Company knowledge base (stable facts) | U4: Needs financial/leadership verification | V4: 2026-07-18
A5: Finland | B5: UPM-Kymmene | C5: 4 | D5: Helsinki | E5: Forestry | F5: Pulp & Paper | G5: Public | H5: 1996 | I5: Verification Pending | J5: https://www.upm.com | K5: Major global forest products and bio-based materials company. | L5: Major global forest products and bio-based materials company | M5: Nasdaq Helsinki | N5: UPM | O5: Verification Pending | P5: Verification Pending | Q5: Verification Pending | R5: Verification Pending | S5: N/A | T5: Company knowledge base (stable facts) | U5: Needs financial/leadership verification | V5: 2026-07-18
A6: Finland | B6: Nordea Bank | C6: 5 | D6: Helsinki | E6: Banking | F6: Financial Services | G6: Public | H6: 1820 | I6: Verification Pending | J6: https://www.nordea.com | K6: Largest financial services group in the Nordic region. | L6: Largest financial services group in the Nordic region | M6: Nasdaq Helsinki | N6: NDA-FI | O6: Verification Pending | P6: Verification Pending | Q6: Verification Pending | R6: Verification Pending | S6: N/A | T6: Company knowledge base (stable facts) | U6: Needs financial/leadership verification | V6: 2026-07-18
A8: Note: | B8: Company identity, industry, HQ, founding year, and website are stable facts. 'Verification Pending' fields (CEO, revenue, net income, market cap, Fortune 500 rank) change frequently and require a live data-verification pass before use in analysis.

Sheet Romania
A1: Rank | B1: Company Name | C1: Country | D1: HQ City | E1: Industry | F1: Sector | G1: Company Type | H1: Founded Year | I1: CEO | J1: Official Website | K1: Business Description | L1: Main Products/Services | M1: Stock Exchange | N1: Ticker Symbol | O1: Annual Revenue (USD) | P1: Net Income (USD) | Q1: Market Cap (USD) | R1: Fortune Global 500 Rank | S1: Parent Company | T1: Data Source | U1: Verification Status | V1: Last Updated
A2: Romania | B2: OMV Petrom | C2: 1 | D2: Bucharest | E2: Oil & Gas | F2: Energy | G2: Public | H2: 1997 | I2: Verification Pending | J2: https://www.omvpetrom.com | K2: Romania's largest oil and gas producer. | L2: Romania's largest oil and gas producer | M2: BVB | N2: SNP | O2: Verification Pending | P2: Verification Pending | Q2: Verification Pending | R2: Verification Pending | S2: N/A | T2: Company knowledge base (stable facts) | U2: Needs financial/leadership verification | V2: 2026-07-18
A3: Romania | B3: Romgaz | C3: 2 | D3: Medias | E3: Oil & Gas | F3: Natural Gas Production | G3: State-Owned | H3: 2001 | I3: Verification Pending | J3: https://www.romgaz.ro | K3: Romania's largest natural gas producer. | L3: Romania's largest natural gas producer | M3: BVB | N3: SNG | O3: Verification Pending | P3: Verification Pending | Q3: Verification Pending | R3: Verification Pending | S3: N/A | T3: Company knowledge base (stable facts) | U3: Needs financial/leadership verification | V3: 2026-07-18
A4: Romania | B4: Banca Transilvania | C4: 3 | D4: Cluj-Napoca | E4: Banking | F4: Financial Services | G4: Public | H4: 1993 | I4: Verification Pending | J4: https://www.bancatransilvania.ro | K4: Romania's largest bank by assets. | L4: Romania's largest bank by assets | M4: BVB | N4: TLV | O4: Verification Pending | P4: Verification Pending | Q4: Verification Pending | R4: Verification Pending | S4: N/A | T4: Company knowledge base (stable facts) | U4: Needs financial/leadership verification | V4: 2026-07-18
A5: Romania | B5: Hidroelectrica | C5: 4 | D5: Bucharest | E5: Utilities | F5: Hydroelectric Power | G5: State-Owned | H5: 2000 | I5: Verification Pending | J5: https://www.hidroelectrica.ro | K5: Romania's largest electricity producer, hydropower focused. | L5: Romania's largest electricity producer, hydropower focused | M5: BVB | N5: H2O | O5: Verification Pending | P5: Verification Pending | Q5: Verification Pending | R5: Verification Pending | S5: N/A | T5: Company knowledge base (stable facts) | U5: Needs financial/leadership verification | V5: 2026-07-18
A6: Romania | B6: Electrica | C6: 5 | D6: Bucharest | E6: Utilities | F6: Electric Power Distribution | G6: Public | H6: 1998 | I6: Verification Pending | J6: https://www.electrica.ro | K6: Major Romanian electricity distribution company. | L6: Major Romanian electricity distribution company | M6: BVB | N6: EL | O6: Verification Pending | P6: Verification Pending | Q6: Verification Pending | R6: Verification Pending | S6: N/A | T6: Company knowledge base (stable facts) | U6: Needs financial/leadership verification | V6: 2026-07-18
A8: Note: | B8: Company identity, industry, HQ, founding year, and website are stable facts. 'Verification Pending' fields (CEO, revenue, net income, market cap, Fortune 500 rank) change frequently and require a live data-verification pass before use in analysis.

Sheet Czech Republic
A1: Rank | B1: Company Name | C1: Country | D1: HQ City | E1: Industry | F1: Sector | G1: Company Type | H1: Founded Year | I1: CEO | J1: Official Website | K1: Business Description | L1: Main Products/Services | M1: Stock Exchange | N1: Ticker Symbol | O1: Annual Revenue (USD) | P1: Net Income (USD) | Q1: Market Cap (USD) | R1: Fortune Global 500 Rank | S1: Parent Company | T1: Data Source | U1: Verification Status | V1: Last Updated
A2: Czech Republic | B2: CEZ Group | C2: 1 | D2: Prague | E2: Utilities | F2: Electric Power | G2: State-Controlled | H2: 1992 | I2: Verification Pending | J2: https://www.cez.cz | K2: Central Europe's largest electricity generator. | L2: Central Europe's largest electricity generator | M2: PSE | N2: CEZ | O2: Verification Pending | P2: Verification Pending | Q2: Verification Pending | R2: Verification Pending | S2: N/A | T2: Company knowledge base (stable facts) | U2: Needs financial/leadership verification | V2: 2026-07-18
A3: Czech Republic | B3: Komercni Banka | C3: 2 | D3: Prague | E3: Banking | F3: Financial Services | G3: Public | H3: 1990 | I3: Verification Pending | J3: https://www.kb.cz | K3: Major Czech commercial bank. | L3: Major Czech commercial bank | M3: PSE | N3: KOMB | O3: Verification Pending | P3: Verification Pending | Q3: Verification Pending | R3: Verification Pending | S3: N/A | T3: Company knowledge base (stable facts) | U3: Needs financial/leadership verification | V3: 2026-07-18
A4: Czech Republic | B4: Ceska sporitelna | C4: 3 | D4: Prague | E4: Banking | F4: Financial Services | G4: Public | H4: 1825 | I4: Verification Pending | J4: https://www.csas.cz | K4: One of the Czech Republic's largest retail banks. | L4: One of the Czech Republic's largest retail banks | M4: Subsidiary of Erste Group | N4: N/A | O4: Verification Pending | P4: Verification Pending | Q4: Verification Pending | R4: Verification Pending | S4: N/A | T4: Company knowledge base (stable facts) | U4: Needs financial/leadership verification | V4: 2026-07-18
A5: Czech Republic | B5: Skoda Auto | C5: 4 | D5: Mlada Boleslav | E5: Automotive | F5: Auto Manufacturing | G5: Public (VW subsidiary) | H5: 1895 | I5: Verification Pending | J5: https://www.skoda-auto.com | K5: Major automaker, part of the Volkswagen Group. | L5: Major automaker, part of the Volkswagen Group | M5: Subsidiary of Volkswagen | N5: N/A | O5: Verification Pending | P5: Verification Pending | Q5: Verification Pending | R5: Verification Pending | S5: N/A | T5: Company knowledge base (stable facts) | U5: Needs financial/leadership verification | V5: 2026-07-18
A6: Czech Republic | B6: EPH (Energeticky a prumyslovy holding) | C6: 5 | D6: Prague | E6: Energy | F6: Energy Infrastructure | G6: Private | H6: 2009 | I6: Verification Pending | J6: https://www.epholding.cz | K6: Major Central European energy infrastructure holding. | L6: Major Central European energy infrastructure holding | M6: Private | N6: N/A | O6: Verification Pending | P6: Verification Pending | Q6: Verification Pending | R6: Verification Pending | S6: N/A | T6: Company knowledge base (stable facts) | U6: Needs financial/leadership verification | V6: 2026-07-18
A8: Note: | B8: Company identity, industry, HQ, founding year, and website are stable facts. 'Verification Pending' fields (CEO, revenue, net income, market cap, Fortune 500 rank) change frequently and require a live data-verification pass before use in analysis.

Sheet Portugal
A1: Rank | B1: Company Name | C1: Country | D1: HQ City | E1: Industry | F1: Sector | G1: Company Type | H1: Founded Year | I1: CEO | J1: Official Website | K1: Business Description | L1: Main Products/Services | M1: Stock Exchange | N1: Ticker Symbol | O1: Annual Revenue (USD) | P1: Net Income (USD) | Q1: Market Cap (USD) | R1: Fortune Global 500 Rank | S1: Parent Company | T1: Data Source | U1: Verification Status | V1: Last Updated
A2: Portugal | B2: Galp Energia | C2: 1 | D2: Lisbon | E2: Oil & Gas | F2: Energy | G2: Public | H2: 1999 | I2: Verification Pending | J2: https://www.galp.com | K2: Portugal's largest integrated energy company. | L2: Portugal's largest integrated energy company | M2: Euronext Lisbon | N2: GALP | O2: Verification Pending | P2: Verification Pending | Q2: Verification Pending | R2: Verification Pending | S2: N/A | T2: Company knowledge base (stable facts) | U2: Needs financial/leadership verification | V2: 2026-07-18
A3: Portugal | B3: EDP - Energias de Portugal | C3: 2 | D3: Lisbon | E3: Utilities | F3: Electric Power & Renewables | G3: Public | H3: 1976 | I3: Verification Pending | J3: https://www.edp.com | K3: Major utility and one of the world's largest wind energy producers. | L3: Major utility and one of the world's largest wind energy producers | M3: Euronext Lisbon | N3: EDP | O3: Verification Pending | P3: Verification Pending | Q3: Verification Pending | R3: Verification Pending | S3: N/A | T3: Company knowledge base (stable facts) | U3: Needs financial/leadership verification | V3: 2026-07-18
A4: Portugal | B4: Jeronimo Martins | C4: 3 | D4: Lisbon | E4: Retail | F4: Grocery Retail | G4: Public | H4: 1792 | I4: Verification Pending | J4: https://www.jeronimomartins.com | K4: Major food distribution group operating in Portugal, Poland, and Colombia. | L4: Major food distribution group operating in Portugal, Poland, and Colombia | M4: Euronext Lisbon | N4: JMT | O4: Verification Pending | P4: Verification Pending | Q4: Verification Pending | R4: Verification Pending | S4: N/A | T4: Company knowledge base (stable facts) | U4: Needs financial/leadership verification | V4: 2026-07-18
A5: Portugal | B5: Millennium bcp | C5: 4 | D5: Lisbon | E5: Banking | F5: Financial Services | G5: Public | H5: 1985 | I5: Verification Pending | J5: https://ind.millenniumbcp.pt | K5: Portugal's largest privately-owned bank. | L5: Portugal's largest privately-owned bank | M5: Euronext Lisbon | N5: BCP | O5: Verification Pending | P5: Verification Pending | Q5: Verification Pending | R5: Verification Pending | S5: N/A | T5: Company knowledge base (stable facts) | U5: Needs financial/leadership verification | V5: 2026-07-18
A6: Portugal | B6: Sonae | C6: 5 | D6: Maia | E6: Conglomerate | F6: Retail & Real Estate | G6: Public | H6: 1959 | I6: Verification Pending | J6: https://www.sonae.pt | K6: Major diversified Portuguese conglomerate in retail and technology. | L6: Major diversified Portuguese conglomerate in retail and technology | M6: Euronext Lisbon | N6: SON | O6: Verification Pending | P6: Verification Pending | Q6: Verification Pending | R6: Verification Pending | S6: N/A | T6: Company knowledge base (stable facts) | U6: Needs financial/leadership verification | V6: 2026-07-18
A8: Note: | B8: Company identity, industry, HQ, founding year, and website are stable facts. 'Verification Pending' fields (CEO, revenue, net income, market cap, Fortune 500 rank) change frequently and require a live data-verification pass before use in analysis.

Sheet Peru
A1: Rank | B1: Company Name | C1: Country | D1: HQ City | E1: Industry | F1: Sector | G1: Company Type | H1: Founded Year | I1: CEO | J1: Official Website | K1: Business Description | L1: Main Products/Services | M1: Stock Exchange | N1: Ticker Symbol | O1: Annual Revenue (USD) | P1: Net Income (USD) | Q1: Market Cap (USD) | R1: Fortune Global 500 Rank | S1: Parent Company | T1: Data Source | U1: Verification Status | V1: Last Updated
A2: Peru | B2: Credicorp | C2: 1 | D2: Lima | E2: Banking | F2: Financial Services | G2: Public | H2: 1889 | I2: Verification Pending | J2: https://www.credicorp.com | K2: Peru's largest financial services holding company. | L2: Peru's largest financial services holding company | M2: BVL/NYSE | N2: BAP | O2: Verification Pending | P2: Verification Pending | Q2: Verification Pending | R2: Verification Pending | S2: N/A | T2: Company knowledge base (stable facts) | U2: Needs financial/leadership verification | V2: 2026-07-18
A3: Peru | B3: Southern Copper Corporation | C3: 2 | D3: Lima | E3: Mining | F3: Copper Mining | G3: Public | H3: 1952 | I3: Verification Pending | J3: https://www.southerncoppercorp.com | K3: One of the world's largest integrated copper producers. | L3: One of the world's largest integrated copper producers | M3: BVL/NYSE | N3: SCCO | O3: Verification Pending | P3: Verification Pending | Q3: Verification Pending | R3: Verification Pending | S3: N/A | T3: Company knowledge base (stable facts) | U3: Needs financial/leadership verification | V3: 2026-07-18
A4: Peru | B4: Buenaventura | C4: 3 | D4: Lima | E4: Mining | F4: Precious Metals Mining | G4: Public | H4: 1953 | I4: Verification Pending | J4: https://www.buenaventura.com | K4: Peru's largest publicly traded precious metals mining company. | L4: Peru's largest publicly traded precious metals mining company | M4: BVL/NYSE | N4: BVN | O4: Verification Pending | P4: Verification Pending | Q4: Verification Pending | R4: Verification Pending | S4: N/A | T4: Company knowledge base (stable facts) | U4: Needs financial/leadership verification | V4: 2026-07-18
A5: Peru | B5: Alicorp | C5: 4 | D5: Lima | E5: Food & Beverage | F5: Consumer Goods | G5: Public | H5: 1956 | I5: Verification Pending | J5: https://www.alicorp.com.pe | K5: Peru's leading consumer goods manufacturer. | L5: Peru's leading consumer goods manufacturer | M5: BVL | N5: ALICORC1 | O5: Verification Pending | P5: Verification Pending | Q5: Verification Pending | R5: Verification Pending | S5: N/A | T5: Company knowledge base (stable facts) | U5: Needs financial/leadership verification | V5: 2026-07-18
A6: Peru | B6: Grupo Romero (Intercorp affiliated) | C6: 5 | D6: Lima | E6: Conglomerate | F6: Diversified Industrial | G6: Private | H6: 1958 | I6: Verification Pending | J6: https://www.grupo-romero.com | K6: One of Peru's oldest and largest business conglomerates. | L6: One of Peru's oldest and largest business conglomerates | M6: Private/Public subsidiaries | N6: N/A | O6: Verification Pending | P6: Verification Pending | Q6: Verification Pending | R6: Verification Pending | S6: N/A | T6: Company knowledge base (stable facts) | U6: Needs financial/leadership verification | V6: 2026-07-18
A8: Note: | B8: Company identity, industry, HQ, founding year, and website are stable facts. 'Verification Pending' fields (CEO, revenue, net income, market cap, Fortune 500 rank) change frequently and require a live data-verification pass before use in analysis.

Sheet New Zealand
A1: Rank | B1: Company Name | C1: Country | D1: HQ City | E1: Industry | F1: Sector | G1: Company Type | H1: Founded Year | I1: CEO | J1: Official Website | K1: Business Description | L1: Main Products/Services | M1: Stock Exchange | N1: Ticker Symbol | O1: Annual Revenue (USD) | P1: Net Income (USD) | Q1: Market Cap (USD) | R1: Fortune Global 500 Rank | S1: Parent Company | T1: Data Source | U1: Verification Status | V1: Last Updated
A2: New Zealand | B2: Fonterra Co-operative Group | C2: 1 | D2: Auckland | E2: Food & Beverage | F2: Dairy | G2: Cooperative | H2: 2001 | I2: Verification Pending | J2: https://www.fonterra.com | K2: World's largest dairy exporter, farmer-owned cooperative. | L2: World's largest dairy exporter, farmer-owned cooperative | M2: NZX (units) | N2: FCG | O2: Verification Pending | P2: Verification Pending | Q2: Verification Pending | R2: Verification Pending | S2: N/A | T2: Company knowledge base (stable facts) | U2: Needs financial/leadership verification | V2: 2026-07-18
A3: New Zealand | B3: Fisher & Paykel Healthcare | C3: 2 | D3: Auckland | E3: Healthcare | F3: Medical Devices | G3: Public | H3: 1934 | I3: Verification Pending | J3: https://www.fphcare.com | K3: Global leader in respiratory and acute care medical devices. | L3: Global leader in respiratory and acute care medical devices | M3: NZX/ASX | N3: FPH | O3: Verification Pending | P3: Verification Pending | Q3: Verification Pending | R3: Verification Pending | S3: N/A | T3: Company knowledge base (stable facts) | U3: Needs financial/leadership verification | V3: 2026-07-18
A4: New Zealand | B4: Auckland International Airport | C4: 3 | D4: Auckland | E4: Aviation/Infrastructure | F4: Airport Operations | G4: Public | H4: 1966 | I4: Verification Pending | J4: https://www.aucklandairport.co.nz | K4: New Zealand's largest international airport. | L4: New Zealand's largest international airport | M4: NZX | N4: AIA | O4: Verification Pending | P4: Verification Pending | Q4: Verification Pending | R4: Verification Pending | S4: N/A | T4: Company knowledge base (stable facts) | U4: Needs financial/leadership verification | V4: 2026-07-18
A5: New Zealand | B5: ANZ Bank New Zealand | C5: 4 | D5: Auckland | E5: Banking | F5: Financial Services | G5: Public (subsidiary) | H5: 1840 | I5: Verification Pending | J5: https://www.anz.co.nz | K5: New Zealand's largest bank by assets. | L5: New Zealand's largest bank by assets | M5: Subsidiary of ANZ Group (ASX) | N5: N/A | O5: Verification Pending | P5: Verification Pending | Q5: Verification Pending | R5: Verification Pending | S5: N/A | T5: Company knowledge base (stable facts) | U5: Needs financial/leadership verification | V5: 2026-07-18
A6: New Zealand | B6: Spark New Zealand | C6: 5 | D6: Auckland | E6: Telecommunications | F6: Telecom Services | G6: Public | H6: 1987 | I6: Verification Pending | J6: https://www.sparknz.co.nz | K6: New Zealand's largest telecommunications provider. | L6: New Zealand's largest telecommunications provider | M6: NZX/ASX | N6: SPK | O6: Verification Pending | P6: Verification Pending | Q6: Verification Pending | R6: Verification Pending | S6: N/A | T6: Company knowledge base (stable facts) | U6: Needs financial/leadership verification | V6: 2026-07-18
A8: Note: | B8: Company identity, industry, HQ, founding year, and website are stable facts. 'Verification Pending' fields (CEO, revenue, net income, market cap, Fortune 500 rank) change frequently and require a live data-verification pass before use in analysis.

Sheet Iraq
A1: Rank | B1: Company Name | C1: Country | D1: HQ City | E1: Industry | F1: Sector | G1: Company Type | H1: Founded Year | I1: CEO | J1: Official Website | K1: Business Description | L1: Main Products/Services | M1: Stock Exchange | N1: Ticker Symbol | O1: Annual Revenue (USD) | P1: Net Income (USD) | Q1: Market Cap (USD) | R1: Fortune Global 500 Rank | S1: Parent Company | T1: Data Source | U1: Verification Status | V1: Last Updated
A2: Iraq | B2: Iraq National Oil Company | C2: 1 | D2: Baghdad | E2: Oil & Gas | F2: Energy | G2: State-Owned | H2: 2018 | I2: Verification Pending | J2: N/A | K2: Iraq's state oil company overseeing upstream operations. | L2: Iraq's state oil company overseeing upstream operations | M2: State-owned | N2: N/A | O2: Verification Pending | P2: Verification Pending | Q2: Verification Pending | R2: Verification Pending | S2: N/A | T2: Company knowledge base (stable facts) | U2: Needs financial/leadership verification | V2: 2026-07-18
A3: Iraq | B3: Basra Oil Company | C3: 2 | D3: Basra | E3: Oil & Gas | F3: Energy | G3: State-Owned | H3: 1987 | I3: Verification Pending | J3: N/A | K3: State operator of Iraq's major southern oil fields. | L3: State operator of Iraq's major southern oil fields | M3: State-owned | N3: N/A | O3: Verification Pending | P3: Verification Pending | Q3: Verification Pending | R3: Verification Pending | S3: N/A | T3: Company knowledge base (stable facts) | U3: Needs financial/leadership verification | V3: 2026-07-18
A4: Iraq | B4: Bank of Baghdad | C4: 3 | D4: Baghdad | E4: Banking | F4: Financial Services | G4: Public | H4: 1992 | I4: Verification Pending | J4: https://bankofbaghdad.com | K4: One of Iraq's leading private commercial banks. | L4: One of Iraq's leading private commercial banks | M4: ISX | N4: BBOB | O4: Verification Pending | P4: Verification Pending | Q4: Verification Pending | R4: Verification Pending | S4: N/A | T4: Company knowledge base (stable facts) | U4: Needs financial/leadership verification | V4: 2026-07-18
A5: Iraq | B5: Asiacell | C5: 4 | D5: Sulaymaniyah | E5: Telecommunications | F5: Telecom Services | G5: Public | H5: 2000 | I5: Verification Pending | J5: https://asiacell.com | K5: Iraq's largest mobile telecom operator. | L5: Iraq's largest mobile telecom operator | M5: ISX | N5: TASC | O5: Verification Pending | P5: Verification Pending | Q5: Verification Pending | R5: Verification Pending | S5: N/A | T5: Company knowledge base (stable facts) | U5: Needs financial/leadership verification | V5: 2026-07-18
A6: Iraq | B6: Zain Iraq | C6: 5 | D6: Baghdad | E6: Telecommunications | F6: Telecom Services | G6: Public (subsidiary) | H6: 2003 | I6: Verification Pending | J6: https://iq.zain.com | K6: Major Iraqi mobile telecom operator, part of Kuwait's Zain Group. | L6: Major Iraqi mobile telecom operator, part of Kuwait's Zain Group | M6: Subsidiary of Zain Group (Kuwait) | N6: N/A | O6: Verification Pending | P6: Verification Pending | Q6: Verification Pending | R6: Verification Pending | S6: N/A | T6: Company knowledge base (stable facts) | U6: Needs financial/leadership verification | V6: 2026-07-18
A8: Note: | B8: Company identity, industry, HQ, founding year, and website are stable facts. 'Verification Pending' fields (CEO, revenue, net income, market cap, Fortune 500 rank) change frequently and require a live data-verification pass before use in analysis.

Sheet Qatar
A1: Rank | B1: Company Name | C1: Country | D1: HQ City | E1: Industry | F1: Sector | G1: Company Type | H1: Founded Year | I1: CEO | J1: Official Website | K1: Business Description | L1: Main Products/Services | M1: Stock Exchange | N1: Ticker Symbol | O1: Annual Revenue (USD) | P1: Net Income (USD) | Q1: Market Cap (USD) | R1: Fortune Global 500 Rank | S1: Parent Company | T1: Data Source | U1: Verification Status | V1: Last Updated
A2: Qatar | B2: QatarEnergy | C2: 1 | D2: Doha | E2: Oil & Gas | F2: Energy | G2: State-Owned | H2: 1974 | I2: Verification Pending | J2: https://www.qatarenergy.qa | K2: Qatar's state-owned oil and the world's largest LNG exporter. | L2: Qatar's state-owned oil and the world's largest LNG exporter | M2: State-owned | N2: N/A | O2: Verification Pending | P2: Verification Pending | Q2: Verification Pending | R2: Verification Pending | S2: N/A | T2: Company knowledge base (stable facts) | U2: Needs financial/leadership verification | V2: 2026-07-18
A3: Qatar | B3: Qatar National Bank (QNB) | C3: 2 | D3: Doha | E3: Banking | F3: Financial Services | G3: Public | H3: 1964 | I3: Verification Pending | J3: https://www.qnb.com | K3: Largest bank in the Middle East and Africa by assets. | L3: Largest bank in the Middle East and Africa by assets | M3: QSE | N3: QNBK | O3: Verification Pending | P3: Verification Pending | Q3: Verification Pending | R3: Verification Pending | S3: N/A | T3: Company knowledge base (stable facts) | U3: Needs financial/leadership verification | V3: 2026-07-18
A4: Qatar | B4: Ooredoo | C4: 3 | D4: Doha | E4: Telecommunications | F4: Telecom Services | G4: Public | H4: 1987 | I4: Verification Pending | J4: https://www.ooredoo.com | K4: Major telecom operator across the Middle East, North Africa, and Southeast Asia. | L4: Major telecom operator across the Middle East, North Africa, and Southeast Asia | M4: QSE | N4: ORDS | O4: Verification Pending | P4: Verification Pending | Q4: Verification Pending | R4: Verification Pending | S4: N/A | T4: Company knowledge base (stable facts) | U4: Needs financial/leadership verification | V4: 2026-07-18
A5: Qatar | B5: Industries Qatar | C5: 4 | D5: Doha | E5: Chemicals/Manufacturing | F5: Petrochemicals & Steel | G5: Public | H5: 2003 | I5: Verification Pending | J5: https://www.iq.com.qa | K5: Major diversified industrial holding in petrochemicals, fertilizers, and steel. | L5: Major diversified industrial holding in petrochemicals, fertilizers, and steel | M5: QSE | N5: IQCD | O5: Verification Pending | P5: Verification Pending | Q5: Verification Pending | R5: Verification Pending | S5: N/A | T5: Company knowledge base (stable facts) | U5: Needs financial/leadership verification | V5: 2026-07-18
A6: Qatar | B6: Qatar Airways | C6: 5 | D6: Doha | E6: Aviation | F6: Airlines | G6: State-Owned | H6: 1993 | I6: Verification Pending | J6: https://www.qatarairways.com | K6: Qatar's state-owned flag carrier, major global airline. | L6: Qatar's state-owned flag carrier, major global airline | M6: State-owned | N6: N/A | O6: Verification Pending | P6: Verification Pending | Q6: Verification Pending | R6: Verification Pending | S6: N/A | T6: Company knowledge base (stable facts) | U6: Needs financial/leadership verification | V6: 2026-07-18
A8: Note: | B8: Company identity, industry, HQ, founding year, and website are stable facts. 'Verification Pending' fields (CEO, revenue, net income, market cap, Fortune 500 rank) change frequently and require a live data-verification pass before use in analysis.
